Workbook

Sheet LEIA-ME
B2: ⚠️ ATENÇÃO – LEIA ANTES DE USAR Esta planilha foi construída para que apenas uma aba seja editada: 👉 “Todas as Funções (Editável)” Todas as demais abas contêm fórmulas e vínculos automáticos. Não altere, não exclua e não renomeie abas, colunas ou fórmulas.
B4: Esta planilha permite a atualização da classificação das Funções Estratégicas sem necessidade de ajustes manuais em cálculos ou fórmulas. Siga rigorosamente as orientações abaixo. 1️⃣ Aba editável Existe apenas uma aba que pode ser editada: 👉 “Todas as Funções (Editável)” É nessa aba que se encontra a lista mais recente de funções mapeadas, construída a partir da coleta manual no SICI de todas as funções até o 3º escalão. 2️⃣ Atualizações estruturais (SICI) Caso haja atualização no SICI: A) De um Órgão já existente - Se apenas houver mudanças em atributos (Área, Escalão, Tipo de Cargo, Nome do Cargo), edite diretamente a linha correspondente. - Se surgirem novas áreas ou funções dentro do órgão, adicione novas linhas ao final das linhas. B) Se for um Órgão novo - Insira as informações das funções ao final da aba. - Verifique se alguma estrutura de órgão existente foi transferida para o novo órgão. - Caso positivo, edite ou exclua as linhas do órgão de origem, conforme o caso. C) Se um Órgão foi extinto Exclua todas as linhas referentes às funções daquele órgão. ⚠️ Importante: não crie novos padrões de nomenclatura. Utilize sempre os nomes institucionais consolidados. Veja o padrão observando outras linhas da tabela. 3️⃣ Preenchimento das colunas I a J Além das informações estruturais, é necessário preencher as colunas I a J, conforme descrito abaixo: - “Gere equipe”: Indica se o ocupante titular daquela função possui equipe sob sua gestão. - “Autonomia para ordenar despesa”: Indica se a função possui competência formal para ordenação de despesa. “Magnitude do Orçamento Gerido”: Deve ser preenchida com as opções 2 a 4 apenas para funções com competência para ordenação de despesa; e titulares de Pasta. Os demais devem ficar com 1. “Poder de decisão sobre o orçamento do órgão”: A resposta “sim” deve ser atribuída apenas às funções regulamentadas pelo RGCAF que possuem poder de decisão sobre a alocação orçamentária, ainda que nem todas atuem como ordenadores formais de despesa.
B6: Para conferir se sua atualização deu certo e a Função foi classificada, confira na coluna "Status da Classificação" da aba "Cálculo". Obs: Na aba "Cálculo" as linhas ou células que estão pintadas na cor amarelo são aquelas que estão com as funções que realizam a importação dos dados e os cálculos.
B8: A metodologia completa do Mapeamento de Funções Estratégicas está documentada em relatório próprio, elaborado pela CDC/FJG, e deve ser consultada em caso de dúvidas conceituais ou revisões metodológicas
B9: Relatório Metodológico do Mapeamento de Funções Estratégicas 2025

Sheet Todas as Funções (Editável)
A1: ID (automático) | B1: Órgão | C1: Escalão (como está na árvore do SICI) | D1: Área (como está no SICI) | E1: Nome do Cargo (como está no SICI) | F1: Tipo de Cargo (deve ser um dos oito tipos) | G1: Área de Negócio (referente à Área) | H1: Macro Área (referente ao órgão) | I1: Gere equipe | J1: Autonomia para ordenar despesa | K1: Magnitude do Orçamento Gerido (apenas para funções com competência para ordenação de despesa e Titulares de Pasta) | L1: Poder de Decisão sobre o Orçamento (funções regulamentadas pelo RGCAF que possuem poder de decisão sobre a alocação orçamentária, ainda que nem todas atuem como ordenadores formais de despesa) | M1: Titular
B2: GBP | C2: 1º | D2: Gabinete do Prefeito | E2: Coordenador Especial do Gabinete do Prefeito | F2: Coordenador(a) | G2: ⚠️ REVISÃO MANUAL (72.26% de Confiança): Técnico-Operacional | H2: Gestão | I2: 2 - Sim | J2: 1 - Não | L2: 1 - Não possui poder de decisão sobre alocação de recursos orçamentários no órgão | M2: Fernando de Menezes Duba
B3: GBP | C3: 2º | D3: Secretaria Geral do CompStat Municipal | E3: Secretário Geral | G3: Administrativo | H3: Gestão | J3: 2 - Sim | L3: 2 - Possui poder de decisão sobre alocação de recursos orçamentários no órgão | M3: Thiago Ramos Dias
B4: GBP | C4: 2º | D4: Assessoria Especial do Gabinete do Prefeito | E4: Assessor Chefe Técnico | F4: Assessor(a) | G4: ⚠️ REVISÃO MANUAL (72.26% de Confiança): Técnico-Operacional | H4: Gestão | I4: 2 - Sim | J4: 1 - Não | L4: 1 - Não possui poder de decisão sobre alocação de recursos orçamentários no órgão | M4: Eduardo Braga Goldenberg
B5: GBP | C5: 2º | D5: Assessoria Técnica de Assuntos Urbanísticos | E5: Assessor Chefe | F5: Assessor(a) | G5: Técnico-Operacional | H5: Gestão | I5: 2 - Sim | J5: 1 - Não | L5: 1 - Não possui poder de decisão sobre alocação de recursos orçamentários no órgão | M5: Maria Madalena Saint Martin de Astacio
B6: GBP | C6: 2º | D6: Assessoria Especial de Estratégia e Políticas Públicas | E6: Assessor Chefe | F6: Assessor(a) | G6: Técnico-Operacional | H6: Gestão | I6: 2 - Sim | J6: 1 - Não | L6: 1 - Não possui poder de decisão sobre alocação de recursos orçamentários no órgão | M6: Guilherme Victor Testoni Boisson
B7: GBP | C7: 2º | D7: Assessoria de Controle de Diligências | E7: Assessor Chefe | F7: Assessor(a) | G7: ⚠️ REVISÃO MANUAL (43.12% de Confiança): Administrativo | H7: Gestão | I7: 2 - Sim | J7: 1 - Não | L7: 1 - Não possui poder de decisão sobre alocação de recursos orçamentários no órgão | M7: Michelle Rodrigues Schinke
B8: GBP | C8: 2º | D8: Assessoria de Estratégias Digitais | E8: Assessor Chefe | F8: Assessor(a) | G8: ⚠️ REVISÃO MANUAL (32.17% de Confiança): Comunicação e Relacionamento com o Cidadão | H8: Gestão | I8: 2 - Sim | J8: 1 - Não | L8: 1 - Não possui poder de decisão sobre alocação de recursos orçamentários no órgão | M8: Lucas Calil Guimarães Silva
B9: GBP | C9: 2º | D9: Assessoria Técnica do Gabinete do Prefeito | E9: Assessor Chefe I | F9: Assessor(a) | G9: Técnico-Operacional | H9: Gestão | I9: 2 - Sim | J9: 1 - Não | L9: 1 - Não possui poder de decisão sobre alocação de recursos orçamentários no órgão | M9: Marcela Odette Ferreira Barboza
B10: GBP | C10: 2º | D10: Assessoria de Apoio Operacional do Gabinete do Prefeito | E10: Assessor Chefe I | F10: Assessor(a) | G10: Técnico-Operacional | H10: Gestão | I10: 2 - Sim | J10: 1 - Não | L10: 1 - Não possui poder de decisão sobre alocação de recursos orçamentários no órgão | M10: Ana Cristina Boldi Fernandes
B11: GBP | C11: 2º | D11: Centro de Operações e Resiliência | E11: Chefe Executivo de Resiliência e Operações | F11: Chefe | G11: Técnico-Operacional | H11: Gestão | I11: 2 - Sim | J11: 1 - Não | L11: 1 - Não possui poder de decisão sobre alocação de recursos orçamentários no órgão | M11: Thiago Curvello Pinto
B12: GBP | C12: 3º | D12: Assessoria de Planejamento e Resiliência | E12: Assessor Chefe | F12: Assessor(a) | G12: Técnico-Operacional | H12: Gestão | I12: 2 - Sim | J12: 1 - Não | L12: 1 - Não possui poder de decisão sobre alocação de recursos orçamentários no órgão | M12: Ana Carla Badaró Moreira Prado
B13: GBP | C13: 3º | D13: Assessoria de Comunicação | E13: Assessor Chefe I | F13: Assessor(a) | G13: Comunicação e Relacionamento com o Cidadão | H13: Gestão | I13: 2 - Sim | J13: 1 - Não | L13: 1 - Não possui poder de decisão sobre alocação de recursos orçamentários no órgão | M13: Leonardo da Silva Cantalice
B14: GBP | C14: 3º | D14: Coordenadoria Técnica de Infraestrutura e Logística | E14: Coordenador Técnico | F14: Coordenador(a) | G14: Administrativo | H14: Gestão | I14: 2 - Sim | J14: 2 - Sim | L14: 2 - Possui poder de decisão sobre alocação de recursos orçamentários no órgão | M14: Maíra Oliveira da Silva
B15: GBP | C15: 3º | D15: Coordenadoria Técnica de Inovação | E15: Coordenador Técnico | F15: Coordenador(a) | G15: Técnico-Operacional | H15: Gestão | I15: 2 - Sim | J15: 1 - Não | L15: 1 - Não possui poder de decisão sobre alocação de recursos orçamentários no órgão | M15: Alexandre Goldfeld Cardeman
... B55: CASA CIVIL | C55: 3º | D55: Coordenadoria de Capacitação e Desenvolvimento | E55: Coordenador I | F55: Coordenador(a) | G55: ⚠️ REVISÃO MANUAL (48.03% de Confiança): Tecnologias da Informação | H55: Gestão | I55: 2 - Sim | J55: 1 - Não | L55: 1 - Não possui poder de decisão sobre alocação de recursos orçamentários no órgão | M55: Rafael Ferreira da Costa Leite
B56: CASA CIVIL | C56: 3º | D56: Núcleo NudgeRio | E56: nan | G56: Técnico-Operacional | H56: Gestão | J56: 1 - Não | L56: 1 - Não possui poder de decisão sobre alocação de recursos orçamentários no órgão | M56: nan
B57: CASA CIVIL | C57: 3º | D57: Núcleo Hub21 | E57: nan | G57: Técnico-Operacional | H57: Gestão | J57: 1 - Não | L57: 1 - Não possui poder de decisão sobre alocação de recursos orçamentários no órgão | M57: nan
B58: CASA CIVIL | C58: 2º | D58: Central de Inteligência, Vigilância e Tecnologia de Apoio a Segurança Pública | E58: Chefe Executivo | F58: Chefe | G58: Técnico-Operacional | H58: Gestão | I58: 2 - Sim | J58: 2 - Sim | L58: 2 - Possui poder de decisão sobre alocação de recursos orçamentários no órgão | M58: Davi de Mattos Carreiro
B59: CASA CIVIL | C59: 3º | D59: Coordenadoria de Tecnologia e Dados | E59: Coordenador I | F59: Coordenador(a) | G59: ⚠️ REVISÃO MANUAL (74.91% de Confiança): Tecnologias da Informação | H59: Gestão | I59: 2 - Sim | J59: 1 - Não | L59: 1 - Não possui poder de decisão sobre alocação de recursos orçamentários no órgão | M59: Maria Eduarda Lacerda Couto
B60: CASA CIVIL | C60: 3º | D60: Coordenadoria de Monitoramento e Operações | E60: Coordenador I | F60: Coordenador(a) | G60: Técnico-Operacional | H60: Gestão | I60: 2 - Sim | J60: 1 - Não | L60: 1 - Não possui poder de decisão sobre alocação de recursos orçamentários no órgão | M60: José Mauricio de Brito Padrone
B61: CASA CIVIL | C61: 2º | D61: Subsecretaria de Transformação Digital e Cidade Inteligente | E61: Subsecretário | F61: Subsecretário(a) | G61: ⚠️ REVISÃO MANUAL (60.11% de Confiança): Tecnologias da Informação | H61: Gestão | I61: 2 - Sim | J61: 1 - Não | L61: 2 - Possui poder de decisão sobre alocação de recursos orçamentários no órgão | M61: Raquel Gonçalves Coimbra Flexa
B62: CASA CIVIL | C62: 3º | D62: Coordenadoria Técnica de Transformação Digital | E62: Coordenador Técnico | F62: Coordenador(a) | G62: ⚠️ REVISÃO MANUAL (62.37% de Confiança): Tecnologias da Informação | H62: Gestão | I62: 2 - Sim | J62: 1 - Não | L62: 1 - Não possui poder de decisão sobre alocação de recursos orçamentários no órgão | M62: Bruno Rainho Mendonça
B63: CASA CIVIL | C63: 3º | D63: Coordenadoria de Relacionamento com o Cidadão | E63: Coordenador I | F63: Coordenador(a) | G63: ⚠️ REVISÃO MANUAL (44.98% de Confiança): Tecnologias da Informação | H63: Gestão | I63: 2 - Sim | J63: 1 - Não | L63: 1 - Não possui poder de decisão sobre alocação de recursos orçamentários no órgão | M63: Gabriela Gervason Reis
B64: CASA CIVIL | C64: 3º | D64: Coordenadoria de Cidade Inteligente | E64: Coordenador I | F64: Coordenador(a) | G64: ⚠️ REVISÃO MANUAL (73.74% de Confiança): Tecnologias da Informação | H64: Gestão | I64: 2 - Sim | J64: 1 - Não | L64: 1 - Não possui poder de decisão sobre alocação de recursos orçamentários no órgão | M64: Willington Domingues Feitosa
B65: CASA CIVIL | C65: 2º | D65: Subsecretaria de Planejamento e Acompanhamento de Resultados | E65: Subsecretário | F65: Subsecretário(a) | G65: ⚠️ REVISÃO MANUAL (59.0% de Confiança): Administrativo | H65: Gestão | I65: 2 - Sim | J65: 2 - Sim | L65: 2 - Possui poder de decisão sobre alocação de recursos orçamentários no órgão | M65: Roberta de Oliveira Guimarães
B66: CASA CIVIL | C66: 3º | D66: Escritório de Planejamento | E66: Coordenador Geral | F66: Coordenador(a) | G66: Técnico-Operacional | H66: Gestão | I66: 2 - Sim | J66: 1 - Não | L66: 1 - Não possui poder de decisão sobre alocação de recursos orçamentários no órgão | M66: Daniel Gleidson Mancebo de Araujo
B67: CASA CIVIL | C67: 3º | D67: Escritório de Gerenciamento de Projetos e Metas | E67: Coordenador Geral | F67: Coordenador(a) | G67: Técnico-Operacional | H67: Gestão | I67: 2 - Sim | J67: 1 - Não | L67: 1 - Não possui poder de decisão sobre alocação de recursos orçamentários no órgão | M67: Fernanda Mofati Lanhas
B68: CASA CIVIL | C68: 2º | D68: Subsecretaria de Assuntos Institucionais | E68: Subsecretário | F68: Subsecretário(a) | G68: Administrativo | H68: Gestão | I68: 2 - Sim | J68: 2 - Sim | L68: 2 - Possui poder de decisão sobre alocação de recursos orçamentários no órgão | M68: Andre Luiz Faria Miranda
B69: CASA CIVIL | C69: 3º | D69: Núcleo de Assuntos Institucionais | E69: Gerente III | F69: Gerente | G69: ⚠️ REVISÃO MANUAL (54.14% de Confiança): Administrativo | H69: Gestão | I69: 2 - Sim | J69: 1 - Não | L69: 1 - Não possui poder de decisão sobre alocação de recursos orçamentários no órgão | M69: Breno Melaragno Costa
... B217: SMF | C217: 3º | D217: Gerência de Integração Governamental | E217: Gerente II | F217: Gerente | G217: Técnico-Operacional | H217: Gestão | I217: 2 - Sim | J217: 1 - Não | L217: 1 - Não possui poder de decisão sobre alocação de recursos orçamentários no órgão | M217: Marcus Vinicius Fraga Martins
B218: SMF | C218: 2º | D218: Núcleo de Apoio Técnico | E218: nan | G218: Técnico-Operacional | H218: Gestão | J218: 1 - Não | L218: 1 - Não possui poder de decisão sobre alocação de recursos orçamentários no órgão | M218: nan
B219: SMA | C219: 1º | D219: Secretaria Municipal de Administração | E219: Secretário Municipal | F219: Secretário(a) | G219: Administrativo | H219: Gestão | I219: 2 - Sim | J219: 2 - Sim | L219: 2 - Possui poder de decisão sobre alocação de recursos orçamentários no órgão | M219: Bernardo Egas Lima Fonseca
B220: SMA | C220: 2º | D220: Núcleo de Monitoramento e Indicadores | E220: Diretor IV | F220: Diretor(a) | G220: ⚠️ REVISÃO MANUAL (72.08% de Confiança): Técnico-Operacional | H220: Gestão | I220: 2 - Sim | J220: 1 - Não | L220: 1 - Não possui poder de decisão sobre alocação de recursos orçamentários no órgão | M220: Willians Cesar Rocha Gaspar
B221: SMA | C221: 2º | D221: Assessoria Técnica Administrativa | E221: Assessor Chefe | F221: Assessor(a) | G221: Administrativo | H221: Gestão | I221: 2 - Sim | J221: 1 - Não | L221: 1 - Não possui poder de decisão sobre alocação de recursos orçamentários no órgão | M221: Felipe de Freitas Lima Magalhães
B222: SMA | C222: 2º | D222: Assessoria de Comunicação Social | E222: Assessor Chefe I | F222: Assessor(a) | G222: Comunicação e Relacionamento com o Cidadão | H222: Gestão | I222: 2 - Sim | J222: 1 - Não | L222: 1 - Não possui poder de decisão sobre alocação de recursos orçamentários no órgão | M222: Deborah Moura Carrolo
B223: SMA | C223: 2º | D223: Ouvidoria | E223: Ouvidor | F223: Ouvidor(a) | G223: Comunicação e Relacionamento com o Cidadão | H223: Gestão | I223: 1 - Não | J223: 1 - Não | L223: 1 - Não possui poder de decisão sobre alocação de recursos orçamentários no órgão | M223: Janaina Mattos de Bacelar
B224: SMA | C224: 2º | D224: Subsecretaria do Sistema Municipal de Administração | E224: Subsecretário | F224: Subsecretário(a) | G224: Administrativo | H224: Gestão | I224: 2 - Sim | J224: 1 - Não | L224: 2 - Possui poder de decisão sobre alocação de recursos orçamentários no órgão | M224: Ana Paula da Silva Giesteira
B225: SMA | C225: 3º | D225: Coordenadoria Geral de Suprimentos e Infraestrutura | E225: Coordenador Geral | F225: Coordenador(a) | G225: ⚠️ REVISÃO MANUAL (32.69% de Confiança): Técnico-Operacional | H225: Gestão | I225: 2 - Sim | J225: 1 - Não | L225: 1 - Não possui poder de decisão sobre alocação de recursos orçamentários no órgão | M225: Alexandre Gonçalves de Souza
B226: SMA | C226: 3º | D226: Coordenadoria Geral de Recursos Humanos | E226: Coordenador Geral | F226: Coordenador(a) | G226: Administrativo | H226: Gestão | I226: 2 - Sim | J226: 2 - Sim | L226: 2 - Possui poder de decisão sobre alocação de recursos orçamentários no órgão | M226: Anderson Ferraz Carneiro
B227: SMA | C227: 2º | D227: Administração Setorial | E227: Diretor I | F227: Diretor(a) | G227: Administrativo | H227: Gestão | I227: 2 - Sim | J227: 1 - Não | L227: 1 - Não possui poder de decisão sobre alocação de recursos orçamentários no órgão | M227: Gabriel Moreira Pinho e Silva
B228: SMA | C228: 3º | D228: Gerência de Recursos Humanos | E228: Gerente II | F228: Gerente | G228: Administrativo | H228: Gestão | I228: 2 - Sim | J228: 1 - Não | L228: 1 - Não possui poder de decisão sobre alocação de recursos orçamentários no órgão | M228: Livia Pecly Pinto Santos
B229: SMA | C229: 3º | D229: Gerência de Infraestrutura e Logística | E229: Gerente II | F229: Gerente | G229: Administrativo | H229: Gestão | I229: 2 - Sim | J229: 1 - Não | L229: 1 - Não possui poder de decisão sobre alocação de recursos orçamentários no órgão | M229: Bruna Rangel de Souza
B230: SMA | C230: 3º | D230: Gerência de Administração e Contratos | E230: Gerente II | F230: Gerente | G230: Administrativo | H230: Gestão | I230: 2 - Sim | J230: 1 - Não | L230: 1 - Não possui poder de decisão sobre alocação de recursos orçamentários no órgão | M230: Daniel Barreto dos Santos
... B513: SMAS | C513: 2º | D513: Gerência de Segurança Alimentar e Nutricional | E513: Gerente II | F513: Gerente | G513: Técnico-Operacional | H513: Social | I513: 2 - Sim | J513: 1 - Não | L513: 1 - Não possui poder de decisão sobre alocação de recursos orçamentários no órgão | M513: Edson Alexander Clemente dos Santos
B514: SMAS | C514: 3º | D514: Centro de Segurança Alimentar da Fazenda Modelo | E514: Diretor V | G514: Técnico-Operacional | H514: Social | J514: 1 - Não | L514: 1 - Não possui poder de decisão sobre alocação de recursos orçamentários no órgão | M514: Hernandes Gomes de Freitas
B515: SMAS | C515: 2º | D515: 1ª Coordenadoria de Assistência Social | E515: Coordenador I | F515: Coordenador(a) | G515: Técnico-Operacional | H515: Social | I515: 2 - Sim | J515: 1 - Não | L515: 1 - Não possui poder de decisão sobre alocação de recursos orçamentários no órgão | M515: Cristiane da Silva Disconzi
B516: SMAS | C516: 3º | D516: Centro de Referência Especializado para População em Situação de Rua Bárbara Calazans | E516: Diretor IV | F516: Diretor(a) | G516: Técnico-Operacional | H516: Social | I516: 2 - Sim | J516: 1 - Não | L516: 1 - Não possui poder de decisão sobre alocação de recursos orçamentários no órgão | M516: Jaqueline Daher Menechini
B517: SMAS | C517: 2º | D517: 2ª Coordenadoria de Assistência Social | E517: Coordenador I | F517: Coordenador(a) | G517: Técnico-Operacional | H517: Social | I517: 2 - Sim | J517: 1 - Não | L517: 1 - Não possui poder de decisão sobre alocação de recursos orçamentários no órgão | M517: Adriana de Sousa Menezes
B518: SMAS | C518: 2º | D518: 3ª Coordenadoria de Assistência Social | E518: Coordenador I | F518: Coordenador(a) | G518: Técnico-Operacional | H518: Social | I518: 2 - Sim | J518: 1 - Não | L518: 1 - Não possui poder de decisão sobre alocação de recursos orçamentários no órgão | M518: Márcia Accioly Cerqueira Serpa
B519: SMAS | C519: 2º | D519: 4ª Coordenadoria de Assistência Social | E519: Coordenador I | F519: Coordenador(a) | G519: Técnico-Operacional | H519: Social | I519: 2 - Sim | J519: 1 - Não | L519: 1 - Não possui poder de decisão sobre alocação de recursos orçamentários no órgão | M519: Viviane Almeida Santos
B520: SMAS | C520: 3º | D520: Centro de Referência Especializado para População em Situação de Rua José Saramago | E520: Diretor IV | F520: Diretor(a) | G520: Técnico-Operacional | H520: Social | I520: 2 - Sim | J520: 1 - Não | L520: 1 - Não possui poder de decisão sobre alocação de recursos orçamentários no órgão | M520: Ilda Márcia Guimarães da Silva
B521: SMAS | C521: 2º | D521: 5ª Coordenadoria de Assistência Social | E521: Coordenador I | F521: Coordenador(a) | G521: Técnico-Operacional | H521: Social | I521: 2 - Sim | J521: 1 - Não | L521: 1 - Não possui poder de decisão sobre alocação de recursos orçamentários no órgão | M521: Claudia de Paiva de Castro
B522: SMAS | C522: 2º | D522: 6ª Coordenadoria de Assistência Social | E522: Coordenador I | F522: Coordenador(a) | G522: Técnico-Operacional | H522: Social | I522: 2 - Sim | J522: 1 - Não | L522: 1 - Não possui poder de decisão sobre alocação de recursos orçamentários no órgão | M522: Leila Regina Ferreira Marques
B523: SMAS | C523: 2º | D523: 7ª Coordenadoria de Assistência Social | E523: Coordenador I | F523: Coordenador(a) | G523: Técnico-Operacional | H523: Social | I523: 2 - Sim | J523: 1 - Não | L523: 1 - Não possui poder de decisão sobre alocação de recursos orçamentários no órgão | M523: Elaine Cristina Mendes de Oliveira Montenegro
B524: SMAS | C524: 2º | D524: 8ª Coordenadoria de Assistência Social | E524: Coordenador I | F524: Coordenador(a) | G524: Técnico-Operacional | H524: Social | I524: 2 - Sim | J524: 1 - Não | L524: 1 - Não possui poder de decisão sobre alocação de recursos orçamentários no órgão | M524: Michele Rose Larrubia Monteiro
B525: SMAS | C525: 2º | D525: 9ª Coordenadoria de Assistência Social | E525: Coordenador I | F525: Coordenador(a) | G525: Técnico-Operacional | H525: Social | I525: 2 - Sim | J525: 1 - Não | L525: 1 - Não possui poder de decisão sobre alocação de recursos orçamentários no órgão | M525: Tatiana Maria Araujo da Fonseca
B526: SMAS | C526: 2º | D526: 10ª Coordenadoria de Assistência Social | E526: Coordenador I | F526: Coordenador(a) | G526: Técnico-Operacional | H526: Social | I526: 2 - Sim | J526: 1 - Não | L526: 1 - Não possui poder de decisão sobre alocação de recursos orçamentários no órgão | M526: Wagner Silva de Andrade
... B754: SMPDA | C754: 3º | D754: Gerência de Cemitérios | E754: Gerente III | F754: Gerente | G754: Técnico-Operacional | H754: Social | I754: 2 - Sim | J754: 1 - Não | L754: 1 - Não possui poder de decisão sobre alocação de recursos orçamentários no órgão | M754: Camila Prado dos Santos
B755: SMPDA | C755: 2º | D755: Núcleo de Apoio Operacional | E755: nan | G755: Técnico-Operacional | H755: Social | J755: 1 - Não | L755: 1 - Não possui poder de decisão sobre alocação de recursos orçamentários no órgão | M755: nan
B756: SMPDA | C756: 2º | D756: Subsecretaria de Gestão | E756: Subsecretário | F756: Subsecretário(a) | G756: Administrativo | H756: Social | I756: 2 - Sim | J756: 2 - Sim | L756: 2 - Possui poder de decisão sobre alocação de recursos orçamentários no órgão | M756: Jorge Willian Ponzo Mathias
B757: SMPDA | C757: 3º | D757: Gerência de Infraestrutura e Logística | E757: Gerente II | F757: Gerente | G757: Administrativo | H757: Social | I757: 2 - Sim | J757: 2 - Sim | L757: 2 - Possui poder de decisão sobre alocação de recursos orçamentários no órgão | M757: Roberto Chaves Carneiro
B758: SMPDA | C758: 3º | D758: Gerência de Contratos | E758: Gerente II | F758: Gerente | G758: Administrativo | H758: Social | I758: 2 - Sim | J758: 1 - Não | L758: 1 - Não possui poder de decisão sobre alocação de recursos orçamentários no órgão | M758: Luciana Souza Alves Soares
B759: SMPDA | C759: 3º | D759: Gerência de Recursos Humanos | E759: Gerente II | F759: Gerente | G759: Administrativo | H759: Social | I759: 2 - Sim | J759: 1 - Não | L759: 1 - Não possui poder de decisão sobre alocação de recursos orçamentários no órgão | M759: Jaqueline Feliciano da Silva
B760: SMTUR-RIO | C760: 1º | D760: Secretaria Municipal de Turismo | E760: Secretário Municipal | F760: Secretário(a) | G760: Administrativo | H760: Planejamento Urbano e Econômico | I760: 2 - Sim | J760: 2 - Sim | L760: 2 - Possui poder de decisão sobre alocação de recursos orçamentários no órgão | M760: Daniela Dalila Ibarra Maia de Andrade Maciel
B761: SMTUR-RIO | C761: 2º | D761: Chefia de Gabinete | E761: Chefe de Gabinete | F761: Chefe | G761: Administrativo | H761: Planejamento Urbano e Econômico | I761: 2 - Sim | J761: 1 - Não | L761: 2 - Possui poder de decisão sobre alocação de recursos orçamentários no órgão | M761: Maria Cecilia de Moraes Duarte
B762: SMTUR-RIO | C762: 2º | D762: Assessoria de Comunicação Social | E762: Assessor Chefe I | F762: Assessor(a) | G762: Comunicação e Relacionamento com o Cidadão | H762: Planejamento Urbano e Econômico | I762: 2 - Sim | J762: 1 - Não | L762: 1 - Não possui poder de decisão sobre alocação de recursos orçamentários no órgão | M762: Fabiana Misse Nassaralla
B763: SMTUR-RIO | C763: 2º | D763: Subsecretaria de Planejamento e Políticas Públicas | E763: Subsecretário | F763: Subsecretário(a) | G763: Técnico-Operacional | H763: Planejamento Urbano e Econômico | I763: 2 - Sim | J763: 1 - Não | L763: 2 - Possui poder de decisão sobre alocação de recursos orçamentários no órgão | M763: Bruno Ferreira de Mattos
B764: SMTUR-RIO | C764: 3º | D764: Gerência de Projetos, Fomento e Inovação | E764: Gerente II | F764: Gerente | G764: Técnico-Operacional | H764: Planejamento Urbano e Econômico | I764: 2 - Sim | J764: 1 - Não | L764: 1 - Não possui poder de decisão sobre alocação de recursos orçamentários no órgão | M764: Laís de Abreu Pires Sardinha
B765: SMTUR-RIO | C765: 3º | D765: Gerência de Observatório do Turismo | E765: Gerente II | F765: Gerente | G765: ⚠️ REVISÃO MANUAL (54.97% de Confiança): Técnico-Operacional | H765: Planejamento Urbano e Econômico | I765: 2 - Sim | J765: 1 - Não | L765: 1 - Não possui poder de decisão sobre alocação de recursos orçamentários no órgão | M765: Renato de Oliveira dos Santos
B766: SMTUR-RIO | C766: 2º | D766: Coordenação de Gestão e Monitoramento de Áreas Turísticas | E766: Coordenador II | F766: Coordenador(a) | G766: ⚠️ REVISÃO MANUAL (53.72% de Confiança): Técnico-Operacional | H766: Planejamento Urbano e Econômico | I766: 2 - Sim | J766: 1 - Não | L766: 1 - Não possui poder de decisão sobre alocação de recursos orçamentários no órgão | M766: Miguel Sebastian Saavedra Ibarra
B767: SMTUR-RIO | C767: 2º | D767: Administração Setorial | E767: Diretor I | F767: Diretor(a) | G767: Administrativo | H767: Planejamento Urbano e Econômico | I767: 2 - Sim | J767: 1 - Não | L767: 1 - Não possui poder de decisão sobre alocação de recursos orçamentários no órgão | M767: Nelza Rodrigues Mello Guimarães
... B771: SEDECON | C771: 1º | D771: Secretaria Especial de Proteção e Defesa do Consumidor | E771: Secretário Especial | F771: Secretário(a) | G771: ⚠️ REVISÃO MANUAL (66.25% de Confiança): Administrativo | H771: Social | I771: 2 - Sim | J771: 1 - Não | L771: 2 - Possui poder de decisão sobre alocação de recursos orçamentários no órgão | M771: Gabriel Siggelkow Guimarães
B772: SEDECON | C772: 2º | D772: Subsecretaria Executiva | E772: Subsecretário Especial | G772: Administrativo | H772: Social | J772: 1 - Não | L772: 1 - Não possui poder de decisão sobre alocação de recursos orçamentários no órgão | M772: Luísa de Oliveira Maciel Pinaud
B773: SEDECON | C773: 2º | D773: Instituto Municipal de Proteção e Defesa do Consumidor - PROCON-Carioca | E773: Diretor I | F773: Diretor(a) | G773: Administrativo | H773: Social | I773: 2 - Sim | J773: 1 - Não | L773: 1 - Não possui poder de decisão sobre alocação de recursos orçamentários no órgão | M773: Soraia Duarte de Oliveira Panella
B774: SEDECON | C774: 3º | D774: Assessoria de Comunicação Social | E774: Assessor Chefe I | F774: Assessor(a) | G774: Comunicação e Relacionamento com o Cidadão | H774: Social | I774: 2 - Sim | J774: 1 - Não | L774: 1 - Não possui poder de decisão sobre alocação de recursos orçamentários no órgão | M774: Mariana Cardoso Silva
B775: SEDECON | C775: 3º | D775: Assessoria Técnica Administrativa | E775: Assessor Chefe I | F775: Assessor(a) | G775: Administrativo | H775: Social | I775: 2 - Sim | J775: 2 - Sim | L775: 2 - Possui poder de decisão sobre alocação de recursos orçamentários no órgão | M775: Felipe César Santiago de Souza
B776: SEDECON | C776: 3º | D776: Gerência de Fiscalização | E776: Gerente III | F776: Gerente | G776: Técnico-Operacional | H776: Social | I776: 2 - Sim | J776: 1 - Não | L776: 1 - Não possui poder de decisão sobre alocação de recursos orçamentários no órgão | M776: Fábio Sampaio Ferreira
B777: SEDECON | C777: 3º | D777: Gerência de Administração | E777: Gerente III | F777: Gerente | G777: Administrativo | H777: Social | I777: 2 - Sim | J777: 1 - Não | L777: 1 - Não possui poder de decisão sobre alocação de recursos orçamentários no órgão | M777: Claudia Fernandes Ribeiro
B778: SEDECON | C778: 3º | D778: Gerência de Atendimento ao Consumidor | E778: Gerente III | F778: Gerente | G778: ⚠️ REVISÃO MANUAL (48.75% de Confiança): Comunicação e Relacionamento com o Cidadão | H778: Social | I778: 2 - Sim | J778: 1 - Não | L778: 1 - Não possui poder de decisão sobre alocação de recursos orçamentários no órgão | M778: Janaina Placido de Oliveira
B779: SPM-RIO | C779: 1º | D779: Secretaria Especial de Políticas para Mulheres e Cuidados | E779: Secretário Especial | F779: Secretário(a) | G779: Técnico-Operacional | H779: Social | I779: 2 - Sim | J779: 2 - Sim | L779: 2 - Possui poder de decisão sobre alocação de recursos orçamentários no órgão | M779: Mariana Xavier da Silva
B780: SPM-RIO | C780: 2º | D780: Chefia de Gabinete | E780: Chefe de Gabinete | F780: Chefe | G780: Administrativo | H780: Social | I780: 2 - Sim | J780: 1 - Não | L780: 2 - Possui poder de decisão sobre alocação de recursos orçamentários no órgão | M780: Taisa Regina Dorne de Freitas
B781: SPM-RIO | C781: 2º | D781: Assessoria Técnica do Gabinete | E781: Assessor Chefe Técnico | F781: Assessor(a) | G781: ⚠️ REVISÃO MANUAL (52.0% de Confiança): Técnico-Operacional | H781: Social | I781: 2 - Sim | J781: 1 - Não | L781: 1 - Não possui poder de decisão sobre alocação de recursos orçamentários no órgão | M781: Mylena Amâncio Soares
B782: SPM-RIO | C782: 2º | D782: Subsecretaria de Políticas para Mulheres | E782: Subsecretário Especial | G782: Técnico-Operacional | H782: Social | J782: 1 - Não | L782: 1 - Não possui poder de decisão sobre alocação de recursos orçamentários no órgão | M782: Mariana da Silva Ferreira de Andrade
B783: SPM-RIO | C783: 3º | D783: Coordenadoria de Promoção da Mulher | E783: Coordenador I | F783: Coordenador(a) | G783: ⚠️ REVISÃO MANUAL (66.28% de Confiança): Técnico-Operacional | H783: Social | I783: 2 - Sim | J783: 1 - Não | L783: 1 - Não possui poder de decisão sobre alocação de recursos orçamentários no órgão | M783: Juliete Dias de Lima de Oliveira
B784: SPM-RIO | C784: 3º | D784: Coordenadoria de Equipamentos Especializados | E784: Coordenador I | F784: Coordenador(a) | G784: Técnico-Operacional | H784: Social | I784: 2 - Sim | J784: 1 - Não | L784: 1 - Não possui poder de decisão sobre alocação de recursos orçamentários no órgão | M784: Valeska Fernandes Pantaleão dos Santos
B785: SPM-RIO | C785: 2º | D785: Coordenadoria de Cuidados | E785: Coordenador I | F785: Coordenador(a) | G785: ⚠️ REVISÃO MANUAL (44.98% de Confiança): Tecnologias da Informação | H785: Social | I785: 2 - Sim | J785: 1 - Não | L785: 1 - Não possui poder de decisão sobre alocação de recursos orçamentários no órgão | M785: Glaucia de Oliveira Gonzaga Xavier
B786: SPM-RIO | C786: 2º | D786: Coordenação de Demandas Institucionais | E786: Coordenador II | F786: Coordenador(a) | G786: Administrativo | H786: Social | I786: 2 - Sim | J786: 1 - Não | L786: 1 - Não possui poder de decisão sobre alocação de recursos orçamentários no órgão | M786: Kelly Dias Rocha Carreira
B787: SPM-RIO | C787: 2º | D787: Coordenadoria de Dados | E787: Coordenador I | F787: Coordenador(a) | G787: Tecnologias da Informação | H787: Social | I787: 2 - Sim | J787: 1 - Não | L787: 1 - Não possui poder de decisão sobre alocação de recursos orçamentários no órgão | M787: Maria Luiza Ferreri Paula Silva
B788: SPM-RIO | C788: 3º | D788: Gerência de Monitoramento de Metas | E788: Gerente III | F788: Gerente | G788: Técnico-Operacional | H788: Social | I788: 2 - Sim | J788: 1 - Não | L788: 1 - Não possui poder de decisão sobre alocação de recursos orçamentários no órgão | M788: Yasmin Carvalho de Assumpção
B789: SPM-RIO | C789: 2º | D789: Administração Setorial | E789: Diretor I | F789: Diretor(a) | G789: Administrativo | H789: Social | I789: 2 - Sim | J789: 2 - Sim | L789: 2 - Possui poder de decisão sobre alocação de recursos orçamentários no órgão | M789: Ana Cláudia Rodrigues Daflon Lescaut
B790: JUV-RIO | C790: 1º | D790: Secretaria Especial da Juventude Carioca | E790: Secretário Especial | F790: Secretário(a) | G790: ⚠️ REVISÃO MANUAL (67.69% de Confiança): Administrativo | H790: Social | I790: 2 - Sim | J790: 1 - Não | L790: 2 - Possui poder de decisão sobre alocação de recursos orçamentários no órgão | M790: Gabriella Rodrigues da Graça
B791: JUV-RIO | C791: 2º | D791: Chefia de Gabinete | E791: Chefe de Gabinete | F791: Chefe | G791: Administrativo | H791: Social | I791: 2 - Sim | J791: 2 - Sim | L791: 2 - Possui poder de decisão sobre alocação de recursos orçamentários no órgão | M791: Fernando Dias da Silva
B792: JUV-RIO | C792: 2º | D792: Subsecretaria de Políticas Temáticas dos Direitos da Juventude | E792: Subsecretário Especial | G792: Técnico-Operacional | H792: Social | J792: 1 - Não | L792: 1 - Não possui poder de decisão sobre alocação de recursos orçamentários no órgão | M792: Felipe Nascimento Lima
B793: JUV-RIO | C793: 3º | D793: Coordenação de Ações Territoriais | E793: Coordenador II | F793: Coordenador(a) | G793: Técnico-Operacional | H793: Social | I793: 2 - Sim | J793: 1 - Não | L793: 1 - Não possui poder de decisão sobre alocação de recursos orçamentários no órgão | M793: Enzo Rangel Gama
B794: JUV-RIO | C794: 3º | D794: Coordenadoria de Informações e Monitoramento da Juventude | E794: Coordenador I | F794: Coordenador(a) | G794: Técnico-Operacional | H794: Social | I794: 2 - Sim | J794: 1 - Não | L794: 1 - Não possui poder de decisão sobre alocação de recursos orçamentários no órgão | M794: Patrick Figueiredo Antunes Pereira
B795: JUV-RIO | C795: 3º | D795: Coordenadoria de Projetos Especiais e Inovação Participativa | E795: Coordenador I | F795: Coordenador(a) | G795: Técnico-Operacional | H795: Social | I795: 2 - Sim | J795: 1 - Não | L795: 1 - Não possui poder de decisão sobre alocação de recursos orçamentários no órgão | M795: Wellington Santos de Souza
B796: JUV-RIO | C796: 3º | D796: Coordenadoria de Equipamentos Públicos | E796: Coordenador I | F796: Coordenador(a) | G796: Técnico-Operacional | H796: Social | I796: 2 - Sim | J796: 1 - Não | L796: 1 - Não possui poder de decisão sobre alocação de recursos orçamentários no órgão | M796: Gisele Costa Silva
B797: JUV-RIO | C797: 2º | D797: Administração Setorial | E797: Diretor I | F797: Diretor(a) | G797: Administrativo | H797: Social | I797: 2 - Sim | J797: 1 - Não | L797: 1 - Não possui poder de decisão sobre alocação de recursos orçamentários no órgão | M797: Anderson Pinheiro Lopes
B798: SEAC-RIO | C798: 1º | D798: Secretaria Especial de Ação Comunitária | E798: Secretário Especial | F798: Secretário(a) | G798: ⚠️ REVISÃO MANUAL (61.15% de Confiança): Administrativo | H798: Social | I798: 2 - Sim | J798: 1 - Não | L798: 2 - Possui poder de decisão sobre alocação de recursos orçamentários no órgão | M798: Gustavo José Freue
...

Sheet Notas Médias
A1: Escalão | B1: Área de Negócio | C1: Tipo de cargo | D1: Chave | E1: Necessidade de realizar articulação com atores | F1: Grau de visibilidade frente a apoio público e accountability | G1: Nível de autonomia para formular e executar políticas públicas | H1: Grau de conhecimento técnico/especializado | I1: Capacidade de ação da área na execução de suas atividades | J1: Capacidade de ação da área na elaboração de estratégias acordadas
A2: 1º | B2: Administrativo | C2: Chefe | D2: {=IF(A2:A985="",, A2:A985&"|"&B2:B985&"|"&C2:C985)} | E2: 4 | F2: 3 | G2: 3 | H2: 3 | I2: 3 | J2: 3
A3: 1º | B3: Administrativo | C3: Coordenador(a) | D3: 1º|Administrativo|Coordenador(a) | E3: 4 | F3: 3 | G3: 3 | H3: 3 | I3: 3 | J3: 3
A4: 1º | B4: Administrativo | C4: Presidente | D4: 1º|Administrativo|Presidente | E4: 4 | F4: 4 | G4: 4 | H4: 4 | I4: 4 | J4: 4
A5: 1º | B5: Administrativo | C5: Secretário(a) | D5: 1º|Administrativo|Secretário(a) | E5: 4 | F5: 3 | G5: 4 | H5: 3 | I5: 4 | J5: 4
A6: 2º | B6: Administrativo | C6: Assessor(a) | D6: 2º|Administrativo|Assessor(a) | E6: 2 | F6: 1 | G6: 1 | H6: 3 | I6: 2 | J6: 2
A7: 2º | B7: Administrativo | C7: Chefe | D7: 2º|Administrativo|Chefe | E7: 4 | F7: 2 | G7: 2 | H7: 3 | I7: 3 | J7: 3
A8: 2º | B8: Administrativo | C8: Coordenador(a) | D8: 2º|Administrativo|Coordenador(a) | E8: 3 | F8: 2 | G8: 2 | H8: 3 | I8: 3 | J8: 2
A9: 2º | B9: Administrativo | C9: Diretor(a) | D9: 2º|Administrativo|Diretor(a) | E9: 2 | F9: 2 | G9: 1 | H9: 3 | I9: 2 | J9: 1
A10: 2º | B10: Administrativo | C10: Presidente | D10: 2º|Administrativo|Presidente | E10: 4 | F10: 3 | G10: 4 | H10: 4 | I10: 4 | J10: 4
A11: 2º | B11: Administrativo | C11: Subsecretário(a) | D11: 2º|Administrativo|Subsecretário(a) | E11: 3 | F11: 3 | G11: 3 | H11: 3 | I11: 3 | J11: 3
A12: 2º | B12: Comunicação e Relacionamento com o Cidadão | C12: Assessor(a) | D12: 2º|Comunicação e Relacionamento com o Cidadão|Assessor(a) | E12: 3 | F12: 2 | G12: 1 | H12: 4 | I12: 2 | J12: 2
A13: 2º | B13: Comunicação e Relacionamento com o Cidadão | C13: Coordenador(a) | D13: 2º|Comunicação e Relacionamento com o Cidadão|Coordenador(a) | E13: 3 | F13: 3 | G13: 3 | H13: 4 | I13: 2 | J13: 2
A14: 2º | B14: Comunicação e Relacionamento com o Cidadão | C14: Ouvidor(a) | D14: 2º|Comunicação e Relacionamento com o Cidadão|Ouvidor(a) | E14: 2 | F14: 2 | G14: 1 | H14: 2 | I14: 2 | J14: 2
... A55: 3º | B55: Tecnologias da Informação | C55: Gerente | D55: 3º|Tecnologias da Informação|Gerente | E55: 2 | F55: 1 | G55: 2 | H55: 4 | I55: 2 | J55: 2
D56: 0
D57: 0
D58: 0
D59: 0
D60: 0
D61: 0
D62: 0
D63: 0
D64: 0
D65: 0
D66: 0
D67: 0
... D985: 0

Sheet Cargos Classificados na Reunião
A1: ID | B1: Órgão | C1: Escalão | D1: Nome do Cargo | E1: Tipo de cargo | F1: Área | G1: Área de Negócio | H1: Macro Área | I1: Necessidade de realizar articulação com atores | J1: Grau de visibilidade frente a apoio público e accountability | K1: RESPONSABILIDADE DE GERIR OUTRAS PESSOAS / EQUIPES | L1: AUTONOMIA PARA ORDENAR DESPESAS | M1: Nível de autonomia para formular e executar políticas públicas | N1: Grau de conhecimento técnico/especializado | O1: Capacidade de ação da área na execução de suas atividades | P1: Capacidade de ação da área na elaboração de estratégias acordadas | Q1: MAGNITUDE DO ORÇAMENTO gerido pelo ocupante do cargo | R1: PODER DE DECISÃO sobre alocação de ORÇAMENTO no órgão
A2: 1001 | B2: SMF | C2: 1º | D2: Secretário Municipal | E2: Secretário(a) | F2: Secretaria Municipal de Fazenda | G2: Administrativo | H2: Gestão | I2: 3 | J2: 4 | M2: 4 | N2: 4 | O2: 4 | P2: 4
A3: 1098 | B3: SMG | C3: 1º | D3: Secretário Municipal | E3: Secretário(a) | F3: Secretaria Municipal de Governo | G3: Administrativo | H3: Gestão | I3: 4 | J3: 4 | M3: 4 | N3: 3 | O3: 4 | P3: 4
A4: 165 | B4: CGM | C4: 2º | D4: Assessor Chefe Técnico | E4: Assessor(a) | F4: Assessoria Técnica do Gabinete | G4: Técnico-Operacional | H4: Gestão | I4: 2 | J4: 2 | M4: 2 | N4: 3 | O4: 3 | P4: 2
A5: 168 | B5: CGM | C5: 2º | D5: Subcontrolador | E5: Subsecretário(a) | F5: Subcontroladoria de Auditoria e Controle | G5: Jurídico | H5: Gestão | I5: 2 | J5: 2 | M5: 3 | N5: 4 | O5: 4 | P5: 4
A6: 169 | B6: CGM | C6: 3º | D6: Auditor Geral | E6: Coordenador(a) | F6: Auditoria Geral | G6: Jurídico | H6: Gestão | I6: 1 | J6: 3 | M6: 3 | N6: 4 | O6: 4 | P6: 4
A7: 171 | B7: CGM | C7: 3º | D7: Coordenador Técnico | E7: Coordenador(a) | F7: Coordenadoria Técnica de Controles e Normas | G7: Técnico-Operacional | H7: Gestão | I7: 3 | J7: 3 | M7: 3 | N7: 4 | O7: 3 | P7: 2
A8: 172 | B8: CGM | C8: 2º | D8: Subcontrolador | E8: Subsecretário(a) | F8: Subcontroladoria de Contabilidade | G8: Financeiro | H8: Gestão | I8: 2 | J8: 3 | M8: 3 | N8: 4 | O8: 4 | P8: 4
A9: 175 | B9: CGM | C9: 3º | D9: Coordenador I | E9: Coordenador(a) | F9: Coordenadoria de Monitoramento e Controle da Regularidade Fiscal | G9: Técnico-Operacional | H9: Gestão | I9: 2 | J9: 4 | M9: 3 | N9: 4 | O9: 4 | P9: 4
A10: 259 | B10: PGM | C10: 2º | D10: Ouvidor de Núcleo I | E10: Ouvidor(a) | F10: Núcleo de Ouvidoria I | G10: Comunicação e Relacionamento com o Cidadão | H10: Gestão | I10: 4 | J10: 1 | M10: 2 | N10: 2 | O10: 3 | P10: 2
A11: 261 | B11: PGM | C11: 2º | D11: Subprocurador Geral do Município | E11: Subsecretário(a) | F11: Subprocuradoria Geral Judicial | G11: Jurídico | H11: Gestão | I11: 4 | J11: 2 | M11: 3 | N11: 4 | O11: 4 | P11: 4
A12: 264 | B12: PGM | C12: 3º | D12: Gerente III | E12: Gerente | F12: Gerência de Gestão de Ofícios | G12: Técnico-Operacional | H12: Gestão | I12: 4 | J12: 2 | M12: 2 | N12: 2 | O12: 3 | P12: 3
A13: 267 | B13: PGM | C13: 2º | D13: Procurador Chefe | E13: Diretor(a) | F13: Procuradoria de Dívida Ativa | G13: Jurídico | H13: Gestão | I13: 3 | J13: 3 | M13: 3 | N13: 4 | O13: 4 | P13: 4
... A1025: 937 | B1025: SMS | C1025: 3º | D1025: Coordenador Geral | E1025: Coordenador(a) | F1025: Coordenadoria Geral de Contratualização, Controle e Auditoria | G1025: Administrativo | H1025: Social | I1025: 2 | J1025: 2 | M1025: 1 | N1025: 4 | O1025: 2 | P1025: 2
A1026: 938 | B1026: SMS | C1026: 3º | D1026: Coordenador Geral | E1026: Coordenador(a) | F1026: Coordenadoria Geral do Complexo Regulador | G1026: Técnico-Operacional | H1026: Social | I1026: 4 | J1026: 4 | N1026: 4 | O1026: 4 | P1026: 4
A1027: 1066 | B1027: SMDU | C1027: 1º | D1027: Secretário Municipal | E1027: Secretário(a) | F1027: Secretaria Municipal de Desenvolvimento Urbano e Licenciamento | G1027: Administrativo | H1027: Planejamento Urbano e Econômico | I1027: 4 | J1027: 4 | M1027: 4 | N1027: 3 | O1027: 4 | P1027: 4
A1028: 1071 | B1028: SMDU | C1028: 2º | D1028: Subsecretário | E1028: Subsecretário(a) | F1028: Subsecretaria de Planejamento Urbano | G1028: Técnico-Operacional | H1028: Planejamento Urbano e Econômico | I1028: 4 | J1028: 3 | M1028: 3 | N1028: 4 | O1028: 4 | P1028: 4
A1029: 1072 | B1029: SMDU | C1029: 3º | D1029: Coordenador Técnico | E1029: Coordenador(a) | F1029: Coordenadoria Técnica de Planejamento Urbano | G1029: Técnico-Operacional | H1029: Planejamento Urbano e Econômico | I1029: 3 | J1029: 3 | M1029: 2 | N1029: 4 | O1029: 3 | P1029: 3
A1030: 1073 | B1030: SMDU | C1030: 3º | D1030: Coordenador I | E1030: Coordenador(a) | F1030: Coordenadoria de Estudos Urbanos | G1030: Técnico-Operacional | H1030: Planejamento Urbano e Econômico | I1030: 3 | J1030: 2 | M1030: 2 | N1030: 4 | O1030: 3 | P1030: 3
A1031: 1074 | B1031: SMDU | C1031: 3º | D1031: Coordenador I | E1031: Coordenador(a) | F1031: Coordenadoria de Planejamento Territorial | G1031: Técnico-Operacional | H1031: Planejamento Urbano e Econômico | I1031: 3 | J1031: 2 | M1031: 2 | N1031: 4 | O1031: 3 | P1031: 3
A1032: 1075 | B1032: SMDU | C1032: 3º | D1032: Coordenador I | E1032: Coordenador(a) | F1032: Coordenação de Projetos Urbanos | G1032: Técnico-Operacional | H1032: Planejamento Urbano e Econômico | I1032: 3 | J1032: 2 | M1032: 2 | N1032: 4 | O1032: 3 | P1032: 3
A1033: 1076 | B1033: SMDU | C1033: 2º | D1033: Subsecretário | E1033: Subsecretário(a) | F1033: Subsecretaria de Controle e Licenciamento Urbanístico | G1033: Técnico-Operacional | H1033: Planejamento Urbano e Econômico | I1033: 4 | J1033: 3 | M1033: 3 | N1033: 4 | O1033: 4 | P1033: 4
A1034: 1077 | B1034: SMDU | C1034: 3º | D1034: Coordenador Geral | E1034: Coordenador(a) | F1034: Coordenadoria Geral de Licenciamento e Fiscalização | G1034: Técnico-Operacional | H1034: Planejamento Urbano e Econômico | I1034: 3 | J1034: 3 | M1034: 2 | N1034: 4 | O1034: 3 | P1034: 4
A1035: 1078 | B1035: SMDU | C1035: 3º | D1035: Coordenador I | E1035: Coordenador(a) | F1035: Coordenadoria de Arrecadação Urbanística | G1035: Técnico-Operacional | H1035: Planejamento Urbano e Econômico | I1035: 3 | J1035: 2 | M1035: 1 | N1035: 3 | O1035: 3 | P1035: 3
A1036: 1079 | B1036: SMDU | C1036: 2º | D1036: Subsecretário | E1036: Subsecretário(a) | F1036: Subsecretaria de Controle e Licenciamento Ambiental | G1036: Técnico-Operacional | H1036: Planejamento Urbano e Econômico | I1036: 4 | J1036: 3 | M1036: 3 | N1036: 4 | O1036: 4 | P1036: 4
A1037: 1080 | B1037: SMDU | C1037: 3º | D1037: Coordenador I | E1037: Coordenador(a) | F1037: Coordenadoria de Controle Ambiental de Atividades de Serviços e Industriais | G1037: Técnico-Operacional | H1037: Planejamento Urbano e Econômico | I1037: 3 | J1037: 2 | M1037: 2 | N1037: 4 | O1037: 3 | P1037: 3
A1038: 1081 | B1038: SMDU | C1038: 3º | D1038: Coordenador I | E1038: Coordenador(a) | F1038: Coordenadoria de Controle Ambiental de Obras e Parcelamento do Solo | G1038: Técnico-Operacional | H1038: Planejamento Urbano e Econômico | I1038: 3 | J1038: 3 | M1038: 2 | N1038: 4 | O1038: 3 | P1038: 3
... A1164: 830 | B1164: SMTE | C1164: 3º | D1164: Gerente II | E1164: Gerente | F1164: Gerência de Projetos Especiais, Inovação e Novos Negócios | G1164: Técnico-Operacional | H1164: Social | I1164: 4 | J1164: 1 | M1164: 2 | N1164: 3 | O1164: 3 | P1164: 3

Sheet Cálculo
A1: =IFERROR(__xludf.dummyfunction("QUERY('Todas as Funções (Editável)'!A1:H3501, ""select A,B,C,D,E,F,G,H where A is not null"")"),"ID (automático)") | B1: =IFERROR(__xludf.dummyfunction("""COMPUTED_VALUE"""),"Órgão") | C1: =IFERROR(__xludf.dummyfunction("""COMPUTED_VALUE"""),"Escalão (como está na árvore do SICI)") | D1: =IFERROR(__xludf.dummyfunction("""COMPUTED_VALUE"""),"Área (como está no SICI)") | E1: =IFERROR(__xludf.dummyfunction("""COMPUTED_VALUE"""),"Nome do Cargo (como está no SICI)") | F1: =IFERROR(__xludf.dummyfunction("""COMPUTED_VALUE"""),"Tipo de Cargo (deve ser um dos oito tipos)") | G1: =IFERROR(__xludf.dummyfunction("""COMPUTED_VALUE"""),"Área de Negócio (referente à Área)") | H1: =IFERROR(__xludf.dummyfunction("""COMPUTED_VALUE"""),"Macro Área (referente ao órgão)") | I1: Necessidade de realizar articulação com atores | J1: Grau de visibilidade frente a apoio público e accountability | K1: Nível de autonomia para formular e executar políticas públicas | L1: Grau de conhecimento técnico/especializado | M1: Capacidade de ação da área na execução de suas atividades | N1: Capacidade de ação da área na elaboração de estratégias acordadas | O1: Gerencia equipe | P1: Autonomia para ordenar despesa | Q1: Magnitude do Orçamento Gerido | R1: Poder de Decisão sobre o Orçamento | S1: Pontos da Habilidade Política | T1: Requer Habilidade Política | U1: Pontos Habilidade Técnica | V1: Requer Habilidade Técnica | W1: Pontos Policy Making | X1: Requer Policy Making | Y1: Pontos Habilidade Gerencial | Z1: Requer Habilidade Gerencial | AA1: Pontos Responsabilidade Orçamentária | AB1: Requer Responsabilidade Orçamentária | AC1: Tipo estratégico (cálculo intermediário) | AD1: Nível estratégico | AE1: Status da classificação
A2: =IFERROR(__xludf.dummyfunction("""COMPUTED_VALUE"""),1) | B2: =IFERROR(__xludf.dummyfunction("""COMPUTED_VALUE"""),"GVP") | C2: =IFERROR(__xludf.dummyfunction("""COMPUTED_VALUE"""),"1º") | D2: =IFERROR(__xludf.dummyfunction("""COMPUTED_VALUE"""),"Gabinete do Vice-Prefeito") | E2: =IFERROR(__xludf.dummyfunction("""COMPUTED_VALUE"""),"Chefe de Gabinete") | F2: =IFERROR(__xludf.dummyfunction("""COMPUTED_VALUE"""),"Chefe") | G2: =IFERROR(__xludf.dummyfunction("""COMPUTED_VALUE"""),"Administrativo") | H2: =IFERROR(__xludf.dummyfunction("""COMPUTED_VALUE"""),"Gestão") | I2: {=map( C2:C2005, G2:G2005, F2:F2005, lambda(escal, area, tipo, IF( escal="", , xlookup( TRIM(escal)&"|"&TRIM(area)&"|"&TRIM(tipo), 'Notas Médias'!D:D, 'Notas Médias'!E:J, "" ) ) ) )} | J2: #NAME? | K2: #NAME? | L2: #NAME? | M2: #NAME? | N2: #NAME? | O2: {=LEFT('Todas as Funções (Editável)'!I2:I2005,1)} | P2: {=LEFT('Todas as Funções (Editável)'!J2:J2005,1)} | Q2: {=LEFT('Todas as Funções (Editável)'!K2:K2005,1)} | R2: {=LEFT('Todas as Funções (Editável)'!L2:L2005,1)} | S2: {=IF(I2:I2005="",, I2:I2005*J2:J2005)} | T2: {=IF(S2:S2005="",, IF(S2:S2005>=8,"Sim","Não"))} | U2: {=IF(K2:K2005="",, K2:K2005*L2:L2005)} | V2: {=IF(U2:U2005="",, IF(U2:U2005>=8,"Sim","Não"))} | W2: {=IF(M2:M2005="",, M2:M2005*N2:N2005)} | X2: {=IF( W2:W2005="", , IF( W2:W2005>=9, "Alta", IF( W2:W2005<4, "Baixa", "Média" ) ) )} | Y2: {=IF(O2:O2005="",, O2:O2005*P2:P2005)} | Z2: {=IF(Y2:Y2005="",, IF(Y2:Y2005>=2,"Sim","Não"))} | AA2: {=IF(Q2:Q2005="",, Q2:Q2005*R2:R2005)} | AB2: {=IF( AA2:AA2005="", , IF( AA2:AA2005>=4, "Alta", IF( AA2:AA2005<2, "Baixa", "Média" ) ) )} | AC2: {=IF( (F2:F2005="") + (R2:R2005=""), "", IFERROR( VLOOKUP( T2:T2005&Z2:Z2005&V2:V2005&X2:X2005&AB2:AB2005, premissas_tipo_cargo, 2, FALSE() ), "" ) )} | AD2: {=IFERROR(ifs( F2 = "Secretário(a)", INDEX(Secretario, MATCH(RIGHT(AC2), premissas_nivel_cargo_letra, 0), MATCH(VALUE(LEFT(AC2)), premissas_nivel_cargo_numero, 0)), F2 = "Presidente", INDEX(Presidente, MATCH(RIGHT(AC2), premissas_nivel_cargo_letra, 0), MATCH(VALUE(LEFT(AC2)), premissas_nivel_cargo_numero, 0)), F2 = "Subsecretário(a)", INDEX(Subsecretario, MATCH(RIGHT(AC2), premissas_nivel_cargo_letra, 0), MATCH(VALUE(LEFT(AC2)), premissas_nivel_cargo_numero, 0)), F2 = "Superintendente", INDEX(Superintendente, MATCH(RIGHT(AC2), premissas_nivel_cargo_letra, 0), MATCH(VALUE(LEFT(AC2)), premissas_nivel_cargo_numero, 0)), F2 = "Coordenador(a)", INDEX(Coordenador, MATCH(RIGHT(AC2), premissas_nivel_cargo_letra, 0), MATCH(VALUE(LEFT(AC2)), premissas_nivel_cargo_numero, 0)), F2 = "Chefe", INDEX(Chefe, MATCH(RIGHT(AC2), premissas_nivel_cargo_letra, 0), MATCH(VALUE(LEFT(AC2)), premissas_nivel_cargo_numero, 0)), F2 = "Diretor(a)", INDEX(Diretor, MATCH(RIGHT(AC2), premissas_nivel_cargo_letra, 0), MATCH(VALUE(LEFT(AC2)), premissas_nivel_cargo_numero, 0)), F2 = "Gerente", INDEX(Gerente, MATCH(RIGHT(AC2), premissas_nivel_cargo_letra, 0), MATCH(VALUE(LEFT(AC2)), premissas_nivel_cargo_numero, 0)), F2 = "Assessor(a)", INDEX(Assessor, MATCH(RIGHT(AC2), premissas_nivel_cargo_letra, 0), MATCH(VALUE(LEFT(AC2)), premissas_nivel_cargo_numero, 0)), F2 = "Ouvidor(a)", INDEX(Ouvidor, MATCH(RIGHT(AC2), premissas_nivel_cargo_letra, 0), MATCH(VALUE(LEFT(AC2)), premissas_nivel_cargo_numero, 0)) ), "")} | AE2: =ifs(G2 = "", "", AD2 = "", "Ainda Não Classificado", NOT(AD2 = ""), "Classificado com Sucesso")
A3: =IFERROR(__xludf.dummyfunction("""COMPUTED_VALUE"""),2) | B3: =IFERROR(__xludf.dummyfunction("""COMPUTED_VALUE"""),"GVP") | C3: =IFERROR(__xludf.dummyfunction("""COMPUTED_VALUE"""),"2º") | D3: =IFERROR(__xludf.dummyfunction("""COMPUTED_VALUE"""),"Coordenadoria de Imprensa") | E3: =IFERROR(__xludf.dummyfunction("""COMPUTED_VALUE"""),"Coordenador I") | F3: =IFERROR(__xludf.dummyfunction("""COMPUTED_VALUE"""),"Coordenador(a)") | G3: =IFERROR(__xludf.dummyfunction("""COMPUTED_VALUE"""),"Comunicação e Relacionamento com o Cidadão") | H3: =IFERROR(__xludf.dummyfunction("""COMPUTED_VALUE"""),"Gestão") | I3: #NAME? | J3: #NAME? | K3: #NAME? | L3: #NAME? | M3: #NAME? | N3: #NAME? | S3: #NAME? | T3: #NAME? | U3: #NAME? | V3: #NAME? | W3: #NAME? | X3: #NAME? | Y3: 0 | Z3: Não | AA3: 0 | AB3: Baixa | AD3: {=IFERROR(ifs( F3 = "Secretário(a)", INDEX(Secretario, MATCH(RIGHT(AC3), premissas_nivel_cargo_letra, 0), MATCH(VALUE(LEFT(AC3)), premissas_nivel_cargo_numero, 0)), F3 = "Presidente", INDEX(Presidente, MATCH(RIGHT(AC3), premissas_nivel_cargo_letra, 0), MATCH(VALUE(LEFT(AC3)), premissas_nivel_cargo_numero, 0)), F3 = "Subsecretário(a)", INDEX(Subsecretario, MATCH(RIGHT(AC3), premissas_nivel_cargo_letra, 0), MATCH(VALUE(LEFT(AC3)), premissas_nivel_cargo_numero, 0)), F3 = "Superintendente", INDEX(Superintendente, MATCH(RIGHT(AC3), premissas_nivel_cargo_letra, 0), MATCH(VALUE(LEFT(AC3)), premissas_nivel_cargo_numero, 0)), F3 = "Coordenador(a)", INDEX(Coordenador, MATCH(RIGHT(AC3), premissas_nivel_cargo_letra, 0), MATCH(VALUE(LEFT(AC3)), premissas_nivel_cargo_numero, 0)), F3 = "Chefe", INDEX(Chefe, MATCH(RIGHT(AC3), premissas_nivel_cargo_letra, 0), MATCH(VALUE(LEFT(AC3)), premissas_nivel_cargo_numero, 0)), F3 = "Diretor(a)", INDEX(Diretor, MATCH(RIGHT(AC3), premissas_nivel_cargo_letra, 0), MATCH(VALUE(LEFT(AC3)), premissas_nivel_cargo_numero, 0)), F3 = "Gerente", INDEX(Gerente, MATCH(RIGHT(AC3), premissas_nivel_cargo_letra, 0), MATCH(VALUE(LEFT(AC3)), premissas_nivel_cargo_numero, 0)), F3 = "Assessor(a)", INDEX(Assessor, MATCH(RIGHT(AC3), premissas_nivel_cargo_letra, 0), MATCH(VALUE(LEFT(AC3)), premissas_nivel_cargo_numero, 0)), F3 = "Ouvidor(a)", INDEX(Ouvidor, MATCH(RIGHT(AC3), premissas_nivel_cargo_letra, 0), MATCH(VALUE(LEFT(AC3)), premissas_nivel_cargo_numero, 0)) ), "")} | AE3: =ifs(G3 = "", "", AD3 = "", "Ainda Não Classificado", NOT(AD3 = ""), "Classificado com Sucesso")
A4: =IFERROR(__xludf.dummyfunction("""COMPUTED_VALUE"""),3) | B4: =IFERROR(__xludf.dummyfunction("""COMPUTED_VALUE"""),"GVP") | C4: =IFERROR(__xludf.dummyfunction("""COMPUTED_VALUE"""),"2º") | D4: =IFERROR(__xludf.dummyfunction("""COMPUTED_VALUE"""),"Coordenadoria de Comunicação Institucional") | E4: =IFERROR(__xludf.dummyfunction("""COMPUTED_VALUE"""),"Coordenador I") | F4: =IFERROR(__xludf.dummyfunction("""COMPUTED_VALUE"""),"Coordenador(a)") | G4: =IFERROR(__xludf.dummyfunction("""COMPUTED_VALUE"""),"Comunicação e Relacionamento com o Cidadão") | H4: =IFERROR(__xludf.dummyfunction("""COMPUTED_VALUE"""),"Gestão") | I4: #NAME? | J4: #NAME? | K4: #NAME? | L4: #NAME? | M4: #NAME? | N4: #NAME? | S4: #NAME? | T4: #NAME? | U4: #NAME? | V4: #NAME? | W4: #NAME? | X4: #NAME? | Y4: 0 | Z4: Não | AA4: 0 | AB4: Baixa | AD4: {=IFERROR(ifs( F4 = "Secretário(a)", INDEX(Secretario, MATCH(RIGHT(AC4), premissas_nivel_cargo_letra, 0), MATCH(VALUE(LEFT(AC4)), premissas_nivel_cargo_numero, 0)), F4 = "Presidente", INDEX(Presidente, MATCH(RIGHT(AC4), premissas_nivel_cargo_letra, 0), MATCH(VALUE(LEFT(AC4)), premissas_nivel_cargo_numero, 0)), F4 = "Subsecretário(a)", INDEX(Subsecretario, MATCH(RIGHT(AC4), premissas_nivel_cargo_letra, 0), MATCH(VALUE(LEFT(AC4)), premissas_nivel_cargo_numero, 0)), F4 = "Superintendente", INDEX(Superintendente, MATCH(RIGHT(AC4), premissas_nivel_cargo_letra, 0), MATCH(VALUE(LEFT(AC4)), premissas_nivel_cargo_numero, 0)), F4 = "Coordenador(a)", INDEX(Coordenador, MATCH(RIGHT(AC4), premissas_nivel_cargo_letra, 0), MATCH(VALUE(LEFT(AC4)), premissas_nivel_cargo_numero, 0)), F4 = "Chefe", INDEX(Chefe, MATCH(RIGHT(AC4), premissas_nivel_cargo_letra, 0), MATCH(VALUE(LEFT(AC4)), premissas_nivel_cargo_numero, 0)), F4 = "Diretor(a)", INDEX(Diretor, MATCH(RIGHT(AC4), premissas_nivel_cargo_letra, 0), MATCH(VALUE(LEFT(AC4)), premissas_nivel_cargo_numero, 0)), F4 = "Gerente", INDEX(Gerente, MATCH(RIGHT(AC4), premissas_nivel_cargo_letra, 0), MATCH(VALUE(LEFT(AC4)), premissas_nivel_cargo_numero, 0)), F4 = "Assessor(a)", INDEX(Assessor, MATCH(RIGHT(AC4), premissas_nivel_cargo_letra, 0), MATCH(VALUE(LEFT(AC4)), premissas_nivel_cargo_numero, 0)), F4 = "Ouvidor(a)", INDEX(Ouvidor, MATCH(RIGHT(AC4), premissas_nivel_cargo_letra, 0), MATCH(VALUE(LEFT(AC4)), premissas_nivel_cargo_numero, 0)) ), "")} | AE4: =ifs(G4 = "", "", AD4 = "", "Ainda Não Classificado", NOT(AD4 = ""), "Classificado com Sucesso")
A5: =IFERROR(__xludf.dummyfunction("""COMPUTED_VALUE"""),4) | B5: =IFERROR(__xludf.dummyfunction("""COMPUTED_VALUE"""),"GVP") | C5: =IFERROR(__xludf.dummyfunction("""COMPUTED_VALUE"""),"2º") | D5: =IFERROR(__xludf.dummyfunction("""COMPUTED_VALUE"""),"Coordenadoria de Conteúdo") | E5: =IFERROR(__xludf.dummyfunction("""COMPUTED_VALUE"""),"Coordenador I") | F5: =IFERROR(__xludf.dummyfunction("""COMPUTED_VALUE"""),"Coordenador(a)") | G5: =IFERROR(__xludf.dummyfunction("""COMPUTED_VALUE"""),"Comunicação e Relacionamento com o Cidadão") | H5: =IFERROR(__xludf.dummyfunction("""COMPUTED_VALUE"""),"Gestão") | I5: #NAME? | J5: #NAME? | K5: #NAME? | L5: #NAME? | M5: #NAME? | N5: #NAME? | S5: #NAME? | T5: #NAME? | U5: #NAME? | V5: #NAME? | W5: #NAME? | X5: #NAME? | Y5: 0 | Z5: Não | AA5: 0 | AB5: Baixa | AD5: {=IFERROR(ifs( F5 = "Secretário(a)", INDEX(Secretario, MATCH(RIGHT(AC5), premissas_nivel_cargo_letra, 0), MATCH(VALUE(LEFT(AC5)), premissas_nivel_cargo_numero, 0)), F5 = "Presidente", INDEX(Presidente, MATCH(RIGHT(AC5), premissas_nivel_cargo_letra, 0), MATCH(VALUE(LEFT(AC5)), premissas_nivel_cargo_numero, 0)), F5 = "Subsecretário(a)", INDEX(Subsecretario, MATCH(RIGHT(AC5), premissas_nivel_cargo_letra, 0), MATCH(VALUE(LEFT(AC5)), premissas_nivel_cargo_numero, 0)), F5 = "Superintendente", INDEX(Superintendente, MATCH(RIGHT(AC5), premissas_nivel_cargo_letra, 0), MATCH(VALUE(LEFT(AC5)), premissas_nivel_cargo_numero, 0)), F5 = "Coordenador(a)", INDEX(Coordenador, MATCH(RIGHT(AC5), premissas_nivel_cargo_letra, 0), MATCH(VALUE(LEFT(AC5)), premissas_nivel_cargo_numero, 0)), F5 = "Chefe", INDEX(Chefe, MATCH(RIGHT(AC5), premissas_nivel_cargo_letra, 0), MATCH(VALUE(LEFT(AC5)), premissas_nivel_cargo_numero, 0)), F5 = "Diretor(a)", INDEX(Diretor, MATCH(RIGHT(AC5), premissas_nivel_cargo_letra, 0), MATCH(VALUE(LEFT(AC5)), premissas_nivel_cargo_numero, 0)), F5 = "Gerente", INDEX(Gerente, MATCH(RIGHT(AC5), premissas_nivel_cargo_letra, 0), MATCH(VALUE(LEFT(AC5)), premissas_nivel_cargo_numero, 0)), F5 = "Assessor(a)", INDEX(Assessor, MATCH(RIGHT(AC5), premissas_nivel_cargo_letra, 0), MATCH(VALUE(LEFT(AC5)), premissas_nivel_cargo_numero, 0)), F5 = "Ouvidor(a)", INDEX(Ouvidor, MATCH(RIGHT(AC5), premissas_nivel_cargo_letra, 0), MATCH(VALUE(LEFT(AC5)), premissas_nivel_cargo_numero, 0)) ), "")} | AE5: =ifs(G5 = "", "", AD5 = "", "Ainda Não Classificado", NOT(AD5 = ""), "Classificado com Sucesso")
A6: =IFERROR(__xludf.dummyfunction("""COMPUTED_VALUE"""),5) | B6: =IFERROR(__xludf.dummyfunction("""COMPUTED_VALUE"""),"GVP") | C6: =IFERROR(__xludf.dummyfunction("""COMPUTED_VALUE"""),"2º") | D6: =IFERROR(__xludf.dummyfunction("""COMPUTED_VALUE"""),"Coordenadoria de Integração Territorial") | E6: =IFERROR(__xludf.dummyfunction("""COMPUTED_VALUE"""),"Coordenador I") | F6: =IFERROR(__xludf.dummyfunction("""COMPUTED_VALUE"""),"Coordenador(a)") | G6: =IFERROR(__xludf.dummyfunction("""COMPUTED_VALUE"""),"Técnico-Operacional") | H6: =IFERROR(__xludf.dummyfunction("""COMPUTED_VALUE"""),"Gestão") | I6: #NAME? | J6: #NAME? | K6: #NAME? | L6: #NAME? | M6: #NAME? | N6: #NAME? | S6: #NAME? | T6: #NAME? | U6: #NAME? | V6: #NAME? | W6: #NAME? | X6: #NAME? | Y6: 0 | Z6: Não | AA6: 0 | AB6: Baixa | AD6: {=IFERROR(ifs( F6 = "Secretário(a)", INDEX(Secretario, MATCH(RIGHT(AC6), premissas_nivel_cargo_letra, 0), MATCH(VALUE(LEFT(AC6)), premissas_nivel_cargo_numero, 0)), F6 = "Presidente", INDEX(Presidente, MATCH(RIGHT(AC6), premissas_nivel_cargo_letra, 0), MATCH(VALUE(LEFT(AC6)), premissas_nivel_cargo_numero, 0)), F6 = "Subsecretário(a)", INDEX(Subsecretario, MATCH(RIGHT(AC6), premissas_nivel_cargo_letra, 0), MATCH(VALUE(LEFT(AC6)), premissas_nivel_cargo_numero, 0)), F6 = "Superintendente", INDEX(Superintendente, MATCH(RIGHT(AC6), premissas_nivel_cargo_letra, 0), MATCH(VALUE(LEFT(AC6)), premissas_nivel_cargo_numero, 0)), F6 = "Coordenador(a)", INDEX(Coordenador, MATCH(RIGHT(AC6), premissas_nivel_cargo_letra, 0), MATCH(VALUE(LEFT(AC6)), premissas_nivel_cargo_numero, 0)), F6 = "Chefe", INDEX(Chefe, MATCH(RIGHT(AC6), premissas_nivel_cargo_letra, 0), MATCH(VALUE(LEFT(AC6)), premissas_nivel_cargo_numero, 0)), F6 = "Diretor(a)", INDEX(Diretor, MATCH(RIGHT(AC6), premissas_nivel_cargo_letra, 0), MATCH(VALUE(LEFT(AC6)), premissas_nivel_cargo_numero, 0)), F6 = "Gerente", INDEX(Gerente, MATCH(RIGHT(AC6), premissas_nivel_cargo_letra, 0), MATCH(VALUE(LEFT(AC6)), premissas_nivel_cargo_numero, 0)), F6 = "Assessor(a)", INDEX(Assessor, MATCH(RIGHT(AC6), premissas_nivel_cargo_letra, 0), MATCH(VALUE(LEFT(AC6)), premissas_nivel_cargo_numero, 0)), F6 = "Ouvidor(a)", INDEX(Ouvidor, MATCH(RIGHT(AC6), premissas_nivel_cargo_letra, 0), MATCH(VALUE(LEFT(AC6)), premissas_nivel_cargo_numero, 0)) ), "")} | AE6: =ifs(G6 = "", "", AD6 = "", "Ainda Não Classificado", NOT(AD6 = ""), "Classificado com Sucesso")
A7: =IFERROR(__xludf.dummyfunction("""COMPUTED_VALUE"""),6) | B7: =IFERROR(__xludf.dummyfunction("""COMPUTED_VALUE"""),"GVP") | C7: =IFERROR(__xludf.dummyfunction("""COMPUTED_VALUE"""),"2º") | D7: =IFERROR(__xludf.dummyfunction("""COMPUTED_VALUE"""),"Coordenadoria Executiva") | E7: =IFERROR(__xludf.dummyfunction("""COMPUTED_VALUE"""),"Coordenador I") | F7: =IFERROR(__xludf.dummyfunction("""COMPUTED_VALUE"""),"Coordenador(a)") | G7: =IFERROR(__xludf.dummyfunction("""COMPUTED_VALUE"""),"Administrativo") | H7: =IFERROR(__xludf.dummyfunction("""COMPUTED_VALUE"""),"Gestão") | I7: #NAME? | J7: #NAME? | K7: #NAME? | L7: #NAME? | M7: #NAME? | N7: #NAME? | S7: #NAME? | T7: #NAME? | U7: #NAME? | V7: #NAME? | W7: #NAME? | X7: #NAME? | Y7: 0 | Z7: Não | AA7: 0 | AB7: Baixa | AD7: {=IFERROR(ifs( F7 = "Secretário(a)", INDEX(Secretario, MATCH(RIGHT(AC7), premissas_nivel_cargo_letra, 0), MATCH(VALUE(LEFT(AC7)), premissas_nivel_cargo_numero, 0)), F7 = "Presidente", INDEX(Presidente, MATCH(RIGHT(AC7), premissas_nivel_cargo_letra, 0), MATCH(VALUE(LEFT(AC7)), premissas_nivel_cargo_numero, 0)), F7 = "Subsecretário(a)", INDEX(Subsecretario, MATCH(RIGHT(AC7), premissas_nivel_cargo_letra, 0), MATCH(VALUE(LEFT(AC7)), premissas_nivel_cargo_numero, 0)), F7 = "Superintendente", INDEX(Superintendente, MATCH(RIGHT(AC7), premissas_nivel_cargo_letra, 0), MATCH(VALUE(LEFT(AC7)), premissas_nivel_cargo_numero, 0)), F7 = "Coordenador(a)", INDEX(Coordenador, MATCH(RIGHT(AC7), premissas_nivel_cargo_letra, 0), MATCH(VALUE(LEFT(AC7)), premissas_nivel_cargo_numero, 0)), F7 = "Chefe", INDEX(Chefe, MATCH(RIGHT(AC7), premissas_nivel_cargo_letra, 0), MATCH(VALUE(LEFT(AC7)), premissas_nivel_cargo_numero, 0)), F7 = "Diretor(a)", INDEX(Diretor, MATCH(RIGHT(AC7), premissas_nivel_cargo_letra, 0), MATCH(VALUE(LEFT(AC7)), premissas_nivel_cargo_numero, 0)), F7 = "Gerente", INDEX(Gerente, MATCH(RIGHT(AC7), premissas_nivel_cargo_letra, 0), MATCH(VALUE(LEFT(AC7)), premissas_nivel_cargo_numero, 0)), F7 = "Assessor(a)", INDEX(Assessor, MATCH(RIGHT(AC7), premissas_nivel_cargo_letra, 0), MATCH(VALUE(LEFT(AC7)), premissas_nivel_cargo_numero, 0)), F7 = "Ouvidor(a)", INDEX(Ouvidor, MATCH(RIGHT(AC7), premissas_nivel_cargo_letra, 0), MATCH(VALUE(LEFT(AC7)), premissas_nivel_cargo_numero, 0)) ), "")} | AE7: =ifs(G7 = "", "", AD7 = "", "Ainda Não Classificado", NOT(AD7 = ""), "Classificado com Sucesso")
A8: =IFERROR(__xludf.dummyfunction("""COMPUTED_VALUE"""),7) | B8: =IFERROR(__xludf.dummyfunction("""COMPUTED_VALUE"""),"SMDE") | C8: =IFERROR(__xludf.dummyfunction("""COMPUTED_VALUE"""),"1º") | D8: =IFERROR(__xludf.dummyfunction("""COMPUTED_VALUE"""),"Secretaria Municipal de Desenvolvimento Econômico") | E8: =IFERROR(__xludf.dummyfunction("""COMPUTED_VALUE"""),"Secretário Municipal") | F8: =IFERROR(__xludf.dummyfunction("""COMPUTED_VALUE"""),"Secretário(a)") | G8: =IFERROR(__xludf.dummyfunction("""COMPUTED_VALUE"""),"Administrativo") | H8: =IFERROR(__xludf.dummyfunction("""COMPUTED_VALUE"""),"Planejamento Urbano e Econômico") | I8: #NAME? | J8: #NAME? | K8: #NAME? | L8: #NAME? | M8: #NAME? | N8: #NAME? | S8: #NAME? | T8: #NAME? | U8: #NAME? | V8: #NAME? | W8: #NAME? | X8: #NAME? | Y8: 0 | Z8: Não | AA8: 0 | AB8: Baixa | AD8: {=IFERROR(ifs( F8 = "Secretário(a)", INDEX(Secretario, MATCH(RIGHT(AC8), premissas_nivel_cargo_letra, 0), MATCH(VALUE(LEFT(AC8)), premissas_nivel_cargo_numero, 0)), F8 = "Presidente", INDEX(Presidente, MATCH(RIGHT(AC8), premissas_nivel_cargo_letra, 0), MATCH(VALUE(LEFT(AC8)), premissas_nivel_cargo_numero, 0)), F8 = "Subsecretário(a)", INDEX(Subsecretario, MATCH(RIGHT(AC8), premissas_nivel_cargo_letra, 0), MATCH(VALUE(LEFT(AC8)), premissas_nivel_cargo_numero, 0)), F8 = "Superintendente", INDEX(Superintendente, MATCH(RIGHT(AC8), premissas_nivel_cargo_letra, 0), MATCH(VALUE(LEFT(AC8)), premissas_nivel_cargo_numero, 0)), F8 = "Coordenador(a)", INDEX(Coordenador, MATCH(RIGHT(AC8), premissas_nivel_cargo_letra, 0), MATCH(VALUE(LEFT(AC8)), premissas_nivel_cargo_numero, 0)), F8 = "Chefe", INDEX(Chefe, MATCH(RIGHT(AC8), premissas_nivel_cargo_letra, 0), MATCH(VALUE(LEFT(AC8)), premissas_nivel_cargo_numero, 0)), F8 = "Diretor(a)", INDEX(Diretor, MATCH(RIGHT(AC8), premissas_nivel_cargo_letra, 0), MATCH(VALUE(LEFT(AC8)), premissas_nivel_cargo_numero, 0)), F8 = "Gerente", INDEX(Gerente, MATCH(RIGHT(AC8), premissas_nivel_cargo_letra, 0), MATCH(VALUE(LEFT(AC8)), premissas_nivel_cargo_numero, 0)), F8 = "Assessor(a)", INDEX(Assessor, MATCH(RIGHT(AC8), premissas_nivel_cargo_letra, 0), MATCH(VALUE(LEFT(AC8)), premissas_nivel_cargo_numero, 0)), F8 = "Ouvidor(a)", INDEX(Ouvidor, MATCH(RIGHT(AC8), premissas_nivel_cargo_letra, 0), MATCH(VALUE(LEFT(AC8)), premissas_nivel_cargo_numero, 0)) ), "")} | AE8: =ifs(G8 = "", "", AD8 = "", "Ainda Não Classificado", NOT(AD8 = ""), "Classificado com Sucesso")
A9: =IFERROR(__xludf.dummyfunction("""COMPUTED_VALUE"""),8) | B9: =IFERROR(__xludf.dummyfunction("""COMPUTED_VALUE"""),"SMDE") | C9: =IFERROR(__xludf.dummyfunction("""COMPUTED_VALUE"""),"2º") | D9: =IFERROR(__xludf.dummyfunction("""COMPUTED_VALUE"""),"Chefia de Gabinete") | E9: =IFERROR(__xludf.dummyfunction("""COMPUTED_VALUE"""),"Chefe de Gabinete") | F9: =IFERROR(__xludf.dummyfunction("""COMPUTED_VALUE"""),"Chefe") | G9: =IFERROR(__xludf.dummyfunction("""COMPUTED_VALUE"""),"Administrativo") | H9: =IFERROR(__xludf.dummyfunction("""COMPUTED_VALUE"""),"Planejamento Urbano e Econômico") | I9: #NAME? | J9: #NAME? | K9: #NAME? | L9: #NAME? | M9: #NAME? | N9: #NAME? | S9: #NAME? | T9: #NAME? | U9: #NAME? | V9: #NAME? | W9: #NAME? | X9: #NAME? | Y9: 0 | Z9: Não | AA9: 0 | AB9: Baixa | AD9: {=IFERROR(ifs( F9 = "Secretário(a)", INDEX(Secretario, MATCH(RIGHT(AC9), premissas_nivel_cargo_letra, 0), MATCH(VALUE(LEFT(AC9)), premissas_nivel_cargo_numero, 0)), F9 = "Presidente", INDEX(Presidente, MATCH(RIGHT(AC9), premissas_nivel_cargo_letra, 0), MATCH(VALUE(LEFT(AC9)), premissas_nivel_cargo_numero, 0)), F9 = "Subsecretário(a)", INDEX(Subsecretario, MATCH(RIGHT(AC9), premissas_nivel_cargo_letra, 0), MATCH(VALUE(LEFT(AC9)), premissas_nivel_cargo_numero, 0)), F9 = "Superintendente", INDEX(Superintendente, MATCH(RIGHT(AC9), premissas_nivel_cargo_letra, 0), MATCH(VALUE(LEFT(AC9)), premissas_nivel_cargo_numero, 0)), F9 = "Coordenador(a)", INDEX(Coordenador, MATCH(RIGHT(AC9), premissas_nivel_cargo_letra, 0), MATCH(VALUE(LEFT(AC9)), premissas_nivel_cargo_numero, 0)), F9 = "Chefe", INDEX(Chefe, MATCH(RIGHT(AC9), premissas_nivel_cargo_letra, 0), MATCH(VALUE(LEFT(AC9)), premissas_nivel_cargo_numero, 0)), F9 = "Diretor(a)", INDEX(Diretor, MATCH(RIGHT(AC9), premissas_nivel_cargo_letra, 0), MATCH(VALUE(LEFT(AC9)), premissas_nivel_cargo_numero, 0)), F9 = "Gerente", INDEX(Gerente, MATCH(RIGHT(AC9), premissas_nivel_cargo_letra, 0), MATCH(VALUE(LEFT(AC9)), premissas_nivel_cargo_numero, 0)), F9 = "Assessor(a)", INDEX(Assessor, MATCH(RIGHT(AC9), premissas_nivel_cargo_letra, 0), MATCH(VALUE(LEFT(AC9)), premissas_nivel_cargo_numero, 0)), F9 = "Ouvidor(a)", INDEX(Ouvidor, MATCH(RIGHT(AC9), premissas_nivel_cargo_letra, 0), MATCH(VALUE(LEFT(AC9)), premissas_nivel_cargo_numero, 0)) ), "")} | AE9: =ifs(G9 = "", "", AD9 = "", "Ainda Não Classificado", NOT(AD9 = ""), "Classificado com Sucesso")
A10: =IFERROR(__xludf.dummyfunction("""COMPUTED_VALUE"""),9) | B10: =IFERROR(__xludf.dummyfunction("""COMPUTED_VALUE"""),"SMDE") | C10: =IFERROR(__xludf.dummyfunction("""COMPUTED_VALUE"""),"2º") | D10: =IFERROR(__xludf.dummyfunction("""COMPUTED_VALUE"""),"Subsecretaria de Desenvolvimento Econômico e Inovação") | E10: =IFERROR(__xludf.dummyfunction("""COMPUTED_VALUE"""),"Subsecretário") | F10: =IFERROR(__xludf.dummyfunction("""COMPUTED_VALUE"""),"Subsecretário(a)") | G10: =IFERROR(__xludf.dummyfunction("""COMPUTED_VALUE"""),"Técnico-Operacional") | H10: =IFERROR(__xludf.dummyfunction("""COMPUTED_VALUE"""),"Planejamento Urbano e Econômico") | I10: #NAME? | J10: #NAME? | K10: #NAME? | L10: #NAME? | M10: #NAME? | N10: #NAME? | S10: #NAME? | T10: #NAME? | U10: #NAME? | V10: #NAME? | W10: #NAME? | X10: #NAME? | Y10: 0 | Z10: Não | AA10: 0 | AB10: Baixa | AD10: {=IFERROR(ifs( F10 = "Secretário(a)", INDEX(Secretario, MATCH(RIGHT(AC10), premissas_nivel_cargo_letra, 0), MATCH(VALUE(LEFT(AC10)), premissas_nivel_cargo_numero, 0)), F10 = "Presidente", INDEX(Presidente, MATCH(RIGHT(AC10), premissas_nivel_cargo_letra, 0), MATCH(VALUE(LEFT(AC10)), premissas_nivel_cargo_numero, 0)), F10 = "Subsecretário(a)", INDEX(Subsecretario, MATCH(RIGHT(AC10), premissas_nivel_cargo_letra, 0), MATCH(VALUE(LEFT(AC10)), premissas_nivel_cargo_numero, 0)), F10 = "Superintendente", INDEX(Superintendente, MATCH(RIGHT(AC10), premissas_nivel_cargo_letra, 0), MATCH(VALUE(LEFT(AC10)), premissas_nivel_cargo_numero, 0)), F10 = "Coordenador(a)", INDEX(Coordenador, MATCH(RIGHT(AC10), premissas_nivel_cargo_letra, 0), MATCH(VALUE(LEFT(AC10)), premissas_nivel_cargo_numero, 0)), F10 = "Chefe", INDEX(Chefe, MATCH(RIGHT(AC10), premissas_nivel_cargo_letra, 0), MATCH(VALUE(LEFT(AC10)), premissas_nivel_cargo_numero, 0)), F10 = "Diretor(a)", INDEX(Diretor, MATCH(RIGHT(AC10), premissas_nivel_cargo_letra, 0), MATCH(VALUE(LEFT(AC10)), premissas_nivel_cargo_numero, 0)), F10 = "Gerente", INDEX(Gerente, MATCH(RIGHT(AC10), premissas_nivel_cargo_letra, 0), MATCH(VALUE(LEFT(AC10)), premissas_nivel_cargo_numero, 0)), F10 = "Assessor(a)", INDEX(Assessor, MATCH(RIGHT(AC10), premissas_nivel_cargo_letra, 0), MATCH(VALUE(LEFT(AC10)), premissas_nivel_cargo_numero, 0)), F10 = "Ouvidor(a)", INDEX(Ouvidor, MATCH(RIGHT(AC10), premissas_nivel_cargo_letra, 0), MATCH(VALUE(LEFT(AC10)), premissas_nivel_cargo_numero, 0)) ), "")} | AE10: =ifs(G10 = "", "", AD10 = "", "Ainda Não Classificado", NOT(AD10 = ""), "Classificado com Sucesso")
A11: =IFERROR(__xludf.dummyfunction("""COMPUTED_VALUE"""),10) | B11: =IFERROR(__xludf.dummyfunction("""COMPUTED_VALUE"""),"SMDE") | C11: =IFERROR(__xludf.dummyfunction("""COMPUTED_VALUE"""),"3º") | D11: =IFERROR(__xludf.dummyfunction("""COMPUTED_VALUE"""),"Escritório de Política Econômica") | E11: =IFERROR(__xludf.dummyfunction("""COMPUTED_VALUE"""),"Diretor I") | F11: =IFERROR(__xludf.dummyfunction("""COMPUTED_VALUE"""),"Diretor(a)") | G11: =IFERROR(__xludf.dummyfunction("""COMPUTED_VALUE"""),"Administrativo") | H11: =IFERROR(__xludf.dummyfunction("""COMPUTED_VALUE"""),"Planejamento Urbano e Econômico") | I11: #NAME? | J11: #NAME? | K11: #NAME? | L11: #NAME? | M11: #NAME? | N11: #NAME? | S11: #NAME? | T11: #NAME? | U11: #NAME? | V11: #NAME? | W11: #NAME? | X11: #NAME? | Y11: 0 | Z11: Não | AA11: 0 | AB11: Baixa | AD11: {=IFERROR(ifs( F11 = "Secretário(a)", INDEX(Secretario, MATCH(RIGHT(AC11), premissas_nivel_cargo_letra, 0), MATCH(VALUE(LEFT(AC11)), premissas_nivel_cargo_numero, 0)), F11 = "Presidente", INDEX(Presidente, MATCH(RIGHT(AC11), premissas_nivel_cargo_letra, 0), MATCH(VALUE(LEFT(AC11)), premissas_nivel_cargo_numero, 0)), F11 = "Subsecretário(a)", INDEX(Subsecretario, MATCH(RIGHT(AC11), premissas_nivel_cargo_letra, 0), MATCH(VALUE(LEFT(AC11)), premissas_nivel_cargo_numero, 0)), F11 = "Superintendente", INDEX(Superintendente, MATCH(RIGHT(AC11), premissas_nivel_cargo_letra, 0), MATCH(VALUE(LEFT(AC11)), premissas_nivel_cargo_numero, 0)), F11 = "Coordenador(a)", INDEX(Coordenador, MATCH(RIGHT(AC11), premissas_nivel_cargo_letra, 0), MATCH(VALUE(LEFT(AC11)), premissas_nivel_cargo_numero, 0)), F11 = "Chefe", INDEX(Chefe, MATCH(RIGHT(AC11), premissas_nivel_cargo_letra, 0), MATCH(VALUE(LEFT(AC11)), premissas_nivel_cargo_numero, 0)), F11 = "Diretor(a)", INDEX(Diretor, MATCH(RIGHT(AC11), premissas_nivel_cargo_letra, 0), MATCH(VALUE(LEFT(AC11)), premissas_nivel_cargo_numero, 0)), F11 = "Gerente", INDEX(Gerente, MATCH(RIGHT(AC11), premissas_nivel_cargo_letra, 0), MATCH(VALUE(LEFT(AC11)), premissas_nivel_cargo_numero, 0)), F11 = "Assessor(a)", INDEX(Assessor, MATCH(RIGHT(AC11), premissas_nivel_cargo_letra, 0), MATCH(VALUE(LEFT(AC11)), premissas_nivel_cargo_numero, 0)), F11 = "Ouvidor(a)", INDEX(Ouvidor, MATCH(RIGHT(AC11), premissas_nivel_cargo_letra, 0), MATCH(VALUE(LEFT(AC11)), premissas_nivel_cargo_numero, 0)) ), "")} | AE11: =ifs(G11 = "", "", AD11 = "", "Ainda Não Classificado", NOT(AD11 = ""), "Classificado com Sucesso")
A12: =IFERROR(__xludf.dummyfunction("""COMPUTED_VALUE"""),11) | B12: =IFERROR(__xludf.dummyfunction("""COMPUTED_VALUE"""),"SMDE") | C12: =IFERROR(__xludf.dummyfunction("""COMPUTED_VALUE"""),"3º") | D12: =IFERROR(__xludf.dummyfunction("""COMPUTED_VALUE"""),"Escritório de Monitoramento e Processamento de Dados") | E12: =IFERROR(__xludf.dummyfunction("""COMPUTED_VALUE"""),"Diretor I") | F12: =IFERROR(__xludf.dummyfunction("""COMPUTED_VALUE"""),"Diretor(a)") | G12: =IFERROR(__xludf.dummyfunction("""COMPUTED_VALUE"""),"Técnico-Operacional") | H12: =IFERROR(__xludf.dummyfunction("""COMPUTED_VALUE"""),"Planejamento Urbano e Econômico") | I12: #NAME? | J12: #NAME? | K12: #NAME? | L12: #NAME? | M12: #NAME? | N12: #NAME? | S12: #NAME? | T12: #NAME? | U12: #NAME? | V12: #NAME? | W12: #NAME? | X12: #NAME? | Y12: 0 | Z12: Não | AA12: 0 | AB12: Baixa | AD12: {=IFERROR(ifs( F12 = "Secretário(a)", INDEX(Secretario, MATCH(RIGHT(AC12), premissas_nivel_cargo_letra, 0), MATCH(VALUE(LEFT(AC12)), premissas_nivel_cargo_numero, 0)), F12 = "Presidente", INDEX(Presidente, MATCH(RIGHT(AC12), premissas_nivel_cargo_letra, 0), MATCH(VALUE(LEFT(AC12)), premissas_nivel_cargo_numero, 0)), F12 = "Subsecretário(a)", INDEX(Subsecretario, MATCH(RIGHT(AC12), premissas_nivel_cargo_letra, 0), MATCH(VALUE(LEFT(AC12)), premissas_nivel_cargo_numero, 0)), F12 = "Superintendente", INDEX(Superintendente, MATCH(RIGHT(AC12), premissas_nivel_cargo_letra, 0), MATCH(VALUE(LEFT(AC12)), premissas_nivel_cargo_numero, 0)), F12 = "Coordenador(a)", INDEX(Coordenador, MATCH(RIGHT(AC12), premissas_nivel_cargo_letra, 0), MATCH(VALUE(LEFT(AC12)), premissas_nivel_cargo_numero, 0)), F12 = "Chefe", INDEX(Chefe, MATCH(RIGHT(AC12), premissas_nivel_cargo_letra, 0), MATCH(VALUE(LEFT(AC12)), premissas_nivel_cargo_numero, 0)), F12 = "Diretor(a)", INDEX(Diretor, MATCH(RIGHT(AC12), premissas_nivel_cargo_letra, 0), MATCH(VALUE(LEFT(AC12)), premissas_nivel_cargo_numero, 0)), F12 = "Gerente", INDEX(Gerente, MATCH(RIGHT(AC12), premissas_nivel_cargo_letra, 0), MATCH(VALUE(LEFT(AC12)), premissas_nivel_cargo_numero, 0)), F12 = "Assessor(a)", INDEX(Assessor, MATCH(RIGHT(AC12), premissas_nivel_cargo_letra, 0), MATCH(VALUE(LEFT(AC12)), premissas_nivel_cargo_numero, 0)), F12 = "Ouvidor(a)", INDEX(Ouvidor, MATCH(RIGHT(AC12), premissas_nivel_cargo_letra, 0), MATCH(VALUE(LEFT(AC12)), premissas_nivel_cargo_numero, 0)) ), "")} | AE12: =ifs(G12 = "", "", AD12 = "", "Ainda Não Classificado", NOT(AD12 = ""), "Classificado com Sucesso")
A13: =IFERROR(__xludf.dummyfunction("""COMPUTED_VALUE"""),12) | B13: =IFERROR(__xludf.dummyfunction("""COMPUTED_VALUE"""),"SMDE") | C13: =IFERROR(__xludf.dummyfunction("""COMPUTED_VALUE"""),"2º") | D13: =IFERROR(__xludf.dummyfunction("""COMPUTED_VALUE"""),"Subsecretaria de Regulação e Ambiente de Negócios") | E13: =IFERROR(__xludf.dummyfunction("""COMPUTED_VALUE"""),"Subsecretário") | F13: =IFERROR(__xludf.dummyfunction("""COMPUTED_VALUE"""),"Subsecretário(a)") | G13: =IFERROR(__xludf.dummyfunction("""COMPUTED_VALUE"""),"Técnico-Operacional") | H13: =IFERROR(__xludf.dummyfunction("""COMPUTED_VALUE"""),"Planejamento Urbano e Econômico") | I13: #NAME? | J13: #NAME? | K13: #NAME? | L13: #NAME? | M13: #NAME? | N13: #NAME? | S13: #NAME? | T13: #NAME? | U13: #NAME? | V13: #NAME? | W13: #NAME? | X13: #NAME? | Y13: 0 | Z13: Não | AA13: 0 | AB13: Baixa | AD13: {=IFERROR(ifs( F13 = "Secretário(a)", INDEX(Secretario, MATCH(RIGHT(AC13), premissas_nivel_cargo_letra, 0), MATCH(VALUE(LEFT(AC13)), premissas_nivel_cargo_numero, 0)), F13 = "Presidente", INDEX(Presidente, MATCH(RIGHT(AC13), premissas_nivel_cargo_letra, 0), MATCH(VALUE(LEFT(AC13)), premissas_nivel_cargo_numero, 0)), F13 = "Subsecretário(a)", INDEX(Subsecretario, MATCH(RIGHT(AC13), premissas_nivel_cargo_letra, 0), MATCH(VALUE(LEFT(AC13)), premissas_nivel_cargo_numero, 0)), F13 = "Superintendente", INDEX(Superintendente, MATCH(RIGHT(AC13), premissas_nivel_cargo_letra, 0), MATCH(VALUE(LEFT(AC13)), premissas_nivel_cargo_numero, 0)), F13 = "Coordenador(a)", INDEX(Coordenador, MATCH(RIGHT(AC13), premissas_nivel_cargo_letra, 0), MATCH(VALUE(LEFT(AC13)), premissas_nivel_cargo_numero, 0)), F13 = "Chefe", INDEX(Chefe, MATCH(RIGHT(AC13), premissas_nivel_cargo_letra, 0), MATCH(VALUE(LEFT(AC13)), premissas_nivel_cargo_numero, 0)), F13 = "Diretor(a)", INDEX(Diretor, MATCH(RIGHT(AC13), premissas_nivel_cargo_letra, 0), MATCH(VALUE(LEFT(AC13)), premissas_nivel_cargo_numero, 0)), F13 = "Gerente", INDEX(Gerente, MATCH(RIGHT(AC13), premissas_nivel_cargo_letra, 0), MATCH(VALUE(LEFT(AC13)), premissas_nivel_cargo_numero, 0)), F13 = "Assessor(a)", INDEX(Assessor, MATCH(RIGHT(AC13), premissas_nivel_cargo_letra, 0), MATCH(VALUE(LEFT(AC13)), premissas_nivel_cargo_numero, 0)), F13 = "Ouvidor(a)", INDEX(Ouvidor, MATCH(RIGHT(AC13), premissas_nivel_cargo_letra, 0), MATCH(VALUE(LEFT(AC13)), premissas_nivel_cargo_numero, 0)) ), "")} | AE13: =ifs(G13 = "", "", AD13 = "", "Ainda Não Classificado", NOT(AD13 = ""), "Classificado com Sucesso")
A14: =IFERROR(__xludf.dummyfunction("""COMPUTED_VALUE"""),13) | B14: =IFERROR(__xludf.dummyfunction("""COMPUTED_VALUE"""),"SMDE") | C14: =IFERROR(__xludf.dummyfunction("""COMPUTED_VALUE"""),"3º") | D14: =IFERROR(__xludf.dummyfunction("""COMPUTED_VALUE"""),"Coordenadoria de Análise do Estoque Regulatório") | E14: =IFERROR(__xludf.dummyfunction("""COMPUTED_VALUE"""),"Coordenador I") | F14: =IFERROR(__xludf.dummyfunction("""COMPUTED_VALUE"""),"Coordenador(a)") | G14: =IFERROR(__xludf.dummyfunction("""COMPUTED_VALUE"""),"Técnico-Operacional") | H14: =IFERROR(__xludf.dummyfunction("""COMPUTED_VALUE"""),"Planejamento Urbano e Econômico") | I14: #NAME? | J14: #NAME? | K14: #NAME? | L14: #NAME? | M14: #NAME? | N14: #NAME? | S14: #NAME? | T14: #NAME? | U14: #NAME? | V14: #NAME? | W14: #NAME? | X14: #NAME? | Y14: 0 | Z14: Não | AA14: 0 | AB14: Baixa | AD14: {=IFERROR(ifs( F14 = "Secretário(a)", INDEX(Secretario, MATCH(RIGHT(AC14), premissas_nivel_cargo_letra, 0), MATCH(VALUE(LEFT(AC14)), premissas_nivel_cargo_numero, 0)), F14 = "Presidente", INDEX(Presidente, MATCH(RIGHT(AC14), premissas_nivel_cargo_letra, 0), MATCH(VALUE(LEFT(AC14)), premissas_nivel_cargo_numero, 0)), F14 = "Subsecretário(a)", INDEX(Subsecretario, MATCH(RIGHT(AC14), premissas_nivel_cargo_letra, 0), MATCH(VALUE(LEFT(AC14)), premissas_nivel_cargo_numero, 0)), F14 = "Superintendente", INDEX(Superintendente, MATCH(RIGHT(AC14), premissas_nivel_cargo_letra, 0), MATCH(VALUE(LEFT(AC14)), premissas_nivel_cargo_numero, 0)), F14 = "Coordenador(a)", INDEX(Coordenador, MATCH(RIGHT(AC14), premissas_nivel_cargo_letra, 0), MATCH(VALUE(LEFT(AC14)), premissas_nivel_cargo_numero, 0)), F14 = "Chefe", INDEX(Chefe, MATCH(RIGHT(AC14), premissas_nivel_cargo_letra, 0), MATCH(VALUE(LEFT(AC14)), premissas_nivel_cargo_numero, 0)), F14 = "Diretor(a)", INDEX(Diretor, MATCH(RIGHT(AC14), premissas_nivel_cargo_letra, 0), MATCH(VALUE(LEFT(AC14)), premissas_nivel_cargo_numero, 0)), F14 = "Gerente", INDEX(Gerente, MATCH(RIGHT(AC14), premissas_nivel_cargo_letra, 0), MATCH(VALUE(LEFT(AC14)), premissas_nivel_cargo_numero, 0)), F14 = "Assessor(a)", INDEX(Assessor, MATCH(RIGHT(AC14), premissas_nivel_cargo_letra, 0), MATCH(VALUE(LEFT(AC14)), premissas_nivel_cargo_numero, 0)), F14 = "Ouvidor(a)", INDEX(Ouvidor, MATCH(RIGHT(AC14), premissas_nivel_cargo_letra, 0), MATCH(VALUE(LEFT(AC14)), premissas_nivel_cargo_numero, 0)) ), "")} | AE14: =ifs(G14 = "", "", AD14 = "", "Ainda Não Classificado", NOT(AD14 = ""), "Classificado com Sucesso")
A15: =IFERROR(__xludf.dummyfunction("""COMPUTED_VALUE"""),14) | B15: =IFERROR(__xludf.dummyfunction("""COMPUTED_VALUE"""),"SMDE") | C15: =IFERROR(__xludf.dummyfunction("""COMPUTED_VALUE"""),"3º") | D15: =IFERROR(__xludf.dummyfunction("""COMPUTED_VALUE"""),"Coordenadoria de Avaliação de Impacto Regulatório") | E15: =IFERROR(__xludf.dummyfunction("""COMPUTED_VALUE"""),"Coordenador I") | F15: =IFERROR(__xludf.dummyfunction("""COMPUTED_VALUE"""),"Coordenador(a)") | G15: =IFERROR(__xludf.dummyfunction("""COMPUTED_VALUE"""),"Técnico-Operacional") | H15: =IFERROR(__xludf.dummyfunction("""COMPUTED_VALUE"""),"Planejamento Urbano e Econômico") | I15: #NAME? | J15: #NAME? | K15: #NAME? | L15: #NAME? | M15: #NAME? | N15: #NAME? | S15: #NAME? | T15: #NAME? | U15: #NAME? | V15: #NAME? | W15: #NAME? | X15: #NAME? | Y15: 0 | Z15: Não | AA15: 0 | AB15: Baixa | AD15: {=IFERROR(ifs( F15 = "Secretário(a)", INDEX(Secretario, MATCH(RIGHT(AC15), premissas_nivel_cargo_letra, 0), MATCH(VALUE(LEFT(AC15)), premissas_nivel_cargo_numero, 0)), F15 = "Presidente", INDEX(Presidente, MATCH(RIGHT(AC15), premissas_nivel_cargo_letra, 0), MATCH(VALUE(LEFT(AC15)), premissas_nivel_cargo_numero, 0)), F15 = "Subsecretário(a)", INDEX(Subsecretario, MATCH(RIGHT(AC15), premissas_nivel_cargo_letra, 0), MATCH(VALUE(LEFT(AC15)), premissas_nivel_cargo_numero, 0)), F15 = "Superintendente", INDEX(Superintendente, MATCH(RIGHT(AC15), premissas_nivel_cargo_letra, 0), MATCH(VALUE(LEFT(AC15)), premissas_nivel_cargo_numero, 0)), F15 = "Coordenador(a)", INDEX(Coordenador, MATCH(RIGHT(AC15), premissas_nivel_cargo_letra, 0), MATCH(VALUE(LEFT(AC15)), premissas_nivel_cargo_numero, 0)), F15 = "Chefe", INDEX(Chefe, MATCH(RIGHT(AC15), premissas_nivel_cargo_letra, 0), MATCH(VALUE(LEFT(AC15)), premissas_nivel_cargo_numero, 0)), F15 = "Diretor(a)", INDEX(Diretor, MATCH(RIGHT(AC15), premissas_nivel_cargo_letra, 0), MATCH(VALUE(LEFT(AC15)), premissas_nivel_cargo_numero, 0)), F15 = "Gerente", INDEX(Gerente, MATCH(RIGHT(AC15), premissas_nivel_cargo_letra, 0), MATCH(VALUE(LEFT(AC15)), premissas_nivel_cargo_numero, 0)), F15 = "Assessor(a)", INDEX(Assessor, MATCH(RIGHT(AC15), premissas_nivel_cargo_letra, 0), MATCH(VALUE(LEFT(AC15)), premissas_nivel_cargo_numero, 0)), F15 = "Ouvidor(a)", INDEX(Ouvidor, MATCH(RIGHT(AC15), premissas_nivel_cargo_letra, 0), MATCH(VALUE(LEFT(AC15)), premissas_nivel_cargo_numero, 0)) ), "")} | AE15: =ifs(G15 = "", "", AD15 = "", "Ainda Não Classificado", NOT(AD15 = ""), "Classificado com Sucesso")
A16: =IFERROR(__xludf.dummyfunction("""COMPUTED_VALUE"""),15) | B16: =IFERROR(__xludf.dummyfunction("""COMPUTED_VALUE"""),"SMDE") | C16: =IFERROR(__xludf.dummyfunction("""COMPUTED_VALUE"""),"3º") | D16: =IFERROR(__xludf.dummyfunction("""COMPUTED_VALUE"""),"Laboratório de Inovação") | E16: =IFERROR(__xludf.dummyfunction("""COMPUTED_VALUE"""),"Diretor I") | F16: =IFERROR(__xludf.dummyfunction("""COMPUTED_VALUE"""),"Diretor(a)") | G16: =IFERROR(__xludf.dummyfunction("""COMPUTED_VALUE"""),"Técnico-Operacional") | H16: =IFERROR(__xludf.dummyfunction("""COMPUTED_VALUE"""),"Planejamento Urbano e Econômico") | I16: #NAME? | J16: #NAME? | K16: #NAME? | L16: #NAME? | M16: #NAME? | N16: #NAME? | S16: #NAME? | T16: #NAME? | U16: #NAME? | V16: #NAME? | W16: #NAME? | X16: #NAME? | Y16: 0 | Z16: Não | AA16: 0 | AB16: Baixa | AD16: {=IFERROR(ifs( F16 = "Secretário(a)", INDEX(Secretario, MATCH(RIGHT(AC16), premissas_nivel_cargo_letra, 0), MATCH(VALUE(LEFT(AC16)), premissas_nivel_cargo_numero, 0)), F16 = "Presidente", INDEX(Presidente, MATCH(RIGHT(AC16), premissas_nivel_cargo_letra, 0), MATCH(VALUE(LEFT(AC16)), premissas_nivel_cargo_numero, 0)), F16 = "Subsecretário(a)", INDEX(Subsecretario, MATCH(RIGHT(AC16), premissas_nivel_cargo_letra, 0), MATCH(VALUE(LEFT(AC16)), premissas_nivel_cargo_numero, 0)), F16 = "Superintendente", INDEX(Superintendente, MATCH(RIGHT(AC16), premissas_nivel_cargo_letra, 0), MATCH(VALUE(LEFT(AC16)), premissas_nivel_cargo_numero, 0)), F16 = "Coordenador(a)", INDEX(Coordenador, MATCH(RIGHT(AC16), premissas_nivel_cargo_letra, 0), MATCH(VALUE(LEFT(AC16)), premissas_nivel_cargo_numero, 0)), F16 = "Chefe", INDEX(Chefe, MATCH(RIGHT(AC16), premissas_nivel_cargo_letra, 0), MATCH(VALUE(LEFT(AC16)), premissas_nivel_cargo_numero, 0)), F16 = "Diretor(a)", INDEX(Diretor, MATCH(RIGHT(AC16), premissas_nivel_cargo_letra, 0), MATCH(VALUE(LEFT(AC16)), premissas_nivel_cargo_numero, 0)), F16 = "Gerente", INDEX(Gerente, MATCH(RIGHT(AC16), premissas_nivel_cargo_letra, 0), MATCH(VALUE(LEFT(AC16)), premissas_nivel_cargo_numero, 0)), F16 = "Assessor(a)", INDEX(Assessor, MATCH(RIGHT(AC16), premissas_nivel_cargo_letra, 0), MATCH(VALUE(LEFT(AC16)), premissas_nivel_cargo_numero, 0)), F16 = "Ouvidor(a)", INDEX(Ouvidor, MATCH(RIGHT(AC16), premissas_nivel_cargo_letra, 0), MATCH(VALUE(LEFT(AC16)), premissas_nivel_cargo_numero, 0)) ), "")} | AE16: =ifs(G16 = "", "", AD16 = "", "Ainda Não Classificado", NOT(AD16 = ""), "Classificado com Sucesso")
A17: =IFERROR(__xludf.dummyfunction("""COMPUTED_VALUE"""),16) | B17: =IFERROR(__xludf.dummyfunction("""COMPUTED_VALUE"""),"CASA CIVIL") | C17: =IFERROR(__xludf.dummyfunction("""COMPUTED_VALUE"""),"1º") | D17: =IFERROR(__xludf.dummyfunction("""COMPUTED_VALUE"""),"Secretaria Municipal da Casa Civil") | E17: =IFERROR(__xludf.dummyfunction("""COMPUTED_VALUE"""),"Secretário Municipal") | F17: =IFERROR(__xludf.dummyfunction("""COMPUTED_VALUE"""),"Secretário(a)") | G17: =IFERROR(__xludf.dummyfunction("""COMPUTED_VALUE"""),"Administrativo") | H17: =IFERROR(__xludf.dummyfunction("""COMPUTED_VALUE"""),"Gestão") | I17: #NAME? | J17: #NAME? | K17: #NAME? | L17: #NAME? | M17: #NAME? | N17: #NAME? | S17: #NAME? | T17: #NAME? | U17: #NAME? | V17: #NAME? | W17: #NAME? | X17: #NAME? | Y17: 0 | Z17: Não | AA17: 0 | AB17: Baixa | AD17: {=IFERROR(ifs( F17 = "Secretário(a)", INDEX(Secretario, MATCH(RIGHT(AC17), premissas_nivel_cargo_letra, 0), MATCH(VALUE(LEFT(AC17)), premissas_nivel_cargo_numero, 0)), F17 = "Presidente", INDEX(Presidente, MATCH(RIGHT(AC17), premissas_nivel_cargo_letra, 0), MATCH(VALUE(LEFT(AC17)), premissas_nivel_cargo_numero, 0)), F17 = "Subsecretário(a)", INDEX(Subsecretario, MATCH(RIGHT(AC17), premissas_nivel_cargo_letra, 0), MATCH(VALUE(LEFT(AC17)), premissas_nivel_cargo_numero, 0)), F17 = "Superintendente", INDEX(Superintendente, MATCH(RIGHT(AC17), premissas_nivel_cargo_letra, 0), MATCH(VALUE(LEFT(AC17)), premissas_nivel_cargo_numero, 0)), F17 = "Coordenador(a)", INDEX(Coordenador, MATCH(RIGHT(AC17), premissas_nivel_cargo_letra, 0), MATCH(VALUE(LEFT(AC17)), premissas_nivel_cargo_numero, 0)), F17 = "Chefe", INDEX(Chefe, MATCH(RIGHT(AC17), premissas_nivel_cargo_letra, 0), MATCH(VALUE(LEFT(AC17)), premissas_nivel_cargo_numero, 0)), F17 = "Diretor(a)", INDEX(Diretor, MATCH(RIGHT(AC17), premissas_nivel_cargo_letra, 0), MATCH(VALUE(LEFT(AC17)), premissas_nivel_cargo_numero, 0)), F17 = "Gerente", INDEX(Gerente, MATCH(RIGHT(AC17), premissas_nivel_cargo_letra, 0), MATCH(VALUE(LEFT(AC17)), premissas_nivel_cargo_numero, 0)), F17 = "Assessor(a)", INDEX(Assessor, MATCH(RIGHT(AC17), premissas_nivel_cargo_letra, 0), MATCH(VALUE(LEFT(AC17)), premissas_nivel_cargo_numero, 0)), F17 = "Ouvidor(a)", INDEX(Ouvidor, MATCH(RIGHT(AC17), premissas_nivel_cargo_letra, 0), MATCH(VALUE(LEFT(AC17)), premissas_nivel_cargo_numero, 0)) ), "")} | AE17: =ifs(G17 = "", "", AD17 = "", "Ainda Não Classificado", NOT(AD17 = ""), "Classificado com Sucesso")
A18: =IFERROR(__xludf.dummyfunction("""COMPUTED_VALUE"""),17) | B18: =IFERROR(__xludf.dummyfunction("""COMPUTED_VALUE"""),"CASA CIVIL") | C18: =IFERROR(__xludf.dummyfunction("""COMPUTED_VALUE"""),"2º") | D18: =IFERROR(__xludf.dummyfunction("""COMPUTED_VALUE"""),"Chefia de Gabinete") | E18: =IFERROR(__xludf.dummyfunction("""COMPUTED_VALUE"""),"Chefe de Gabinete") | F18: =IFERROR(__xludf.dummyfunction("""COMPUTED_VALUE"""),"Chefe") | G18: =IFERROR(__xludf.dummyfunction("""COMPUTED_VALUE"""),"Administrativo") | H18: =IFERROR(__xludf.dummyfunction("""COMPUTED_VALUE"""),"Gestão") | I18: #NAME? | J18: #NAME? | K18: #NAME? | L18: #NAME? | M18: #NAME? | N18: #NAME? | S18: #NAME? | T18: #NAME? | U18: #NAME? | V18: #NAME? | W18: #NAME? | X18: #NAME? | Y18: 0 | Z18: Não | AA18: 0 | AB18: Baixa | AD18: {=IFERROR(ifs( F18 = "Secretário(a)", INDEX(Secretario, MATCH(RIGHT(AC18), premissas_nivel_cargo_letra, 0), MATCH(VALUE(LEFT(AC18)), premissas_nivel_cargo_numero, 0)), F18 = "Presidente", INDEX(Presidente, MATCH(RIGHT(AC18), premissas_nivel_cargo_letra, 0), MATCH(VALUE(LEFT(AC18)), premissas_nivel_cargo_numero, 0)), F18 = "Subsecretário(a)", INDEX(Subsecretario, MATCH(RIGHT(AC18), premissas_nivel_cargo_letra, 0), MATCH(VALUE(LEFT(AC18)), premissas_nivel_cargo_numero, 0)), F18 = "Superintendente", INDEX(Superintendente, MATCH(RIGHT(AC18), premissas_nivel_cargo_letra, 0), MATCH(VALUE(LEFT(AC18)), premissas_nivel_cargo_numero, 0)), F18 = "Coordenador(a)", INDEX(Coordenador, MATCH(RIGHT(AC18), premissas_nivel_cargo_letra, 0), MATCH(VALUE(LEFT(AC18)), premissas_nivel_cargo_numero, 0)), F18 = "Chefe", INDEX(Chefe, MATCH(RIGHT(AC18), premissas_nivel_cargo_letra, 0), MATCH(VALUE(LEFT(AC18)), premissas_nivel_cargo_numero, 0)), F18 = "Diretor(a)", INDEX(Diretor, MATCH(RIGHT(AC18), premissas_nivel_cargo_letra, 0), MATCH(VALUE(LEFT(AC18)), premissas_nivel_cargo_numero, 0)), F18 = "Gerente", INDEX(Gerente, MATCH(RIGHT(AC18), premissas_nivel_cargo_letra, 0), MATCH(VALUE(LEFT(AC18)), premissas_nivel_cargo_numero, 0)), F18 = "Assessor(a)", INDEX(Assessor, MATCH(RIGHT(AC18), premissas_nivel_cargo_letra, 0), MATCH(VALUE(LEFT(AC18)), premissas_nivel_cargo_numero, 0)), F18 = "Ouvidor(a)", INDEX(Ouvidor, MATCH(RIGHT(AC18), premissas_nivel_cargo_letra, 0), MATCH(VALUE(LEFT(AC18)), premissas_nivel_cargo_numero, 0)) ), "")} | AE18: =ifs(G18 = "", "", AD18 = "", "Ainda Não Classificado", NOT(AD18 = ""), "Classificado com Sucesso")
A19: =IFERROR(__xludf.dummyfunction("""COMPUTED_VALUE"""),18) | B19: =IFERROR(__xludf.dummyfunction("""COMPUTED_VALUE"""),"CASA CIVIL") | C19: =IFERROR(__xludf.dummyfunction("""COMPUTED_VALUE"""),"2º") | D19: =IFERROR(__xludf.dummyfunction("""COMPUTED_VALUE"""),"Subsecretaria de Assuntos Institucionais") | E19: =IFERROR(__xludf.dummyfunction("""COMPUTED_VALUE"""),"Subsecretário") | F19: =IFERROR(__xludf.dummyfunction("""COMPUTED_VALUE"""),"Subsecretário(a)") | G19: =IFERROR(__xludf.dummyfunction("""COMPUTED_VALUE"""),"Administrativo") | H19: =IFERROR(__xludf.dummyfunction("""COMPUTED_VALUE"""),"Gestão") | I19: #NAME? | J19: #NAME? | K19: #NAME? | L19: #NAME? | M19: #NAME? | N19: #NAME? | S19: #NAME? | T19: #NAME? | U19: #NAME? | V19: #NAME? | W19: #NAME? | X19: #NAME? | Y19: 0 | Z19: Não | AA19: 0 | AB19: Baixa | AD19: {=IFERROR(ifs( F19 = "Secretário(a)", INDEX(Secretario, MATCH(RIGHT(AC19), premissas_nivel_cargo_letra, 0), MATCH(VALUE(LEFT(AC19)), premissas_nivel_cargo_numero, 0)), F19 = "Presidente", INDEX(Presidente, MATCH(RIGHT(AC19), premissas_nivel_cargo_letra, 0), MATCH(VALUE(LEFT(AC19)), premissas_nivel_cargo_numero, 0)), F19 = "Subsecretário(a)", INDEX(Subsecretario, MATCH(RIGHT(AC19), premissas_nivel_cargo_letra, 0), MATCH(VALUE(LEFT(AC19)), premissas_nivel_cargo_numero, 0)), F19 = "Superintendente", INDEX(Superintendente, MATCH(RIGHT(AC19), premissas_nivel_cargo_letra, 0), MATCH(VALUE(LEFT(AC19)), premissas_nivel_cargo_numero, 0)), F19 = "Coordenador(a)", INDEX(Coordenador, MATCH(RIGHT(AC19), premissas_nivel_cargo_letra, 0), MATCH(VALUE(LEFT(AC19)), premissas_nivel_cargo_numero, 0)), F19 = "Chefe", INDEX(Chefe, MATCH(RIGHT(AC19), premissas_nivel_cargo_letra, 0), MATCH(VALUE(LEFT(AC19)), premissas_nivel_cargo_numero, 0)), F19 = "Diretor(a)", INDEX(Diretor, MATCH(RIGHT(AC19), premissas_nivel_cargo_letra, 0), MATCH(VALUE(LEFT(AC19)), premissas_nivel_cargo_numero, 0)), F19 = "Gerente", INDEX(Gerente, MATCH(RIGHT(AC19), premissas_nivel_cargo_letra, 0), MATCH(VALUE(LEFT(AC19)), premissas_nivel_cargo_numero, 0)), F19 = "Assessor(a)", INDEX(Assessor, MATCH(RIGHT(AC19), premissas_nivel_cargo_letra, 0), MATCH(VALUE(LEFT(AC19)), premissas_nivel_cargo_numero, 0)), F19 = "Ouvidor(a)", INDEX(Ouvidor, MATCH(RIGHT(AC19), premissas_nivel_cargo_letra, 0), MATCH(VALUE(LEFT(AC19)), premissas_nivel_cargo_numero, 0)) ), "")} | AE19: =ifs(G19 = "", "", AD19 = "", "Ainda Não Classificado", NOT(AD19 = ""), "Classificado com Sucesso")
A20: =IFERROR(__xludf.dummyfunction("""COMPUTED_VALUE"""),19) | B20: =IFERROR(__xludf.dummyfunction("""COMPUTED_VALUE"""),"CASA CIVIL") | C20: =IFERROR(__xludf.dummyfunction("""COMPUTED_VALUE"""),"2º") | D20: =IFERROR(__xludf.dummyfunction("""COMPUTED_VALUE"""),"Casa Militar do Prefeito") | E20: =IFERROR(__xludf.dummyfunction("""COMPUTED_VALUE"""),"Chefe da Casa Militar") | F20: =IFERROR(__xludf.dummyfunction("""COMPUTED_VALUE"""),"Chefe") | G20: =IFERROR(__xludf.dummyfunction("""COMPUTED_VALUE"""),"Técnico-Operacional") | H20: =IFERROR(__xludf.dummyfunction("""COMPUTED_VALUE"""),"Gestão") | I20: #NAME? | J20: #NAME? | K20: #NAME? | L20: #NAME? | M20: #NAME? | N20: #NAME? | S20: #NAME? | T20: #NAME? | U20: #NAME? | V20: #NAME? | W20: #NAME? | X20: #NAME? | Y20: 0 | Z20: Não | AA20: 0 | AB20: Baixa | AD20: {=IFERROR(ifs( F20 = "Secretário(a)", INDEX(Secretario, MATCH(RIGHT(AC20), premissas_nivel_cargo_letra, 0), MATCH(VALUE(LEFT(AC20)), premissas_nivel_cargo_numero, 0)), F20 = "Presidente", INDEX(Presidente, MATCH(RIGHT(AC20), premissas_nivel_cargo_letra, 0), MATCH(VALUE(LEFT(AC20)), premissas_nivel_cargo_numero, 0)), F20 = "Subsecretário(a)", INDEX(Subsecretario, MATCH(RIGHT(AC20), premissas_nivel_cargo_letra, 0), MATCH(VALUE(LEFT(AC20)), premissas_nivel_cargo_numero, 0)), F20 = "Superintendente", INDEX(Superintendente, MATCH(RIGHT(AC20), premissas_nivel_cargo_letra, 0), MATCH(VALUE(LEFT(AC20)), premissas_nivel_cargo_numero, 0)), F20 = "Coordenador(a)", INDEX(Coordenador, MATCH(RIGHT(AC20), premissas_nivel_cargo_letra, 0), MATCH(VALUE(LEFT(AC20)), premissas_nivel_cargo_numero, 0)), F20 = "Chefe", INDEX(Chefe, MATCH(RIGHT(AC20), premissas_nivel_cargo_letra, 0), MATCH(VALUE(LEFT(AC20)), premissas_nivel_cargo_numero, 0)), F20 = "Diretor(a)", INDEX(Diretor, MATCH(RIGHT(AC20), premissas_nivel_cargo_letra, 0), MATCH(VALUE(LEFT(AC20)), premissas_nivel_cargo_numero, 0)), F20 = "Gerente", INDEX(Gerente, MATCH(RIGHT(AC20), premissas_nivel_cargo_letra, 0), MATCH(VALUE(LEFT(AC20)), premissas_nivel_cargo_numero, 0)), F20 = "Assessor(a)", INDEX(Assessor, MATCH(RIGHT(AC20), premissas_nivel_cargo_letra, 0), MATCH(VALUE(LEFT(AC20)), premissas_nivel_cargo_numero, 0)), F20 = "Ouvidor(a)", INDEX(Ouvidor, MATCH(RIGHT(AC20), premissas_nivel_cargo_letra, 0), MATCH(VALUE(LEFT(AC20)), premissas_nivel_cargo_numero, 0)) ), "")} | AE20: =ifs(G20 = "", "", AD20 = "", "Ainda Não Classificado", NOT(AD20 = ""), "Classificado com Sucesso")
A21: =IFERROR(__xludf.dummyfunction("""COMPUTED_VALUE"""),20) | B21: =IFERROR(__xludf.dummyfunction("""COMPUTED_VALUE"""),"CASA CIVIL") | C21: =IFERROR(__xludf.dummyfunction("""COMPUTED_VALUE"""),"3º") | D21: =IFERROR(__xludf.dummyfunction("""COMPUTED_VALUE"""),"Superintendência de Segurança") | E21: =IFERROR(__xludf.dummyfunction("""COMPUTED_VALUE"""),"Superintendente") | F21: =IFERROR(__xludf.dummyfunction("""COMPUTED_VALUE"""),"Superintendente") | G21: =IFERROR(__xludf.dummyfunction("""COMPUTED_VALUE"""),"Técnico-Operacional") | H21: =IFERROR(__xludf.dummyfunction("""COMPUTED_VALUE"""),"Gestão") | I21: #NAME? | J21: #NAME? | K21: #NAME? | L21: #NAME? | M21: #NAME? | N21: #NAME? | S21: #NAME? | T21: #NAME? | U21: #NAME? | V21: #NAME? | W21: #NAME? | X21: #NAME? | Y21: 0 | Z21: Não | AA21: 0 | AB21: Baixa | AD21: {=IFERROR(ifs( F21 = "Secretário(a)", INDEX(Secretario, MATCH(RIGHT(AC21), premissas_nivel_cargo_letra, 0), MATCH(VALUE(LEFT(AC21)), premissas_nivel_cargo_numero, 0)), F21 = "Presidente", INDEX(Presidente, MATCH(RIGHT(AC21), premissas_nivel_cargo_letra, 0), MATCH(VALUE(LEFT(AC21)), premissas_nivel_cargo_numero, 0)), F21 = "Subsecretário(a)", INDEX(Subsecretario, MATCH(RIGHT(AC21), premissas_nivel_cargo_letra, 0), MATCH(VALUE(LEFT(AC21)), premissas_nivel_cargo_numero, 0)), F21 = "Superintendente", INDEX(Superintendente, MATCH(RIGHT(AC21), premissas_nivel_cargo_letra, 0), MATCH(VALUE(LEFT(AC21)), premissas_nivel_cargo_numero, 0)), F21 = "Coordenador(a)", INDEX(Coordenador, MATCH(RIGHT(AC21), premissas_nivel_cargo_letra, 0), MATCH(VALUE(LEFT(AC21)), premissas_nivel_cargo_numero, 0)), F21 = "Chefe", INDEX(Chefe, MATCH(RIGHT(AC21), premissas_nivel_cargo_letra, 0), MATCH(VALUE(LEFT(AC21)), premissas_nivel_cargo_numero, 0)), F21 = "Diretor(a)", INDEX(Diretor, MATCH(RIGHT(AC21), premissas_nivel_cargo_letra, 0), MATCH(VALUE(LEFT(AC21)), premissas_nivel_cargo_numero, 0)), F21 = "Gerente", INDEX(Gerente, MATCH(RIGHT(AC21), premissas_nivel_cargo_letra, 0), MATCH(VALUE(LEFT(AC21)), premissas_nivel_cargo_numero, 0)), F21 = "Assessor(a)", INDEX(Assessor, MATCH(RIGHT(AC21), premissas_nivel_cargo_letra, 0), MATCH(VALUE(LEFT(AC21)), premissas_nivel_cargo_numero, 0)), F21 = "Ouvidor(a)", INDEX(Ouvidor, MATCH(RIGHT(AC21), premissas_nivel_cargo_letra, 0), MATCH(VALUE(LEFT(AC21)), premissas_nivel_cargo_numero, 0)) ), "")} | AE21: =ifs(G21 = "", "", AD21 = "", "Ainda Não Classificado", NOT(AD21 = ""), "Classificado com Sucesso")
A22: =IFERROR(__xludf.dummyfunction("""COMPUTED_VALUE"""),21) | B22: =IFERROR(__xludf.dummyfunction("""COMPUTED_VALUE"""),"CASA CIVIL") | C22: =IFERROR(__xludf.dummyfunction("""COMPUTED_VALUE"""),"3º") | D22: =IFERROR(__xludf.dummyfunction("""COMPUTED_VALUE"""),"Gerência de Pessoal") | E22: =IFERROR(__xludf.dummyfunction("""COMPUTED_VALUE"""),"Gerente I") | F22: =IFERROR(__xludf.dummyfunction("""COMPUTED_VALUE"""),"Gerente") | G22: =IFERROR(__xludf.dummyfunction("""COMPUTED_VALUE"""),"Administrativo") | H22: =IFERROR(__xludf.dummyfunction("""COMPUTED_VALUE"""),"Gestão") | I22: #NAME? | J22: #NAME? | K22: #NAME? | L22: #NAME? | M22: #NAME? | N22: #NAME? | S22: #NAME? | T22: #NAME? | U22: #NAME? | V22: #NAME? | W22: #NAME? | X22: #NAME? | Y22: 0 | Z22: Não | AA22: 0 | AB22: Baixa | AD22: {=IFERROR(ifs( F22 = "Secretário(a)", INDEX(Secretario, MATCH(RIGHT(AC22), premissas_nivel_cargo_letra, 0), MATCH(VALUE(LEFT(AC22)), premissas_nivel_cargo_numero, 0)), F22 = "Presidente", INDEX(Presidente, MATCH(RIGHT(AC22), premissas_nivel_cargo_letra, 0), MATCH(VALUE(LEFT(AC22)), premissas_nivel_cargo_numero, 0)), F22 = "Subsecretário(a)", INDEX(Subsecretario, MATCH(RIGHT(AC22), premissas_nivel_cargo_letra, 0), MATCH(VALUE(LEFT(AC22)), premissas_nivel_cargo_numero, 0)), F22 = "Superintendente", INDEX(Superintendente, MATCH(RIGHT(AC22), premissas_nivel_cargo_letra, 0), MATCH(VALUE(LEFT(AC22)), premissas_nivel_cargo_numero, 0)), F22 = "Coordenador(a)", INDEX(Coordenador, MATCH(RIGHT(AC22), premissas_nivel_cargo_letra, 0), MATCH(VALUE(LEFT(AC22)), premissas_nivel_cargo_numero, 0)), F22 = "Chefe", INDEX(Chefe, MATCH(RIGHT(AC22), premissas_nivel_cargo_letra, 0), MATCH(VALUE(LEFT(AC22)), premissas_nivel_cargo_numero, 0)), F22 = "Diretor(a)", INDEX(Diretor, MATCH(RIGHT(AC22), premissas_nivel_cargo_letra, 0), MATCH(VALUE(LEFT(AC22)), premissas_nivel_cargo_numero, 0)), F22 = "Gerente", INDEX(Gerente, MATCH(RIGHT(AC22), premissas_nivel_cargo_letra, 0), MATCH(VALUE(LEFT(AC22)), premissas_nivel_cargo_numero, 0)), F22 = "Assessor(a)", INDEX(Assessor, MATCH(RIGHT(AC22), premissas_nivel_cargo_letra, 0), MATCH(VALUE(LEFT(AC22)), premissas_nivel_cargo_numero, 0)), F22 = "Ouvidor(a)", INDEX(Ouvidor, MATCH(RIGHT(AC22), premissas_nivel_cargo_letra, 0), MATCH(VALUE(LEFT(AC22)), premissas_nivel_cargo_numero, 0)) ), "")} | AE22: =ifs(G22 = "", "", AD22 = "", "Ainda Não Classificado", NOT(AD22 = ""), "Classificado com Sucesso")
A23: =IFERROR(__xludf.dummyfunction("""COMPUTED_VALUE"""),22) | B23: =IFERROR(__xludf.dummyfunction("""COMPUTED_VALUE"""),"CASA CIVIL") | C23: =IFERROR(__xludf.dummyfunction("""COMPUTED_VALUE"""),"3º") | D23: =IFERROR(__xludf.dummyfunction("""COMPUTED_VALUE"""),"Gerência de Inteligência") | E23: =IFERROR(__xludf.dummyfunction("""COMPUTED_VALUE"""),"Gerente II") | F23: =IFERROR(__xludf.dummyfunction("""COMPUTED_VALUE"""),"Gerente") | G23: =IFERROR(__xludf.dummyfunction("""COMPUTED_VALUE"""),"Técnico-Operacional") | H23: =IFERROR(__xludf.dummyfunction("""COMPUTED_VALUE"""),"Gestão") | I23: #NAME? | J23: #NAME? | K23: #NAME? | L23: #NAME? | M23: #NAME? | N23: #NAME? | S23: #NAME? | T23: #NAME? | U23: #NAME? | V23: #NAME? | W23: #NAME? | X23: #NAME? | Y23: 0 | Z23: Não | AA23: 0 | AB23: Baixa | AD23: {=IFERROR(ifs( F23 = "Secretário(a)", INDEX(Secretario, MATCH(RIGHT(AC23), premissas_nivel_cargo_letra, 0), MATCH(VALUE(LEFT(AC23)), premissas_nivel_cargo_numero, 0)), F23 = "Presidente", INDEX(Presidente, MATCH(RIGHT(AC23), premissas_nivel_cargo_letra, 0), MATCH(VALUE(LEFT(AC23)), premissas_nivel_cargo_numero, 0)), F23 = "Subsecretário(a)", INDEX(Subsecretario, MATCH(RIGHT(AC23), premissas_nivel_cargo_letra, 0), MATCH(VALUE(LEFT(AC23)), premissas_nivel_cargo_numero, 0)), F23 = "Superintendente", INDEX(Superintendente, MATCH(RIGHT(AC23), premissas_nivel_cargo_letra, 0), MATCH(VALUE(LEFT(AC23)), premissas_nivel_cargo_numero, 0)), F23 = "Coordenador(a)", INDEX(Coordenador, MATCH(RIGHT(AC23), premissas_nivel_cargo_letra, 0), MATCH(VALUE(LEFT(AC23)), premissas_nivel_cargo_numero, 0)), F23 = "Chefe", INDEX(Chefe, MATCH(RIGHT(AC23), premissas_nivel_cargo_letra, 0), MATCH(VALUE(LEFT(AC23)), premissas_nivel_cargo_numero, 0)), F23 = "Diretor(a)", INDEX(Diretor, MATCH(RIGHT(AC23), premissas_nivel_cargo_letra, 0), MATCH(VALUE(LEFT(AC23)), premissas_nivel_cargo_numero, 0)), F23 = "Gerente", INDEX(Gerente, MATCH(RIGHT(AC23), premissas_nivel_cargo_letra, 0), MATCH(VALUE(LEFT(AC23)), premissas_nivel_cargo_numero, 0)), F23 = "Assessor(a)", INDEX(Assessor, MATCH(RIGHT(AC23), premissas_nivel_cargo_letra, 0), MATCH(VALUE(LEFT(AC23)), premissas_nivel_cargo_numero, 0)), F23 = "Ouvidor(a)", INDEX(Ouvidor, MATCH(RIGHT(AC23), premissas_nivel_cargo_letra, 0), MATCH(VALUE(LEFT(AC23)), premissas_nivel_cargo_numero, 0)) ), "")} | AE23: =ifs(G23 = "", "", AD23 = "", "Ainda Não Classificado", NOT(AD23 = ""), "Classificado com Sucesso")
A24: =IFERROR(__xludf.dummyfunction("""COMPUTED_VALUE"""),23) | B24: =IFERROR(__xludf.dummyfunction("""COMPUTED_VALUE"""),"CASA CIVIL") | C24: =IFERROR(__xludf.dummyfunction("""COMPUTED_VALUE"""),"3º") | D24: =IFERROR(__xludf.dummyfunction("""COMPUTED_VALUE"""),"Gerência de Administração") | E24: =IFERROR(__xludf.dummyfunction("""COMPUTED_VALUE"""),"Gerente II") | F24: =IFERROR(__xludf.dummyfunction("""COMPUTED_VALUE"""),"Gerente") | G24: =IFERROR(__xludf.dummyfunction("""COMPUTED_VALUE"""),"Administrativo") | H24: =IFERROR(__xludf.dummyfunction("""COMPUTED_VALUE"""),"Gestão") | I24: #NAME? | J24: #NAME? | K24: #NAME? | L24: #NAME? | M24: #NAME? | N24: #NAME? | S24: #NAME? | T24: #NAME? | U24: #NAME? | V24: #NAME? | W24: #NAME? | X24: #NAME? | Y24: 0 | Z24: Não | AA24: 0 | AB24: Baixa | AD24: {=IFERROR(ifs( F24 = "Secretário(a)", INDEX(Secretario, MATCH(RIGHT(AC24), premissas_nivel_cargo_letra, 0), MATCH(VALUE(LEFT(AC24)), premissas_nivel_cargo_numero, 0)), F24 = "Presidente", INDEX(Presidente, MATCH(RIGHT(AC24), premissas_nivel_cargo_letra, 0), MATCH(VALUE(LEFT(AC24)), premissas_nivel_cargo_numero, 0)), F24 = "Subsecretário(a)", INDEX(Subsecretario, MATCH(RIGHT(AC24), premissas_nivel_cargo_letra, 0), MATCH(VALUE(LEFT(AC24)), premissas_nivel_cargo_numero, 0)), F24 = "Superintendente", INDEX(Superintendente, MATCH(RIGHT(AC24), premissas_nivel_cargo_letra, 0), MATCH(VALUE(LEFT(AC24)), premissas_nivel_cargo_numero, 0)), F24 = "Coordenador(a)", INDEX(Coordenador, MATCH(RIGHT(AC24), premissas_nivel_cargo_letra, 0), MATCH(VALUE(LEFT(AC24)), premissas_nivel_cargo_numero, 0)), F24 = "Chefe", INDEX(Chefe, MATCH(RIGHT(AC24), premissas_nivel_cargo_letra, 0), MATCH(VALUE(LEFT(AC24)), premissas_nivel_cargo_numero, 0)), F24 = "Diretor(a)", INDEX(Diretor, MATCH(RIGHT(AC24), premissas_nivel_cargo_letra, 0), MATCH(VALUE(LEFT(AC24)), premissas_nivel_cargo_numero, 0)), F24 = "Gerente", INDEX(Gerente, MATCH(RIGHT(AC24), premissas_nivel_cargo_letra, 0), MATCH(VALUE(LEFT(AC24)), premissas_nivel_cargo_numero, 0)), F24 = "Assessor(a)", INDEX(Assessor, MATCH(RIGHT(AC24), premissas_nivel_cargo_letra, 0), MATCH(VALUE(LEFT(AC24)), premissas_nivel_cargo_numero, 0)), F24 = "Ouvidor(a)", INDEX(Ouvidor, MATCH(RIGHT(AC24), premissas_nivel_cargo_letra, 0), MATCH(VALUE(LEFT(AC24)), premissas_nivel_cargo_numero, 0)) ), "")} | AE24: =ifs(G24 = "", "", AD24 = "", "Ainda Não Classificado", NOT(AD24 = ""), "Classificado com Sucesso")
A25: =IFERROR(__xludf.dummyfunction("""COMPUTED_VALUE"""),24) | B25: =IFERROR(__xludf.dummyfunction("""COMPUTED_VALUE"""),"CASA CIVIL") | C25: =IFERROR(__xludf.dummyfunction("""COMPUTED_VALUE"""),"2º") | D25: =IFERROR(__xludf.dummyfunction("""COMPUTED_VALUE"""),"Subsecretaria de Transformação Digital e Cidade Inteligente") | E25: =IFERROR(__xludf.dummyfunction("""COMPUTED_VALUE"""),"Subsecretário") | F25: =IFERROR(__xludf.dummyfunction("""COMPUTED_VALUE"""),"Subsecretário(a)") | G25: =IFERROR(__xludf.dummyfunction("""COMPUTED_VALUE"""),"Tecnologias da Informação") | H25: =IFERROR(__xludf.dummyfunction("""COMPUTED_VALUE"""),"Gestão") | I25: #NAME? | J25: #NAME? | K25: #NAME? | L25: #NAME? | M25: #NAME? | N25: #NAME? | S25: #NAME? | T25: #NAME? | U25: #NAME? | V25: #NAME? | W25: #NAME? | X25: #NAME? | Y25: 0 | Z25: Não | AA25: 0 | AB25: Baixa | AD25: {=IFERROR(ifs( F25 = "Secretário(a)", INDEX(Secretario, MATCH(RIGHT(AC25), premissas_nivel_cargo_letra, 0), MATCH(VALUE(LEFT(AC25)), premissas_nivel_cargo_numero, 0)), F25 = "Presidente", INDEX(Presidente, MATCH(RIGHT(AC25), premissas_nivel_cargo_letra, 0), MATCH(VALUE(LEFT(AC25)), premissas_nivel_cargo_numero, 0)), F25 = "Subsecretário(a)", INDEX(Subsecretario, MATCH(RIGHT(AC25), premissas_nivel_cargo_letra, 0), MATCH(VALUE(LEFT(AC25)), premissas_nivel_cargo_numero, 0)), F25 = "Superintendente", INDEX(Superintendente, MATCH(RIGHT(AC25), premissas_nivel_cargo_letra, 0), MATCH(VALUE(LEFT(AC25)), premissas_nivel_cargo_numero, 0)), F25 = "Coordenador(a)", INDEX(Coordenador, MATCH(RIGHT(AC25), premissas_nivel_cargo_letra, 0), MATCH(VALUE(LEFT(AC25)), premissas_nivel_cargo_numero, 0)), F25 = "Chefe", INDEX(Chefe, MATCH(RIGHT(AC25), premissas_nivel_cargo_letra, 0), MATCH(VALUE(LEFT(AC25)), premissas_nivel_cargo_numero, 0)), F25 = "Diretor(a)", INDEX(Diretor, MATCH(RIGHT(AC25), premissas_nivel_cargo_letra, 0), MATCH(VALUE(LEFT(AC25)), premissas_nivel_cargo_numero, 0)), F25 = "Gerente", INDEX(Gerente, MATCH(RIGHT(AC25), premissas_nivel_cargo_letra, 0), MATCH(VALUE(LEFT(AC25)), premissas_nivel_cargo_numero, 0)), F25 = "Assessor(a)", INDEX(Assessor, MATCH(RIGHT(AC25), premissas_nivel_cargo_letra, 0), MATCH(VALUE(LEFT(AC25)), premissas_nivel_cargo_numero, 0)), F25 = "Ouvidor(a)", INDEX(Ouvidor, MATCH(RIGHT(AC25), premissas_nivel_cargo_letra, 0), MATCH(VALUE(LEFT(AC25)), premissas_nivel_cargo_numero, 0)) ), "")} | AE25: =ifs(G25 = "", "", AD25 = "", "Ainda Não Classificado", NOT(AD25 = ""), "Classificado com Sucesso")
A26: =IFERROR(__xludf.dummyfunction("""COMPUTED_VALUE"""),25) | B26: =IFERROR(__xludf.dummyfunction("""COMPUTED_VALUE"""),"CASA CIVIL") | C26: =IFERROR(__xludf.dummyfunction("""COMPUTED_VALUE"""),"3º") | D26: =IFERROR(__xludf.dummyfunction("""COMPUTED_VALUE"""),"Coordenadoria Técnica de Transformação Digital") | E26: =IFERROR(__xludf.dummyfunction("""COMPUTED_VALUE"""),"Coordenador Técnico") | F26: =IFERROR(__xludf.dummyfunction("""COMPUTED_VALUE"""),"Coordenador(a)") | G26: =IFERROR(__xludf.dummyfunction("""COMPUTED_VALUE"""),"Tecnologias da Informação") | H26: =IFERROR(__xludf.dummyfunction("""COMPUTED_VALUE"""),"Gestão") | I26: #NAME? | J26: #NAME? | K26: #NAME? | L26: #NAME? | M26: #NAME? | N26: #NAME? | S26: #NAME? | T26: #NAME? | U26: #NAME? | V26: #NAME? | W26: #NAME? | X26: #NAME? | Y26: 0 | Z26: Não | AA26: 0 | AB26: Baixa | AD26: {=IFERROR(ifs( F26 = "Secretário(a)", INDEX(Secretario, MATCH(RIGHT(AC26), premissas_nivel_cargo_letra, 0), MATCH(VALUE(LEFT(AC26)), premissas_nivel_cargo_numero, 0)), F26 = "Presidente", INDEX(Presidente, MATCH(RIGHT(AC26), premissas_nivel_cargo_letra, 0), MATCH(VALUE(LEFT(AC26)), premissas_nivel_cargo_numero, 0)), F26 = "Subsecretário(a)", INDEX(Subsecretario, MATCH(RIGHT(AC26), premissas_nivel_cargo_letra, 0), MATCH(VALUE(LEFT(AC26)), premissas_nivel_cargo_numero, 0)), F26 = "Superintendente", INDEX(Superintendente, MATCH(RIGHT(AC26), premissas_nivel_cargo_letra, 0), MATCH(VALUE(LEFT(AC26)), premissas_nivel_cargo_numero, 0)), F26 = "Coordenador(a)", INDEX(Coordenador, MATCH(RIGHT(AC26), premissas_nivel_cargo_letra, 0), MATCH(VALUE(LEFT(AC26)), premissas_nivel_cargo_numero, 0)), F26 = "Chefe", INDEX(Chefe, MATCH(RIGHT(AC26), premissas_nivel_cargo_letra, 0), MATCH(VALUE(LEFT(AC26)), premissas_nivel_cargo_numero, 0)), F26 = "Diretor(a)", INDEX(Diretor, MATCH(RIGHT(AC26), premissas_nivel_cargo_letra, 0), MATCH(VALUE(LEFT(AC26)), premissas_nivel_cargo_numero, 0)), F26 = "Gerente", INDEX(Gerente, MATCH(RIGHT(AC26), premissas_nivel_cargo_letra, 0), MATCH(VALUE(LEFT(AC26)), premissas_nivel_cargo_numero, 0)), F26 = "Assessor(a)", INDEX(Assessor, MATCH(RIGHT(AC26), premissas_nivel_cargo_letra, 0), MATCH(VALUE(LEFT(AC26)), premissas_nivel_cargo_numero, 0)), F26 = "Ouvidor(a)", INDEX(Ouvidor, MATCH(RIGHT(AC26), premissas_nivel_cargo_letra, 0), MATCH(VALUE(LEFT(AC26)), premissas_nivel_cargo_numero, 0)) ), "")} | AE26: =ifs(G26 = "", "", AD26 = "", "Ainda Não Classificado", NOT(AD26 = ""), "Classificado com Sucesso")
A27: =IFERROR(__xludf.dummyfunction("""COMPUTED_VALUE"""),26) | B27: =IFERROR(__xludf.dummyfunction("""COMPUTED_VALUE"""),"CASA CIVIL") | C27: =IFERROR(__xludf.dummyfunction("""COMPUTED_VALUE"""),"3º") | D27: =IFERROR(__xludf.dummyfunction("""COMPUTED_VALUE"""),"Coordenadoria de Relacionamento com o Cidadão") | E27: =IFERROR(__xludf.dummyfunction("""COMPUTED_VALUE"""),"Coordenador I") | F27: =IFERROR(__xludf.dummyfunction("""COMPUTED_VALUE"""),"Coordenador(a)") | G27: =IFERROR(__xludf.dummyfunction("""COMPUTED_VALUE"""),"Comunicação e Relacionamento com o Cidadão") | H27: =IFERROR(__xludf.dummyfunction("""COMPUTED_VALUE"""),"Gestão") | I27: #NAME? | J27: #NAME? | K27: #NAME? | L27: #NAME? | M27: #NAME? | N27: #NAME? | S27: #NAME? | T27: #NAME? | U27: #NAME? | V27: #NAME? | W27: #NAME? | X27: #NAME? | Y27: 0 | Z27: Não | AA27: 0 | AB27: Baixa | AD27: {=IFERROR(ifs( F27 = "Secretário(a)", INDEX(Secretario, MATCH(RIGHT(AC27), premissas_nivel_cargo_letra, 0), MATCH(VALUE(LEFT(AC27)), premissas_nivel_cargo_numero, 0)), F27 = "Presidente", INDEX(Presidente, MATCH(RIGHT(AC27), premissas_nivel_cargo_letra, 0), MATCH(VALUE(LEFT(AC27)), premissas_nivel_cargo_numero, 0)), F27 = "Subsecretário(a)", INDEX(Subsecretario, MATCH(RIGHT(AC27), premissas_nivel_cargo_letra, 0), MATCH(VALUE(LEFT(AC27)), premissas_nivel_cargo_numero, 0)), F27 = "Superintendente", INDEX(Superintendente, MATCH(RIGHT(AC27), premissas_nivel_cargo_letra, 0), MATCH(VALUE(LEFT(AC27)), premissas_nivel_cargo_numero, 0)), F27 = "Coordenador(a)", INDEX(Coordenador, MATCH(RIGHT(AC27), premissas_nivel_cargo_letra, 0), MATCH(VALUE(LEFT(AC27)), premissas_nivel_cargo_numero, 0)), F27 = "Chefe", INDEX(Chefe, MATCH(RIGHT(AC27), premissas_nivel_cargo_letra, 0), MATCH(VALUE(LEFT(AC27)), premissas_nivel_cargo_numero, 0)), F27 = "Diretor(a)", INDEX(Diretor, MATCH(RIGHT(AC27), premissas_nivel_cargo_letra, 0), MATCH(VALUE(LEFT(AC27)), premissas_nivel_cargo_numero, 0)), F27 = "Gerente", INDEX(Gerente, MATCH(RIGHT(AC27), premissas_nivel_cargo_letra, 0), MATCH(VALUE(LEFT(AC27)), premissas_nivel_cargo_numero, 0)), F27 = "Assessor(a)", INDEX(Assessor, MATCH(RIGHT(AC27), premissas_nivel_cargo_letra, 0), MATCH(VALUE(LEFT(AC27)), premissas_nivel_cargo_numero, 0)), F27 = "Ouvidor(a)", INDEX(Ouvidor, MATCH(RIGHT(AC27), premissas_nivel_cargo_letra, 0), MATCH(VALUE(LEFT(AC27)), premissas_nivel_cargo_numero, 0)) ), "")} | AE27: =ifs(G27 = "", "", AD27 = "", "Ainda Não Classificado", NOT(AD27 = ""), "Classificado com Sucesso")
A28: =IFERROR(__xludf.dummyfunction("""COMPUTED_VALUE"""),27) | B28: =IFERROR(__xludf.dummyfunction("""COMPUTED_VALUE"""),"CASA CIVIL") | C28: =IFERROR(__xludf.dummyfunction("""COMPUTED_VALUE"""),"3º") | D28: =IFERROR(__xludf.dummyfunction("""COMPUTED_VALUE"""),"Coordenadoria de Cidade Inteligente") | E28: =IFERROR(__xludf.dummyfunction("""COMPUTED_VALUE"""),"Coordenador I") | F28: =IFERROR(__xludf.dummyfunction("""COMPUTED_VALUE"""),"Coordenador(a)") | G28: =IFERROR(__xludf.dummyfunction("""COMPUTED_VALUE"""),"Tecnologias da Informação") | H28: =IFERROR(__xludf.dummyfunction("""COMPUTED_VALUE"""),"Gestão") | I28: #NAME? | J28: #NAME? | K28: #NAME? | L28: #NAME? | M28: #NAME? | N28: #NAME? | S28: #NAME? | T28: #NAME? | U28: #NAME? | V28: #NAME? | W28: #NAME? | X28: #NAME? | Y28: 0 | Z28: Não | AA28: 0 | AB28: Baixa | AD28: {=IFERROR(ifs( F28 = "Secretário(a)", INDEX(Secretario, MATCH(RIGHT(AC28), premissas_nivel_cargo_letra, 0), MATCH(VALUE(LEFT(AC28)), premissas_nivel_cargo_numero, 0)), F28 = "Presidente", INDEX(Presidente, MATCH(RIGHT(AC28), premissas_nivel_cargo_letra, 0), MATCH(VALUE(LEFT(AC28)), premissas_nivel_cargo_numero, 0)), F28 = "Subsecretário(a)", INDEX(Subsecretario, MATCH(RIGHT(AC28), premissas_nivel_cargo_letra, 0), MATCH(VALUE(LEFT(AC28)), premissas_nivel_cargo_numero, 0)), F28 = "Superintendente", INDEX(Superintendente, MATCH(RIGHT(AC28), premissas_nivel_cargo_letra, 0), MATCH(VALUE(LEFT(AC28)), premissas_nivel_cargo_numero, 0)), F28 = "Coordenador(a)", INDEX(Coordenador, MATCH(RIGHT(AC28), premissas_nivel_cargo_letra, 0), MATCH(VALUE(LEFT(AC28)), premissas_nivel_cargo_numero, 0)), F28 = "Chefe", INDEX(Chefe, MATCH(RIGHT(AC28), premissas_nivel_cargo_letra, 0), MATCH(VALUE(LEFT(AC28)), premissas_nivel_cargo_numero, 0)), F28 = "Diretor(a)", INDEX(Diretor, MATCH(RIGHT(AC28), premissas_nivel_cargo_letra, 0), MATCH(VALUE(LEFT(AC28)), premissas_nivel_cargo_numero, 0)), F28 = "Gerente", INDEX(Gerente, MATCH(RIGHT(AC28), premissas_nivel_cargo_letra, 0), MATCH(VALUE(LEFT(AC28)), premissas_nivel_cargo_numero, 0)), F28 = "Assessor(a)", INDEX(Assessor, MATCH(RIGHT(AC28), premissas_nivel_cargo_letra, 0), MATCH(VALUE(LEFT(AC28)), premissas_nivel_cargo_numero, 0)), F28 = "Ouvidor(a)", INDEX(Ouvidor, MATCH(RIGHT(AC28), premissas_nivel_cargo_letra, 0), MATCH(VALUE(LEFT(AC28)), premissas_nivel_cargo_numero, 0)) ), "")} | AE28: =ifs(G28 = "", "", AD28 = "", "Ainda Não Classificado", NOT(AD28 = ""), "Classificado com Sucesso")
A29: =IFERROR(__xludf.dummyfunction("""COMPUTED_VALUE"""),28) | B29: =IFERROR(__xludf.dummyfunction("""COMPUTED_VALUE"""),"CASA CIVIL") | C29: =IFERROR(__xludf.dummyfunction("""COMPUTED_VALUE"""),"2º") | D29: =IFERROR(__xludf.dummyfunction("""COMPUTED_VALUE"""),"Subsecretaria de Planejamento e Acompanhamento de Resultados") | E29: =IFERROR(__xludf.dummyfunction("""COMPUTED_VALUE"""),"Subsecretário") | F29: =IFERROR(__xludf.dummyfunction("""COMPUTED_VALUE"""),"Subsecretário(a)") | G29: =IFERROR(__xludf.dummyfunction("""COMPUTED_VALUE"""),"Administrativo") | H29: =IFERROR(__xludf.dummyfunction("""COMPUTED_VALUE"""),"Gestão") | I29: #NAME? | J29: #NAME? | K29: #NAME? | L29: #NAME? | M29: #NAME? | N29: #NAME? | S29: #NAME? | T29: #NAME? | U29: #NAME? | V29: #NAME? | W29: #NAME? | X29: #NAME? | Y29: 0 | Z29: Não | AA29: 0 | AB29: Baixa | AD29: {=IFERROR(ifs( F29 = "Secretário(a)", INDEX(Secretario, MATCH(RIGHT(AC29), premissas_nivel_cargo_letra, 0), MATCH(VALUE(LEFT(AC29)), premissas_nivel_cargo_numero, 0)), F29 = "Presidente", INDEX(Presidente, MATCH(RIGHT(AC29), premissas_nivel_cargo_letra, 0), MATCH(VALUE(LEFT(AC29)), premissas_nivel_cargo_numero, 0)), F29 = "Subsecretário(a)", INDEX(Subsecretario, MATCH(RIGHT(AC29), premissas_nivel_cargo_letra, 0), MATCH(VALUE(LEFT(AC29)), premissas_nivel_cargo_numero, 0)), F29 = "Superintendente", INDEX(Superintendente, MATCH(RIGHT(AC29), premissas_nivel_cargo_letra, 0), MATCH(VALUE(LEFT(AC29)), premissas_nivel_cargo_numero, 0)), F29 = "Coordenador(a)", INDEX(Coordenador, MATCH(RIGHT(AC29), premissas_nivel_cargo_letra, 0), MATCH(VALUE(LEFT(AC29)), premissas_nivel_cargo_numero, 0)), F29 = "Chefe", INDEX(Chefe, MATCH(RIGHT(AC29), premissas_nivel_cargo_letra, 0), MATCH(VALUE(LEFT(AC29)), premissas_nivel_cargo_numero, 0)), F29 = "Diretor(a)", INDEX(Diretor, MATCH(RIGHT(AC29), premissas_nivel_cargo_letra, 0), MATCH(VALUE(LEFT(AC29)), premissas_nivel_cargo_numero, 0)), F29 = "Gerente", INDEX(Gerente, MATCH(RIGHT(AC29), premissas_nivel_cargo_letra, 0), MATCH(VALUE(LEFT(AC29)), premissas_nivel_cargo_numero, 0)), F29 = "Assessor(a)", INDEX(Assessor, MATCH(RIGHT(AC29), premissas_nivel_cargo_letra, 0), MATCH(VALUE(LEFT(AC29)), premissas_nivel_cargo_numero, 0)), F29 = "Ouvidor(a)", INDEX(Ouvidor, MATCH(RIGHT(AC29), premissas_nivel_cargo_letra, 0), MATCH(VALUE(LEFT(AC29)), premissas_nivel_cargo_numero, 0)) ), "")} | AE29: =ifs(G29 = "", "", AD29 = "", "Ainda Não Classificado", NOT(AD29 = ""), "Classificado com Sucesso")
A30: =IFERROR(__xludf.dummyfunction("""COMPUTED_VALUE"""),29) | B30: =IFERROR(__xludf.dummyfunction("""COMPUTED_VALUE"""),"CASA CIVIL") | C30: =IFERROR(__xludf.dummyfunction("""COMPUTED_VALUE"""),"3º") | D30: =IFERROR(__xludf.dummyfunction("""COMPUTED_VALUE"""),"Escritório de Planejamento") | E30: =IFERROR(__xludf.dummyfunction("""COMPUTED_VALUE"""),"Coordenador Geral") | F30: =IFERROR(__xludf.dummyfunction("""COMPUTED_VALUE"""),"Coordenador(a)") | G30: =IFERROR(__xludf.dummyfunction("""COMPUTED_VALUE"""),"Técnico-Operacional") | H30: =IFERROR(__xludf.dummyfunction("""COMPUTED_VALUE"""),"Gestão") | I30: #NAME? | J30: #NAME? | K30: #NAME? | L30: #NAME? | M30: #NAME? | N30: #NAME? | S30: #NAME? | T30: #NAME? | U30: #NAME? | V30: #NAME? | W30: #NAME? | X30: #NAME? | Y30: 0 | Z30: Não | AA30: 0 | AB30: Baixa | AD30: {=IFERROR(ifs( F30 = "Secretário(a)", INDEX(Secretario, MATCH(RIGHT(AC30), premissas_nivel_cargo_letra, 0), MATCH(VALUE(LEFT(AC30)), premissas_nivel_cargo_numero, 0)), F30 = "Presidente", INDEX(Presidente, MATCH(RIGHT(AC30), premissas_nivel_cargo_letra, 0), MATCH(VALUE(LEFT(AC30)), premissas_nivel_cargo_numero, 0)), F30 = "Subsecretário(a)", INDEX(Subsecretario, MATCH(RIGHT(AC30), premissas_nivel_cargo_letra, 0), MATCH(VALUE(LEFT(AC30)), premissas_nivel_cargo_numero, 0)), F30 = "Superintendente", INDEX(Superintendente, MATCH(RIGHT(AC30), premissas_nivel_cargo_letra, 0), MATCH(VALUE(LEFT(AC30)), premissas_nivel_cargo_numero, 0)), F30 = "Coordenador(a)", INDEX(Coordenador, MATCH(RIGHT(AC30), premissas_nivel_cargo_letra, 0), MATCH(VALUE(LEFT(AC30)), premissas_nivel_cargo_numero, 0)), F30 = "Chefe", INDEX(Chefe, MATCH(RIGHT(AC30), premissas_nivel_cargo_letra, 0), MATCH(VALUE(LEFT(AC30)), premissas_nivel_cargo_numero, 0)), F30 = "Diretor(a)", INDEX(Diretor, MATCH(RIGHT(AC30), premissas_nivel_cargo_letra, 0), MATCH(VALUE(LEFT(AC30)), premissas_nivel_cargo_numero, 0)), F30 = "Gerente", INDEX(Gerente, MATCH(RIGHT(AC30), premissas_nivel_cargo_letra, 0), MATCH(VALUE(LEFT(AC30)), premissas_nivel_cargo_numero, 0)), F30 = "Assessor(a)", INDEX(Assessor, MATCH(RIGHT(AC30), premissas_nivel_cargo_letra, 0), MATCH(VALUE(LEFT(AC30)), premissas_nivel_cargo_numero, 0)), F30 = "Ouvidor(a)", INDEX(Ouvidor, MATCH(RIGHT(AC30), premissas_nivel_cargo_letra, 0), MATCH(VALUE(LEFT(AC30)), premissas_nivel_cargo_numero, 0)) ), "")} | AE30: =ifs(G30 = "", "", AD30 = "", "Ainda Não Classificado", NOT(AD30 = ""), "Classificado com Sucesso")
A31: =IFERROR(__xludf.dummyfunction("""COMPUTED_VALUE"""),30) | B31: =IFERROR(__xludf.dummyfunction("""COMPUTED_VALUE"""),"CASA CIVIL") | C31: =IFERROR(__xludf.dummyfunction("""COMPUTED_VALUE"""),"3º") | D31: =IFERROR(__xludf.dummyfunction("""COMPUTED_VALUE"""),"Escritório de Gerenciamento de Projetos e Metas") | E31: =IFERROR(__xludf.dummyfunction("""COMPUTED_VALUE"""),"Coordenador Geral") | F31: =IFERROR(__xludf.dummyfunction("""COMPUTED_VALUE"""),"Coordenador(a)") | G31: =IFERROR(__xludf.dummyfunction("""COMPUTED_VALUE"""),"Técnico-Operacional") | H31: =IFERROR(__xludf.dummyfunction("""COMPUTED_VALUE"""),"Gestão") | I31: #NAME? | J31: #NAME? | K31: #NAME? | L31: #NAME? | M31: #NAME? | N31: #NAME? | S31: #NAME? | T31: #NAME? | U31: #NAME? | V31: #NAME? | W31: #NAME? | X31: #NAME? | Y31: 0 | Z31: Não | AA31: 0 | AB31: Baixa | AD31: {=IFERROR(ifs( F31 = "Secretário(a)", INDEX(Secretario, MATCH(RIGHT(AC31), premissas_nivel_cargo_letra, 0), MATCH(VALUE(LEFT(AC31)), premissas_nivel_cargo_numero, 0)), F31 = "Presidente", INDEX(Presidente, MATCH(RIGHT(AC31), premissas_nivel_cargo_letra, 0), MATCH(VALUE(LEFT(AC31)), premissas_nivel_cargo_numero, 0)), F31 = "Subsecretário(a)", INDEX(Subsecretario, MATCH(RIGHT(AC31), premissas_nivel_cargo_letra, 0), MATCH(VALUE(LEFT(AC31)), premissas_nivel_cargo_numero, 0)), F31 = "Superintendente", INDEX(Superintendente, MATCH(RIGHT(AC31), premissas_nivel_cargo_letra, 0), MATCH(VALUE(LEFT(AC31)), premissas_nivel_cargo_numero, 0)), F31 = "Coordenador(a)", INDEX(Coordenador, MATCH(RIGHT(AC31), premissas_nivel_cargo_letra, 0), MATCH(VALUE(LEFT(AC31)), premissas_nivel_cargo_numero, 0)), F31 = "Chefe", INDEX(Chefe, MATCH(RIGHT(AC31), premissas_nivel_cargo_letra, 0), MATCH(VALUE(LEFT(AC31)), premissas_nivel_cargo_numero, 0)), F31 = "Diretor(a)", INDEX(Diretor, MATCH(RIGHT(AC31), premissas_nivel_cargo_letra, 0), MATCH(VALUE(LEFT(AC31)), premissas_nivel_cargo_numero, 0)), F31 = "Gerente", INDEX(Gerente, MATCH(RIGHT(AC31), premissas_nivel_cargo_letra, 0), MATCH(VALUE(LEFT(AC31)), premissas_nivel_cargo_numero, 0)), F31 = "Assessor(a)", INDEX(Assessor, MATCH(RIGHT(AC31), premissas_nivel_cargo_letra, 0), MATCH(VALUE(LEFT(AC31)), premissas_nivel_cargo_numero, 0)), F31 = "Ouvidor(a)", INDEX(Ouvidor, MATCH(RIGHT(AC31), premissas_nivel_cargo_letra, 0), MATCH(VALUE(LEFT(AC31)), premissas_nivel_cargo_numero, 0)) ), "")} | AE31: =ifs(G31 = "", "", AD31 = "", "Ainda Não Classificado", NOT(AD31 = ""), "Classificado com Sucesso")
A32: =IFERROR(__xludf.dummyfunction("""COMPUTED_VALUE"""),31) | B32: =IFERROR(__xludf.dummyfunction("""COMPUTED_VALUE"""),"CASA CIVIL") | C32: =IFERROR(__xludf.dummyfunction("""COMPUTED_VALUE"""),"2º") | D32: =IFERROR(__xludf.dummyfunction("""COMPUTED_VALUE"""),"Subsecretaria de Gestão") | E32: =IFERROR(__xludf.dummyfunction("""COMPUTED_VALUE"""),"Subsecretário") | F32: =IFERROR(__xludf.dummyfunction("""COMPUTED_VALUE"""),"Subsecretário(a)") | G32: =IFERROR(__xludf.dummyfunction("""COMPUTED_VALUE"""),"Administrativo") | H32: =IFERROR(__xludf.dummyfunction("""COMPUTED_VALUE"""),"Gestão") | I32: #NAME? | J32: #NAME? | K32: #NAME? | L32: #NAME? | M32: #NAME? | N32: #NAME? | S32: #NAME? | T32: #NAME? | U32: #NAME? | V32: #NAME? | W32: #NAME? | X32: #NAME? | Y32: 0 | Z32: Não | AA32: 0 | AB32: Baixa | AD32: {=IFERROR(ifs( F32 = "Secretário(a)", INDEX(Secretario, MATCH(RIGHT(AC32), premissas_nivel_cargo_letra, 0), MATCH(VALUE(LEFT(AC32)), premissas_nivel_cargo_numero, 0)), F32 = "Presidente", INDEX(Presidente, MATCH(RIGHT(AC32), premissas_nivel_cargo_letra, 0), MATCH(VALUE(LEFT(AC32)), premissas_nivel_cargo_numero, 0)), F32 = "Subsecretário(a)", INDEX(Subsecretario, MATCH(RIGHT(AC32), premissas_nivel_cargo_letra, 0), MATCH(VALUE(LEFT(AC32)), premissas_nivel_cargo_numero, 0)), F32 = "Superintendente", INDEX(Superintendente, MATCH(RIGHT(AC32), premissas_nivel_cargo_letra, 0), MATCH(VALUE(LEFT(AC32)), premissas_nivel_cargo_numero, 0)), F32 = "Coordenador(a)", INDEX(Coordenador, MATCH(RIGHT(AC32), premissas_nivel_cargo_letra, 0), MATCH(VALUE(LEFT(AC32)), premissas_nivel_cargo_numero, 0)), F32 = "Chefe", INDEX(Chefe, MATCH(RIGHT(AC32), premissas_nivel_cargo_letra, 0), MATCH(VALUE(LEFT(AC32)), premissas_nivel_cargo_numero, 0)), F32 = "Diretor(a)", INDEX(Diretor, MATCH(RIGHT(AC32), premissas_nivel_cargo_letra, 0), MATCH(VALUE(LEFT(AC32)), premissas_nivel_cargo_numero, 0)), F32 = "Gerente", INDEX(Gerente, MATCH(RIGHT(AC32), premissas_nivel_cargo_letra, 0), MATCH(VALUE(LEFT(AC32)), premissas_nivel_cargo_numero, 0)), F32 = "Assessor(a)", INDEX(Assessor, MATCH(RIGHT(AC32), premissas_nivel_cargo_letra, 0), MATCH(VALUE(LEFT(AC32)), premissas_nivel_cargo_numero, 0)), F32 = "Ouvidor(a)", INDEX(Ouvidor, MATCH(RIGHT(AC32), premissas_nivel_cargo_letra, 0), MATCH(VALUE(LEFT(AC32)), premissas_nivel_cargo_numero, 0)) ), "")} | AE32: =ifs(G32 = "", "", AD32 = "", "Ainda Não Classificado", NOT(AD32 = ""), "Classificado com Sucesso")
A33: =IFERROR(__xludf.dummyfunction("""COMPUTED_VALUE"""),32) | B33: =IFERROR(__xludf.dummyfunction("""COMPUTED_VALUE"""),"CASA CIVIL") | C33: =IFERROR(__xludf.dummyfunction("""COMPUTED_VALUE"""),"3º") | D33: =IFERROR(__xludf.dummyfunction("""COMPUTED_VALUE"""),"Assessoria Técnica Administrativa") | E33: =IFERROR(__xludf.dummyfunction("""COMPUTED_VALUE"""),"Assessor Chefe I") | F33: =IFERROR(__xludf.dummyfunction("""COMPUTED_VALUE"""),"Assessor(a)") | G33: =IFERROR(__xludf.dummyfunction("""COMPUTED_VALUE"""),"Administrativo") | H33: =IFERROR(__xludf.dummyfunction("""COMPUTED_VALUE"""),"Gestão") | I33: #NAME? | J33: #NAME? | K33: #NAME? | L33: #NAME? | M33: #NAME? | N33: #NAME? | S33: #NAME? | T33: #NAME? | U33: #NAME? | V33: #NAME? | W33: #NAME? | X33: #NAME? | Y33: 0 | Z33: Não | AA33: 0 | AB33: Baixa | AD33: {=IFERROR(ifs( F33 = "Secretário(a)", INDEX(Secretario, MATCH(RIGHT(AC33), premissas_nivel_cargo_letra, 0), MATCH(VALUE(LEFT(AC33)), premissas_nivel_cargo_numero, 0)), F33 = "Presidente", INDEX(Presidente, MATCH(RIGHT(AC33), premissas_nivel_cargo_letra, 0), MATCH(VALUE(LEFT(AC33)), premissas_nivel_cargo_numero, 0)), F33 = "Subsecretário(a)", INDEX(Subsecretario, MATCH(RIGHT(AC33), premissas_nivel_cargo_letra, 0), MATCH(VALUE(LEFT(AC33)), premissas_nivel_cargo_numero, 0)), F33 = "Superintendente", INDEX(Superintendente, MATCH(RIGHT(AC33), premissas_nivel_cargo_letra, 0), MATCH(VALUE(LEFT(AC33)), premissas_nivel_cargo_numero, 0)), F33 = "Coordenador(a)", INDEX(Coordenador, MATCH(RIGHT(AC33), premissas_nivel_cargo_letra, 0), MATCH(VALUE(LEFT(AC33)), premissas_nivel_cargo_numero, 0)), F33 = "Chefe", INDEX(Chefe, MATCH(RIGHT(AC33), premissas_nivel_cargo_letra, 0), MATCH(VALUE(LEFT(AC33)), premissas_nivel_cargo_numero, 0)), F33 = "Diretor(a)", INDEX(Diretor, MATCH(RIGHT(AC33), premissas_nivel_cargo_letra, 0), MATCH(VALUE(LEFT(AC33)), premissas_nivel_cargo_numero, 0)), F33 = "Gerente", INDEX(Gerente, MATCH(RIGHT(AC33), premissas_nivel_cargo_letra, 0), MATCH(VALUE(LEFT(AC33)), premissas_nivel_cargo_numero, 0)), F33 = "Assessor(a)", INDEX(Assessor, MATCH(RIGHT(AC33), premissas_nivel_cargo_letra, 0), MATCH(VALUE(LEFT(AC33)), premissas_nivel_cargo_numero, 0)), F33 = "Ouvidor(a)", INDEX(Ouvidor, MATCH(RIGHT(AC33), premissas_nivel_cargo_letra, 0), MATCH(VALUE(LEFT(AC33)), premissas_nivel_cargo_numero, 0)) ), "")} | AE33: =ifs(G33 = "", "", AD33 = "", "Ainda Não Classificado", NOT(AD33 = ""), "Classificado com Sucesso")
A34: =IFERROR(__xludf.dummyfunction("""COMPUTED_VALUE"""),33) | B34: =IFERROR(__xludf.dummyfunction("""COMPUTED_VALUE"""),"CASA CIVIL") | C34: =IFERROR(__xludf.dummyfunction("""COMPUTED_VALUE"""),"3º") | D34: =IFERROR(__xludf.dummyfunction("""COMPUTED_VALUE"""),"Coordenadoria Técnica de Controle de Contratos e Licitações") | E34: =IFERROR(__xludf.dummyfunction("""COMPUTED_VALUE"""),"Coordenador Técnico") | F34: =IFERROR(__xludf.dummyfunction("""COMPUTED_VALUE"""),"Coordenador(a)") | G34: =IFERROR(__xludf.dummyfunction("""COMPUTED_VALUE"""),"Administrativo") | H34: =IFERROR(__xludf.dummyfunction("""COMPUTED_VALUE"""),"Gestão") | I34: #NAME? | J34: #NAME? | K34: #NAME? | L34: #NAME? | M34: #NAME? | N34: #NAME? | S34: #NAME? | T34: #NAME? | U34: #NAME? | V34: #NAME? | W34: #NAME? | X34: #NAME? | Y34: 0 | Z34: Não | AA34: 0 | AB34: Baixa | AD34: {=IFERROR(ifs( F34 = "Secretário(a)", INDEX(Secretario, MATCH(RIGHT(AC34), premissas_nivel_cargo_letra, 0), MATCH(VALUE(LEFT(AC34)), premissas_nivel_cargo_numero, 0)), F34 = "Presidente", INDEX(Presidente, MATCH(RIGHT(AC34), premissas_nivel_cargo_letra, 0), MATCH(VALUE(LEFT(AC34)), premissas_nivel_cargo_numero, 0)), F34 = "Subsecretário(a)", INDEX(Subsecretario, MATCH(RIGHT(AC34), premissas_nivel_cargo_letra, 0), MATCH(VALUE(LEFT(AC34)), premissas_nivel_cargo_numero, 0)), F34 = "Superintendente", INDEX(Superintendente, MATCH(RIGHT(AC34), premissas_nivel_cargo_letra, 0), MATCH(VALUE(LEFT(AC34)), premissas_nivel_cargo_numero, 0)), F34 = "Coordenador(a)", INDEX(Coordenador, MATCH(RIGHT(AC34), premissas_nivel_cargo_letra, 0), MATCH(VALUE(LEFT(AC34)), premissas_nivel_cargo_numero, 0)), F34 = "Chefe", INDEX(Chefe, MATCH(RIGHT(AC34), premissas_nivel_cargo_letra, 0), MATCH(VALUE(LEFT(AC34)), premissas_nivel_cargo_numero, 0)), F34 = "Diretor(a)", INDEX(Diretor, MATCH(RIGHT(AC34), premissas_nivel_cargo_letra, 0), MATCH(VALUE(LEFT(AC34)), premissas_nivel_cargo_numero, 0)), F34 = "Gerente", INDEX(Gerente, MATCH(RIGHT(AC34), premissas_nivel_cargo_letra, 0), MATCH(VALUE(LEFT(AC34)), premissas_nivel_cargo_numero, 0)), F34 = "Assessor(a)", INDEX(Assessor, MATCH(RIGHT(AC34), premissas_nivel_cargo_letra, 0), MATCH(VALUE(LEFT(AC34)), premissas_nivel_cargo_numero, 0)), F34 = "Ouvidor(a)", INDEX(Ouvidor, MATCH(RIGHT(AC34), premissas_nivel_cargo_letra, 0), MATCH(VALUE(LEFT(AC34)), premissas_nivel_cargo_numero, 0)) ), "")} | AE34: =ifs(G34 = "", "", AD34 = "", "Ainda Não Classificado", NOT(AD34 = ""), "Classificado com Sucesso")
A35: =IFERROR(__xludf.dummyfunction("""COMPUTED_VALUE"""),34) | B35: =IFERROR(__xludf.dummyfunction("""COMPUTED_VALUE"""),"CASA CIVIL") | C35: =IFERROR(__xludf.dummyfunction("""COMPUTED_VALUE"""),"3º") | D35: =IFERROR(__xludf.dummyfunction("""COMPUTED_VALUE"""),"Coordenadoria Técnica de Infraestrutura e Logística") | E35: =IFERROR(__xludf.dummyfunction("""COMPUTED_VALUE"""),"Coordenador Técnico") | F35: =IFERROR(__xludf.dummyfunction("""COMPUTED_VALUE"""),"Coordenador(a)") | G35: =IFERROR(__xludf.dummyfunction("""COMPUTED_VALUE"""),"Administrativo") | H35: =IFERROR(__xludf.dummyfunction("""COMPUTED_VALUE"""),"Gestão") | I35: #NAME? | J35: #NAME? | K35: #NAME? | L35: #NAME? | M35: #NAME? | N35: #NAME? | S35: #NAME? | T35: #NAME? | U35: #NAME? | V35: #NAME? | W35: #NAME? | X35: #NAME? | Y35: 0 | Z35: Não | AA35: 0 | AB35: Baixa | AD35: {=IFERROR(ifs( F35 = "Secretário(a)", INDEX(Secretario, MATCH(RIGHT(AC35), premissas_nivel_cargo_letra, 0), MATCH(VALUE(LEFT(AC35)), premissas_nivel_cargo_numero, 0)), F35 = "Presidente", INDEX(Presidente, MATCH(RIGHT(AC35), premissas_nivel_cargo_letra, 0), MATCH(VALUE(LEFT(AC35)), premissas_nivel_cargo_numero, 0)), F35 = "Subsecretário(a)", INDEX(Subsecretario, MATCH(RIGHT(AC35), premissas_nivel_cargo_letra, 0), MATCH(VALUE(LEFT(AC35)), premissas_nivel_cargo_numero, 0)), F35 = "Superintendente", INDEX(Superintendente, MATCH(RIGHT(AC35), premissas_nivel_cargo_letra, 0), MATCH(VALUE(LEFT(AC35)), premissas_nivel_cargo_numero, 0)), F35 = "Coordenador(a)", INDEX(Coordenador, MATCH(RIGHT(AC35), premissas_nivel_cargo_letra, 0), MATCH(VALUE(LEFT(AC35)), premissas_nivel_cargo_numero, 0)), F35 = "Chefe", INDEX(Chefe, MATCH(RIGHT(AC35), premissas_nivel_cargo_letra, 0), MATCH(VALUE(LEFT(AC35)), premissas_nivel_cargo_numero, 0)), F35 = "Diretor(a)", INDEX(Diretor, MATCH(RIGHT(AC35), premissas_nivel_cargo_letra, 0), MATCH(VALUE(LEFT(AC35)), premissas_nivel_cargo_numero, 0)), F35 = "Gerente", INDEX(Gerente, MATCH(RIGHT(AC35), premissas_nivel_cargo_letra, 0), MATCH(VALUE(LEFT(AC35)), premissas_nivel_cargo_numero, 0)), F35 = "Assessor(a)", INDEX(Assessor, MATCH(RIGHT(AC35), premissas_nivel_cargo_letra, 0), MATCH(VALUE(LEFT(AC35)), premissas_nivel_cargo_numero, 0)), F35 = "Ouvidor(a)", INDEX(Ouvidor, MATCH(RIGHT(AC35), premissas_nivel_cargo_letra, 0), MATCH(VALUE(LEFT(AC35)), premissas_nivel_cargo_numero, 0)) ), "")} | AE35: =ifs(G35 = "", "", AD35 = "", "Ainda Não Classificado", NOT(AD35 = ""), "Classificado com Sucesso")
A36: =IFERROR(__xludf.dummyfunction("""COMPUTED_VALUE"""),35) | B36: =IFERROR(__xludf.dummyfunction("""COMPUTED_VALUE"""),"CASA CIVIL") | C36: =IFERROR(__xludf.dummyfunction("""COMPUTED_VALUE"""),"3º") | D36: =IFERROR(__xludf.dummyfunction("""COMPUTED_VALUE"""),"Coordenadoria Técnica de Recursos Humanos") | E36: =IFERROR(__xludf.dummyfunction("""COMPUTED_VALUE"""),"Coordenador Técnico") | F36: =IFERROR(__xludf.dummyfunction("""COMPUTED_VALUE"""),"Coordenador(a)") | G36: =IFERROR(__xludf.dummyfunction("""COMPUTED_VALUE"""),"Administrativo") | H36: =IFERROR(__xludf.dummyfunction("""COMPUTED_VALUE"""),"Gestão") | I36: #NAME? | J36: #NAME? | K36: #NAME? | L36: #NAME? | M36: #NAME? | N36: #NAME? | S36: #NAME? | T36: #NAME? | U36: #NAME? | V36: #NAME? | W36: #NAME? | X36: #NAME? | Y36: 0 | Z36: Não | AA36: 0 | AB36: Baixa | AD36: {=IFERROR(ifs( F36 = "Secretário(a)", INDEX(Secretario, MATCH(RIGHT(AC36), premissas_nivel_cargo_letra, 0), MATCH(VALUE(LEFT(AC36)), premissas_nivel_cargo_numero, 0)), F36 = "Presidente", INDEX(Presidente, MATCH(RIGHT(AC36), premissas_nivel_cargo_letra, 0), MATCH(VALUE(LEFT(AC36)), premissas_nivel_cargo_numero, 0)), F36 = "Subsecretário(a)", INDEX(Subsecretario, MATCH(RIGHT(AC36), premissas_nivel_cargo_letra, 0), MATCH(VALUE(LEFT(AC36)), premissas_nivel_cargo_numero, 0)), F36 = "Superintendente", INDEX(Superintendente, MATCH(RIGHT(AC36), premissas_nivel_cargo_letra, 0), MATCH(VALUE(LEFT(AC36)), premissas_nivel_cargo_numero, 0)), F36 = "Coordenador(a)", INDEX(Coordenador, MATCH(RIGHT(AC36), premissas_nivel_cargo_letra, 0), MATCH(VALUE(LEFT(AC36)), premissas_nivel_cargo_numero, 0)), F36 = "Chefe", INDEX(Chefe, MATCH(RIGHT(AC36), premissas_nivel_cargo_letra, 0), MATCH(VALUE(LEFT(AC36)), premissas_nivel_cargo_numero, 0)), F36 = "Diretor(a)", INDEX(Diretor, MATCH(RIGHT(AC36), premissas_nivel_cargo_letra, 0), MATCH(VALUE(LEFT(AC36)), premissas_nivel_cargo_numero, 0)), F36 = "Gerente", INDEX(Gerente, MATCH(RIGHT(AC36), premissas_nivel_cargo_letra, 0), MATCH(VALUE(LEFT(AC36)), premissas_nivel_cargo_numero, 0)), F36 = "Assessor(a)", INDEX(Assessor, MATCH(RIGHT(AC36), premissas_nivel_cargo_letra, 0), MATCH(VALUE(LEFT(AC36)), premissas_nivel_cargo_numero, 0)), F36 = "Ouvidor(a)", INDEX(Ouvidor, MATCH(RIGHT(AC36), premissas_nivel_cargo_letra, 0), MATCH(VALUE(LEFT(AC36)), premissas_nivel_cargo_numero, 0)) ), "")} | AE36: =ifs(G36 = "", "", AD36 = "", "Ainda Não Classificado", NOT(AD36 = ""), "Classificado com Sucesso")
A37: =IFERROR(__xludf.dummyfunction("""COMPUTED_VALUE"""),36) | B37: =IFERROR(__xludf.dummyfunction("""COMPUTED_VALUE"""),"CASA CIVIL") | C37: =IFERROR(__xludf.dummyfunction("""COMPUTED_VALUE"""),"2º") | D37: =IFERROR(__xludf.dummyfunction("""COMPUTED_VALUE"""),"Subsecretaria de Agricultura") | E37: =IFERROR(__xludf.dummyfunction("""COMPUTED_VALUE"""),"Subsecretário") | F37: =IFERROR(__xludf.dummyfunction("""COMPUTED_VALUE"""),"Subsecretário(a)") | G37: =IFERROR(__xludf.dummyfunction("""COMPUTED_VALUE"""),"Técnico-Operacional") | H37: =IFERROR(__xludf.dummyfunction("""COMPUTED_VALUE"""),"Gestão") | I37: #NAME? | J37: #NAME? | K37: #NAME? | L37: #NAME? | M37: #NAME? | N37: #NAME? | S37: #NAME? | T37: #NAME? | U37: #NAME? | V37: #NAME? | W37: #NAME? | X37: #NAME? | Y37: 0 | Z37: Não | AA37: 0 | AB37: Baixa | AD37: {=IFERROR(ifs( F37 = "Secretário(a)", INDEX(Secretario, MATCH(RIGHT(AC37), premissas_nivel_cargo_letra, 0), MATCH(VALUE(LEFT(AC37)), premissas_nivel_cargo_numero, 0)), F37 = "Presidente", INDEX(Presidente, MATCH(RIGHT(AC37), premissas_nivel_cargo_letra, 0), MATCH(VALUE(LEFT(AC37)), premissas_nivel_cargo_numero, 0)), F37 = "Subsecretário(a)", INDEX(Subsecretario, MATCH(RIGHT(AC37), premissas_nivel_cargo_letra, 0), MATCH(VALUE(LEFT(AC37)), premissas_nivel_cargo_numero, 0)), F37 = "Superintendente", INDEX(Superintendente, MATCH(RIGHT(AC37), premissas_nivel_cargo_letra, 0), MATCH(VALUE(LEFT(AC37)), premissas_nivel_cargo_numero, 0)), F37 = "Coordenador(a)", INDEX(Coordenador, MATCH(RIGHT(AC37), premissas_nivel_cargo_letra, 0), MATCH(VALUE(LEFT(AC37)), premissas_nivel_cargo_numero, 0)), F37 = "Chefe", INDEX(Chefe, MATCH(RIGHT(AC37), premissas_nivel_cargo_letra, 0), MATCH(VALUE(LEFT(AC37)), premissas_nivel_cargo_numero, 0)), F37 = "Diretor(a)", INDEX(Diretor, MATCH(RIGHT(AC37), premissas_nivel_cargo_letra, 0), MATCH(VALUE(LEFT(AC37)), premissas_nivel_cargo_numero, 0)), F37 = "Gerente", INDEX(Gerente, MATCH(RIGHT(AC37), premissas_nivel_cargo_letra, 0), MATCH(VALUE(LEFT(AC37)), premissas_nivel_cargo_numero, 0)), F37 = "Assessor(a)", INDEX(Assessor, MATCH(RIGHT(AC37), premissas_nivel_cargo_letra, 0), MATCH(VALUE(LEFT(AC37)), premissas_nivel_cargo_numero, 0)), F37 = "Ouvidor(a)", INDEX(Ouvidor, MATCH(RIGHT(AC37), premissas_nivel_cargo_letra, 0), MATCH(VALUE(LEFT(AC37)), premissas_nivel_cargo_numero, 0)) ), "")} | AE37: =ifs(G37 = "", "", AD37 = "", "Ainda Não Classificado", NOT(AD37 = ""), "Classificado com Sucesso")
A38: =IFERROR(__xludf.dummyfunction("""COMPUTED_VALUE"""),37) | B38: =IFERROR(__xludf.dummyfunction("""COMPUTED_VALUE"""),"CASA CIVIL") | C38: =IFERROR(__xludf.dummyfunction("""COMPUTED_VALUE"""),"3º") | D38: =IFERROR(__xludf.dummyfunction("""COMPUTED_VALUE"""),"Gerência de Agricultura") | E38: =IFERROR(__xludf.dummyfunction("""COMPUTED_VALUE"""),"Gerente II") | F38: =IFERROR(__xludf.dummyfunction("""COMPUTED_VALUE"""),"Gerente") | G38: =IFERROR(__xludf.dummyfunction("""COMPUTED_VALUE"""),"Técnico-Operacional") | H38: =IFERROR(__xludf.dummyfunction("""COMPUTED_VALUE"""),"Gestão") | I38: #NAME? | J38: #NAME? | K38: #NAME? | L38: #NAME? | M38: #NAME? | N38: #NAME? | S38: #NAME? | T38: #NAME? | U38: #NAME? | V38: #NAME? | W38: #NAME? | X38: #NAME? | Y38: 0 | Z38: Não | AA38: 0 | AB38: Baixa | AD38: {=IFERROR(ifs( F38 = "Secretário(a)", INDEX(Secretario, MATCH(RIGHT(AC38), premissas_nivel_cargo_letra, 0), MATCH(VALUE(LEFT(AC38)), premissas_nivel_cargo_numero, 0)), F38 = "Presidente", INDEX(Presidente, MATCH(RIGHT(AC38), premissas_nivel_cargo_letra, 0), MATCH(VALUE(LEFT(AC38)), premissas_nivel_cargo_numero, 0)), F38 = "Subsecretário(a)", INDEX(Subsecretario, MATCH(RIGHT(AC38), premissas_nivel_cargo_letra, 0), MATCH(VALUE(LEFT(AC38)), premissas_nivel_cargo_numero, 0)), F38 = "Superintendente", INDEX(Superintendente, MATCH(RIGHT(AC38), premissas_nivel_cargo_letra, 0), MATCH(VALUE(LEFT(AC38)), premissas_nivel_cargo_numero, 0)), F38 = "Coordenador(a)", INDEX(Coordenador, MATCH(RIGHT(AC38), premissas_nivel_cargo_letra, 0), MATCH(VALUE(LEFT(AC38)), premissas_nivel_cargo_numero, 0)), F38 = "Chefe", INDEX(Chefe, MATCH(RIGHT(AC38), premissas_nivel_cargo_letra, 0), MATCH(VALUE(LEFT(AC38)), premissas_nivel_cargo_numero, 0)), F38 = "Diretor(a)", INDEX(Diretor, MATCH(RIGHT(AC38), premissas_nivel_cargo_letra, 0), MATCH(VALUE(LEFT(AC38)), premissas_nivel_cargo_numero, 0)), F38 = "Gerente", INDEX(Gerente, MATCH(RIGHT(AC38), premissas_nivel_cargo_letra, 0), MATCH(VALUE(LEFT(AC38)), premissas_nivel_cargo_numero, 0)), F38 = "Assessor(a)", INDEX(Assessor, MATCH(RIGHT(AC38), premissas_nivel_cargo_letra, 0), MATCH(VALUE(LEFT(AC38)), premissas_nivel_cargo_numero, 0)), F38 = "Ouvidor(a)", INDEX(Ouvidor, MATCH(RIGHT(AC38), premissas_nivel_cargo_letra, 0), MATCH(VALUE(LEFT(AC38)), premissas_nivel_cargo_numero, 0)) ), "")} | AE38: =ifs(G38 = "", "", AD38 = "", "Ainda Não Classificado", NOT(AD38 = ""), "Classificado com Sucesso")
A39: =IFERROR(__xludf.dummyfunction("""COMPUTED_VALUE"""),38) | B39: =IFERROR(__xludf.dummyfunction("""COMPUTED_VALUE"""),"CASA CIVIL") | C39: =IFERROR(__xludf.dummyfunction("""COMPUTED_VALUE"""),"3º") | D39: =IFERROR(__xludf.dummyfunction("""COMPUTED_VALUE"""),"Gerência de Pesca") | E39: =IFERROR(__xludf.dummyfunction("""COMPUTED_VALUE"""),"Gerente II") | F39: =IFERROR(__xludf.dummyfunction("""COMPUTED_VALUE"""),"Gerente") | G39: =IFERROR(__xludf.dummyfunction("""COMPUTED_VALUE"""),"Técnico-Operacional") | H39: =IFERROR(__xludf.dummyfunction("""COMPUTED_VALUE"""),"Gestão") | I39: #NAME? | J39: #NAME? | K39: #NAME? | L39: #NAME? | M39: #NAME? | N39: #NAME? | S39: #NAME? | T39: #NAME? | U39: #NAME? | V39: #NAME? | W39: #NAME? | X39: #NAME? | Y39: 0 | Z39: Não | AA39: 0 | AB39: Baixa | AD39: {=IFERROR(ifs( F39 = "Secretário(a)", INDEX(Secretario, MATCH(RIGHT(AC39), premissas_nivel_cargo_letra, 0), MATCH(VALUE(LEFT(AC39)), premissas_nivel_cargo_numero, 0)), F39 = "Presidente", INDEX(Presidente, MATCH(RIGHT(AC39), premissas_nivel_cargo_letra, 0), MATCH(VALUE(LEFT(AC39)), premissas_nivel_cargo_numero, 0)), F39 = "Subsecretário(a)", INDEX(Subsecretario, MATCH(RIGHT(AC39), premissas_nivel_cargo_letra, 0), MATCH(VALUE(LEFT(AC39)), premissas_nivel_cargo_numero, 0)), F39 = "Superintendente", INDEX(Superintendente, MATCH(RIGHT(AC39), premissas_nivel_cargo_letra, 0), MATCH(VALUE(LEFT(AC39)), premissas_nivel_cargo_numero, 0)), F39 = "Coordenador(a)", INDEX(Coordenador, MATCH(RIGHT(AC39), premissas_nivel_cargo_letra, 0), MATCH(VALUE(LEFT(AC39)), premissas_nivel_cargo_numero, 0)), F39 = "Chefe", INDEX(Chefe, MATCH(RIGHT(AC39), premissas_nivel_cargo_letra, 0), MATCH(VALUE(LEFT(AC39)), premissas_nivel_cargo_numero, 0)), F39 = "Diretor(a)", INDEX(Diretor, MATCH(RIGHT(AC39), premissas_nivel_cargo_letra, 0), MATCH(VALUE(LEFT(AC39)), premissas_nivel_cargo_numero, 0)), F39 = "Gerente", INDEX(Gerente, MATCH(RIGHT(AC39), premissas_nivel_cargo_letra, 0), MATCH(VALUE(LEFT(AC39)), premissas_nivel_cargo_numero, 0)), F39 = "Assessor(a)", INDEX(Assessor, MATCH(RIGHT(AC39), premissas_nivel_cargo_letra, 0), MATCH(VALUE(LEFT(AC39)), premissas_nivel_cargo_numero, 0)), F39 = "Ouvidor(a)", INDEX(Ouvidor, MATCH(RIGHT(AC39), premissas_nivel_cargo_letra, 0), MATCH(VALUE(LEFT(AC39)), premissas_nivel_cargo_numero, 0)) ), "")} | AE39: =ifs(G39 = "", "", AD39 = "", "Ainda Não Classificado", NOT(AD39 = ""), "Classificado com Sucesso")
A40: =IFERROR(__xludf.dummyfunction("""COMPUTED_VALUE"""),39) | B40: =IFERROR(__xludf.dummyfunction("""COMPUTED_VALUE"""),"CASA CIVIL") | C40: =IFERROR(__xludf.dummyfunction("""COMPUTED_VALUE"""),"3º") | D40: =IFERROR(__xludf.dummyfunction("""COMPUTED_VALUE"""),"Gerência de Pecuária") | E40: =IFERROR(__xludf.dummyfunction("""COMPUTED_VALUE"""),"Gerente II") | F40: =IFERROR(__xludf.dummyfunction("""COMPUTED_VALUE"""),"Gerente") | G40: =IFERROR(__xludf.dummyfunction("""COMPUTED_VALUE"""),"Técnico-Operacional") | H40: =IFERROR(__xludf.dummyfunction("""COMPUTED_VALUE"""),"Gestão") | I40: #NAME? | J40: #NAME? | K40: #NAME? | L40: #NAME? | M40: #NAME? | N40: #NAME? | S40: #NAME? | T40: #NAME? | U40: #NAME? | V40: #NAME? | W40: #NAME? | X40: #NAME? | Y40: 0 | Z40: Não | AA40: 0 | AB40: Baixa | AD40: {=IFERROR(ifs( F40 = "Secretário(a)", INDEX(Secretario, MATCH(RIGHT(AC40), premissas_nivel_cargo_letra, 0), MATCH(VALUE(LEFT(AC40)), premissas_nivel_cargo_numero, 0)), F40 = "Presidente", INDEX(Presidente, MATCH(RIGHT(AC40), premissas_nivel_cargo_letra, 0), MATCH(VALUE(LEFT(AC40)), premissas_nivel_cargo_numero, 0)), F40 = "Subsecretário(a)", INDEX(Subsecretario, MATCH(RIGHT(AC40), premissas_nivel_cargo_letra, 0), MATCH(VALUE(LEFT(AC40)), premissas_nivel_cargo_numero, 0)), F40 = "Superintendente", INDEX(Superintendente, MATCH(RIGHT(AC40), premissas_nivel_cargo_letra, 0), MATCH(VALUE(LEFT(AC40)), premissas_nivel_cargo_numero, 0)), F40 = "Coordenador(a)", INDEX(Coordenador, MATCH(RIGHT(AC40), premissas_nivel_cargo_letra, 0), MATCH(VALUE(LEFT(AC40)), premissas_nivel_cargo_numero, 0)), F40 = "Chefe", INDEX(Chefe, MATCH(RIGHT(AC40), premissas_nivel_cargo_letra, 0), MATCH(VALUE(LEFT(AC40)), premissas_nivel_cargo_numero, 0)), F40 = "Diretor(a)", INDEX(Diretor, MATCH(RIGHT(AC40), premissas_nivel_cargo_letra, 0), MATCH(VALUE(LEFT(AC40)), premissas_nivel_cargo_numero, 0)), F40 = "Gerente", INDEX(Gerente, MATCH(RIGHT(AC40), premissas_nivel_cargo_letra, 0), MATCH(VALUE(LEFT(AC40)), premissas_nivel_cargo_numero, 0)), F40 = "Assessor(a)", INDEX(Assessor, MATCH(RIGHT(AC40), premissas_nivel_cargo_letra, 0), MATCH(VALUE(LEFT(AC40)), premissas_nivel_cargo_numero, 0)), F40 = "Ouvidor(a)", INDEX(Ouvidor, MATCH(RIGHT(AC40), premissas_nivel_cargo_letra, 0), MATCH(VALUE(LEFT(AC40)), premissas_nivel_cargo_numero, 0)) ), "")} | AE40: =ifs(G40 = "", "", AD40 = "", "Ainda Não Classificado", NOT(AD40 = ""), "Classificado com Sucesso")
A41: =IFERROR(__xludf.dummyfunction("""COMPUTED_VALUE"""),40) | B41: =IFERROR(__xludf.dummyfunction("""COMPUTED_VALUE"""),"CASA CIVIL") | C41: =IFERROR(__xludf.dummyfunction("""COMPUTED_VALUE"""),"3º") | D41: =IFERROR(__xludf.dummyfunction("""COMPUTED_VALUE"""),"Gerência Técnica de Desenvolvimento Rural") | E41: =IFERROR(__xludf.dummyfunction("""COMPUTED_VALUE"""),"Gerente II") | F41: =IFERROR(__xludf.dummyfunction("""COMPUTED_VALUE"""),"Gerente") | G41: =IFERROR(__xludf.dummyfunction("""COMPUTED_VALUE"""),"Técnico-Operacional") | H41: =IFERROR(__xludf.dummyfunction("""COMPUTED_VALUE"""),"Gestão") | I41: #NAME? | J41: #NAME? | K41: #NAME? | L41: #NAME? | M41: #NAME? | N41: #NAME? | S41: #NAME? | T41: #NAME? | U41: #NAME? | V41: #NAME? | W41: #NAME? | X41: #NAME? | Y41: 0 | Z41: Não | AA41: 0 | AB41: Baixa | AD41: {=IFERROR(ifs( F41 = "Secretário(a)", INDEX(Secretario, MATCH(RIGHT(AC41), premissas_nivel_cargo_letra, 0), MATCH(VALUE(LEFT(AC41)), premissas_nivel_cargo_numero, 0)), F41 = "Presidente", INDEX(Presidente, MATCH(RIGHT(AC41), premissas_nivel_cargo_letra, 0), MATCH(VALUE(LEFT(AC41)), premissas_nivel_cargo_numero, 0)), F41 = "Subsecretário(a)", INDEX(Subsecretario, MATCH(RIGHT(AC41), premissas_nivel_cargo_letra, 0), MATCH(VALUE(LEFT(AC41)), premissas_nivel_cargo_numero, 0)), F41 = "Superintendente", INDEX(Superintendente, MATCH(RIGHT(AC41), premissas_nivel_cargo_letra, 0), MATCH(VALUE(LEFT(AC41)), premissas_nivel_cargo_numero, 0)), F41 = "Coordenador(a)", INDEX(Coordenador, MATCH(RIGHT(AC41), premissas_nivel_cargo_letra, 0), MATCH(VALUE(LEFT(AC41)), premissas_nivel_cargo_numero, 0)), F41 = "Chefe", INDEX(Chefe, MATCH(RIGHT(AC41), premissas_nivel_cargo_letra, 0), MATCH(VALUE(LEFT(AC41)), premissas_nivel_cargo_numero, 0)), F41 = "Diretor(a)", INDEX(Diretor, MATCH(RIGHT(AC41), premissas_nivel_cargo_letra, 0), MATCH(VALUE(LEFT(AC41)), premissas_nivel_cargo_numero, 0)), F41 = "Gerente", INDEX(Gerente, MATCH(RIGHT(AC41), premissas_nivel_cargo_letra, 0), MATCH(VALUE(LEFT(AC41)), premissas_nivel_cargo_numero, 0)), F41 = "Assessor(a)", INDEX(Assessor, MATCH(RIGHT(AC41), premissas_nivel_cargo_letra, 0), MATCH(VALUE(LEFT(AC41)), premissas_nivel_cargo_numero, 0)), F41 = "Ouvidor(a)", INDEX(Ouvidor, MATCH(RIGHT(AC41), premissas_nivel_cargo_letra, 0), MATCH(VALUE(LEFT(AC41)), premissas_nivel_cargo_numero, 0)) ), "")} | AE41: =ifs(G41 = "", "", AD41 = "", "Ainda Não Classificado", NOT(AD41 = ""), "Classificado com Sucesso")
A42: =IFERROR(__xludf.dummyfunction("""COMPUTED_VALUE"""),41) | B42: =IFERROR(__xludf.dummyfunction("""COMPUTED_VALUE"""),"CASA CIVIL") | C42: =IFERROR(__xludf.dummyfunction("""COMPUTED_VALUE"""),"2º") | D42: =IFERROR(__xludf.dummyfunction("""COMPUTED_VALUE"""),"Instituto Fundação João Goulart") | E42: =IFERROR(__xludf.dummyfunction("""COMPUTED_VALUE"""),"Presidente") | F42: =IFERROR(__xludf.dummyfunction("""COMPUTED_VALUE"""),"Presidente") | G42: =IFERROR(__xludf.dummyfunction("""COMPUTED_VALUE"""),"Administrativo") | H42: =IFERROR(__xludf.dummyfunction("""COMPUTED_VALUE"""),"Gestão") | I42: #NAME? | J42: #NAME? | K42: #NAME? | L42: #NAME? | M42: #NAME? | N42: #NAME? | S42: #NAME? | T42: #NAME? | U42: #NAME? | V42: #NAME? | W42: #NAME? | X42: #NAME? | Y42: 0 | Z42: Não | AA42: 0 | AB42: Baixa | AD42: {=IFERROR(ifs( F42 = "Secretário(a)", INDEX(Secretario, MATCH(RIGHT(AC42), premissas_nivel_cargo_letra, 0), MATCH(VALUE(LEFT(AC42)), premissas_nivel_cargo_numero, 0)), F42 = "Presidente", INDEX(Presidente, MATCH(RIGHT(AC42), premissas_nivel_cargo_letra, 0), MATCH(VALUE(LEFT(AC42)), premissas_nivel_cargo_numero, 0)), F42 = "Subsecretário(a)", INDEX(Subsecretario, MATCH(RIGHT(AC42), premissas_nivel_cargo_letra, 0), MATCH(VALUE(LEFT(AC42)), premissas_nivel_cargo_numero, 0)), F42 = "Superintendente", INDEX(Superintendente, MATCH(RIGHT(AC42), premissas_nivel_cargo_letra, 0), MATCH(VALUE(LEFT(AC42)), premissas_nivel_cargo_numero, 0)), F42 = "Coordenador(a)", INDEX(Coordenador, MATCH(RIGHT(AC42), premissas_nivel_cargo_letra, 0), MATCH(VALUE(LEFT(AC42)), premissas_nivel_cargo_numero, 0)), F42 = "Chefe", INDEX(Chefe, MATCH(RIGHT(AC42), premissas_nivel_cargo_letra, 0), MATCH(VALUE(LEFT(AC42)), premissas_nivel_cargo_numero, 0)), F42 = "Diretor(a)", INDEX(Diretor, MATCH(RIGHT(AC42), premissas_nivel_cargo_letra, 0), MATCH(VALUE(LEFT(AC42)), premissas_nivel_cargo_numero, 0)), F42 = "Gerente", INDEX(Gerente, MATCH(RIGHT(AC42), premissas_nivel_cargo_letra, 0), MATCH(VALUE(LEFT(AC42)), premissas_nivel_cargo_numero, 0)), F42 = "Assessor(a)", INDEX(Assessor, MATCH(RIGHT(AC42), premissas_nivel_cargo_letra, 0), MATCH(VALUE(LEFT(AC42)), premissas_nivel_cargo_numero, 0)), F42 = "Ouvidor(a)", INDEX(Ouvidor, MATCH(RIGHT(AC42), premissas_nivel_cargo_letra, 0), MATCH(VALUE(LEFT(AC42)), premissas_nivel_cargo_numero, 0)) ), "")} | AE42: =ifs(G42 = "", "", AD42 = "", "Ainda Não Classificado", NOT(AD42 = ""), "Classificado com Sucesso")
A43: =IFERROR(__xludf.dummyfunction("""COMPUTED_VALUE"""),42) | B43: =IFERROR(__xludf.dummyfunction("""COMPUTED_VALUE"""),"CASA CIVIL") | C43: =IFERROR(__xludf.dummyfunction("""COMPUTED_VALUE"""),"3º") | D43: =IFERROR(__xludf.dummyfunction("""COMPUTED_VALUE"""),"Coordenadoria de Dados e Comportamento") | E43: =IFERROR(__xludf.dummyfunction("""COMPUTED_VALUE"""),"Coordenador I") | F43: =IFERROR(__xludf.dummyfunction("""COMPUTED_VALUE"""),"Coordenador(a)") | G43: =IFERROR(__xludf.dummyfunction("""COMPUTED_VALUE"""),"Técnico-Operacional") | H43: =IFERROR(__xludf.dummyfunction("""COMPUTED_VALUE"""),"Gestão") | I43: #NAME? | J43: #NAME? | K43: #NAME? | L43: #NAME? | M43: #NAME? | N43: #NAME? | S43: #NAME? | T43: #NAME? | U43: #NAME? | V43: #NAME? | W43: #NAME? | X43: #NAME? | Y43: 0 | Z43: Não | AA43: 0 | AB43: Baixa | AD43: {=IFERROR(ifs( F43 = "Secretário(a)", INDEX(Secretario, MATCH(RIGHT(AC43), premissas_nivel_cargo_letra, 0), MATCH(VALUE(LEFT(AC43)), premissas_nivel_cargo_numero, 0)), F43 = "Presidente", INDEX(Presidente, MATCH(RIGHT(AC43), premissas_nivel_cargo_letra, 0), MATCH(VALUE(LEFT(AC43)), premissas_nivel_cargo_numero, 0)), F43 = "Subsecretário(a)", INDEX(Subsecretario, MATCH(RIGHT(AC43), premissas_nivel_cargo_letra, 0), MATCH(VALUE(LEFT(AC43)), premissas_nivel_cargo_numero, 0)), F43 = "Superintendente", INDEX(Superintendente, MATCH(RIGHT(AC43), premissas_nivel_cargo_letra, 0), MATCH(VALUE(LEFT(AC43)), premissas_nivel_cargo_numero, 0)), F43 = "Coordenador(a)", INDEX(Coordenador, MATCH(RIGHT(AC43), premissas_nivel_cargo_letra, 0), MATCH(VALUE(LEFT(AC43)), premissas_nivel_cargo_numero, 0)), F43 = "Chefe", INDEX(Chefe, MATCH(RIGHT(AC43), premissas_nivel_cargo_letra, 0), MATCH(VALUE(LEFT(AC43)), premissas_nivel_cargo_numero, 0)), F43 = "Diretor(a)", INDEX(Diretor, MATCH(RIGHT(AC43), premissas_nivel_cargo_letra, 0), MATCH(VALUE(LEFT(AC43)), premissas_nivel_cargo_numero, 0)), F43 = "Gerente", INDEX(Gerente, MATCH(RIGHT(AC43), premissas_nivel_cargo_letra, 0), MATCH(VALUE(LEFT(AC43)), premissas_nivel_cargo_numero, 0)), F43 = "Assessor(a)", INDEX(Assessor, MATCH(RIGHT(AC43), premissas_nivel_cargo_letra, 0), MATCH(VALUE(LEFT(AC43)), premissas_nivel_cargo_numero, 0)), F43 = "Ouvidor(a)", INDEX(Ouvidor, MATCH(RIGHT(AC43), premissas_nivel_cargo_letra, 0), MATCH(VALUE(LEFT(AC43)), premissas_nivel_cargo_numero, 0)) ), "")} | AE43: =ifs(G43 = "", "", AD43 = "", "Ainda Não Classificado", NOT(AD43 = ""), "Classificado com Sucesso")
A44: =IFERROR(__xludf.dummyfunction("""COMPUTED_VALUE"""),43) | B44: =IFERROR(__xludf.dummyfunction("""COMPUTED_VALUE"""),"CASA CIVIL") | C44: =IFERROR(__xludf.dummyfunction("""COMPUTED_VALUE"""),"3º") | D44: =IFERROR(__xludf.dummyfunction("""COMPUTED_VALUE"""),"Coordenadoria de Desenvolvimento de Projetos e Transversalidade") | E44: =IFERROR(__xludf.dummyfunction("""COMPUTED_VALUE"""),"Coordenador I") | F44: =IFERROR(__xludf.dummyfunction("""COMPUTED_VALUE"""),"Coordenador(a)") | G44: =IFERROR(__xludf.dummyfunction("""COMPUTED_VALUE"""),"Técnico-Operacional") | H44: =IFERROR(__xludf.dummyfunction("""COMPUTED_VALUE"""),"Gestão") | I44: #NAME? | J44: #NAME? | K44: #NAME? | L44: #NAME? | M44: #NAME? | N44: #NAME? | S44: #NAME? | T44: #NAME? | U44: #NAME? | V44: #NAME? | W44: #NAME? | X44: #NAME? | Y44: 0 | Z44: Não | AA44: 0 | AB44: Baixa | AD44: {=IFERROR(ifs( F44 = "Secretário(a)", INDEX(Secretario, MATCH(RIGHT(AC44), premissas_nivel_cargo_letra, 0), MATCH(VALUE(LEFT(AC44)), premissas_nivel_cargo_numero, 0)), F44 = "Presidente", INDEX(Presidente, MATCH(RIGHT(AC44), premissas_nivel_cargo_letra, 0), MATCH(VALUE(LEFT(AC44)), premissas_nivel_cargo_numero, 0)), F44 = "Subsecretário(a)", INDEX(Subsecretario, MATCH(RIGHT(AC44), premissas_nivel_cargo_letra, 0), MATCH(VALUE(LEFT(AC44)), premissas_nivel_cargo_numero, 0)), F44 = "Superintendente", INDEX(Superintendente, MATCH(RIGHT(AC44), premissas_nivel_cargo_letra, 0), MATCH(VALUE(LEFT(AC44)), premissas_nivel_cargo_numero, 0)), F44 = "Coordenador(a)", INDEX(Coordenador, MATCH(RIGHT(AC44), premissas_nivel_cargo_letra, 0), MATCH(VALUE(LEFT(AC44)), premissas_nivel_cargo_numero, 0)), F44 = "Chefe", INDEX(Chefe, MATCH(RIGHT(AC44), premissas_nivel_cargo_letra, 0), MATCH(VALUE(LEFT(AC44)), premissas_nivel_cargo_numero, 0)), F44 = "Diretor(a)", INDEX(Diretor, MATCH(RIGHT(AC44), premissas_nivel_cargo_letra, 0), MATCH(VALUE(LEFT(AC44)), premissas_nivel_cargo_numero, 0)), F44 = "Gerente", INDEX(Gerente, MATCH(RIGHT(AC44), premissas_nivel_cargo_letra, 0), MATCH(VALUE(LEFT(AC44)), premissas_nivel_cargo_numero, 0)), F44 = "Assessor(a)", INDEX(Assessor, MATCH(RIGHT(AC44), premissas_nivel_cargo_letra, 0), MATCH(VALUE(LEFT(AC44)), premissas_nivel_cargo_numero, 0)), F44 = "Ouvidor(a)", INDEX(Ouvidor, MATCH(RIGHT(AC44), premissas_nivel_cargo_letra, 0), MATCH(VALUE(LEFT(AC44)), premissas_nivel_cargo_numero, 0)) ), "")} | AE44: =ifs(G44 = "", "", AD44 = "", "Ainda Não Classificado", NOT(AD44 = ""), "Classificado com Sucesso")
A45: =IFERROR(__xludf.dummyfunction("""COMPUTED_VALUE"""),44) | B45: =IFERROR(__xludf.dummyfunction("""COMPUTED_VALUE"""),"CASA CIVIL") | C45: =IFERROR(__xludf.dummyfunction("""COMPUTED_VALUE"""),"3º") | D45: =IFERROR(__xludf.dummyfunction("""COMPUTED_VALUE"""),"Coordenadoria de Gestão de Lideranças") | E45: =IFERROR(__xludf.dummyfunction("""COMPUTED_VALUE"""),"Coordenador I") | F45: =IFERROR(__xludf.dummyfunction("""COMPUTED_VALUE"""),"Coordenador(a)") | G45: =IFERROR(__xludf.dummyfunction("""COMPUTED_VALUE"""),"Administrativo") | H45: =IFERROR(__xludf.dummyfunction("""COMPUTED_VALUE"""),"Gestão") | I45: #NAME? | J45: #NAME? | K45: #NAME? | L45: #NAME? | M45: #NAME? | N45: #NAME? | S45: #NAME? | T45: #NAME? | U45: #NAME? | V45: #NAME? | W45: #NAME? | X45: #NAME? | Y45: 0 | Z45: Não | AA45: 0 | AB45: Baixa | AD45: {=IFERROR(ifs( F45 = "Secretário(a)", INDEX(Secretario, MATCH(RIGHT(AC45), premissas_nivel_cargo_letra, 0), MATCH(VALUE(LEFT(AC45)), premissas_nivel_cargo_numero, 0)), F45 = "Presidente", INDEX(Presidente, MATCH(RIGHT(AC45), premissas_nivel_cargo_letra, 0), MATCH(VALUE(LEFT(AC45)), premissas_nivel_cargo_numero, 0)), F45 = "Subsecretário(a)", INDEX(Subsecretario, MATCH(RIGHT(AC45), premissas_nivel_cargo_letra, 0), MATCH(VALUE(LEFT(AC45)), premissas_nivel_cargo_numero, 0)), F45 = "Superintendente", INDEX(Superintendente, MATCH(RIGHT(AC45), premissas_nivel_cargo_letra, 0), MATCH(VALUE(LEFT(AC45)), premissas_nivel_cargo_numero, 0)), F45 = "Coordenador(a)", INDEX(Coordenador, MATCH(RIGHT(AC45), premissas_nivel_cargo_letra, 0), MATCH(VALUE(LEFT(AC45)), premissas_nivel_cargo_numero, 0)), F45 = "Chefe", INDEX(Chefe, MATCH(RIGHT(AC45), premissas_nivel_cargo_letra, 0), MATCH(VALUE(LEFT(AC45)), premissas_nivel_cargo_numero, 0)), F45 = "Diretor(a)", INDEX(Diretor, MATCH(RIGHT(AC45), premissas_nivel_cargo_letra, 0), MATCH(VALUE(LEFT(AC45)), premissas_nivel_cargo_numero, 0)), F45 = "Gerente", INDEX(Gerente, MATCH(RIGHT(AC45), premissas_nivel_cargo_letra, 0), MATCH(VALUE(LEFT(AC45)), premissas_nivel_cargo_numero, 0)), F45 = "Assessor(a)", INDEX(Assessor, MATCH(RIGHT(AC45), premissas_nivel_cargo_letra, 0), MATCH(VALUE(LEFT(AC45)), premissas_nivel_cargo_numero, 0)), F45 = "Ouvidor(a)", INDEX(Ouvidor, MATCH(RIGHT(AC45), premissas_nivel_cargo_letra, 0), MATCH(VALUE(LEFT(AC45)), premissas_nivel_cargo_numero, 0)) ), "")} | AE45: =ifs(G45 = "", "", AD45 = "", "Ainda Não Classificado", NOT(AD45 = ""), "Classificado com Sucesso")
A46: =IFERROR(__xludf.dummyfunction("""COMPUTED_VALUE"""),45) | B46: =IFERROR(__xludf.dummyfunction("""COMPUTED_VALUE"""),"CASA CIVIL") | C46: =IFERROR(__xludf.dummyfunction("""COMPUTED_VALUE"""),"3º") | D46: =IFERROR(__xludf.dummyfunction("""COMPUTED_VALUE"""),"Coordenadoria de Capacitação e Desenvolvimento") | E46: =IFERROR(__xludf.dummyfunction("""COMPUTED_VALUE"""),"Coordenador I") | F46: =IFERROR(__xludf.dummyfunction("""COMPUTED_VALUE"""),"Coordenador(a)") | G46: =IFERROR(__xludf.dummyfunction("""COMPUTED_VALUE"""),"Administrativo") | H46: =IFERROR(__xludf.dummyfunction("""COMPUTED_VALUE"""),"Gestão") | I46: #NAME? | J46: #NAME? | K46: #NAME? | L46: #NAME? | M46: #NAME? | N46: #NAME? | S46: #NAME? | T46: #NAME? | U46: #NAME? | V46: #NAME? | W46: #NAME? | X46: #NAME? | Y46: 0 | Z46: Não | AA46: 0 | AB46: Baixa | AD46: {=IFERROR(ifs( F46 = "Secretário(a)", INDEX(Secretario, MATCH(RIGHT(AC46), premissas_nivel_cargo_letra, 0), MATCH(VALUE(LEFT(AC46)), premissas_nivel_cargo_numero, 0)), F46 = "Presidente", INDEX(Presidente, MATCH(RIGHT(AC46), premissas_nivel_cargo_letra, 0), MATCH(VALUE(LEFT(AC46)), premissas_nivel_cargo_numero, 0)), F46 = "Subsecretário(a)", INDEX(Subsecretario, MATCH(RIGHT(AC46), premissas_nivel_cargo_letra, 0), MATCH(VALUE(LEFT(AC46)), premissas_nivel_cargo_numero, 0)), F46 = "Superintendente", INDEX(Superintendente, MATCH(RIGHT(AC46), premissas_nivel_cargo_letra, 0), MATCH(VALUE(LEFT(AC46)), premissas_nivel_cargo_numero, 0)), F46 = "Coordenador(a)", INDEX(Coordenador, MATCH(RIGHT(AC46), premissas_nivel_cargo_letra, 0), MATCH(VALUE(LEFT(AC46)), premissas_nivel_cargo_numero, 0)), F46 = "Chefe", INDEX(Chefe, MATCH(RIGHT(AC46), premissas_nivel_cargo_letra, 0), MATCH(VALUE(LEFT(AC46)), premissas_nivel_cargo_numero, 0)), F46 = "Diretor(a)", INDEX(Diretor, MATCH(RIGHT(AC46), premissas_nivel_cargo_letra, 0), MATCH(VALUE(LEFT(AC46)), premissas_nivel_cargo_numero, 0)), F46 = "Gerente", INDEX(Gerente, MATCH(RIGHT(AC46), premissas_nivel_cargo_letra, 0), MATCH(VALUE(LEFT(AC46)), premissas_nivel_cargo_numero, 0)), F46 = "Assessor(a)", INDEX(Assessor, MATCH(RIGHT(AC46), premissas_nivel_cargo_letra, 0), MATCH(VALUE(LEFT(AC46)), premissas_nivel_cargo_numero, 0)), F46 = "Ouvidor(a)", INDEX(Ouvidor, MATCH(RIGHT(AC46), premissas_nivel_cargo_letra, 0), MATCH(VALUE(LEFT(AC46)), premissas_nivel_cargo_numero, 0)) ), "")} | AE46: =ifs(G46 = "", "", AD46 = "", "Ainda Não Classificado", NOT(AD46 = ""), "Classificado com Sucesso")
A47: =IFERROR(__xludf.dummyfunction("""COMPUTED_VALUE"""),46) | B47: =IFERROR(__xludf.dummyfunction("""COMPUTED_VALUE"""),"CASA CIVIL") | C47: =IFERROR(__xludf.dummyfunction("""COMPUTED_VALUE"""),"2º") | D47: =IFERROR(__xludf.dummyfunction("""COMPUTED_VALUE"""),"Central de Inteligência, Vigilância e Tecnologia de Apoio a Segurança Pública") | E47: =IFERROR(__xludf.dummyfunction("""COMPUTED_VALUE"""),"Chefe Executivo") | F47: =IFERROR(__xludf.dummyfunction("""COMPUTED_VALUE"""),"Chefe") | G47: =IFERROR(__xludf.dummyfunction("""COMPUTED_VALUE"""),"Técnico-Operacional") | H47: =IFERROR(__xludf.dummyfunction("""COMPUTED_VALUE"""),"Gestão") | I47: #NAME? | J47: #NAME? | K47: #NAME? | L47: #NAME? | M47: #NAME? | N47: #NAME? | S47: #NAME? | T47: #NAME? | U47: #NAME? | V47: #NAME? | W47: #NAME? | X47: #NAME? | Y47: 0 | Z47: Não | AA47: 0 | AB47: Baixa | AD47: {=IFERROR(ifs( F47 = "Secretário(a)", INDEX(Secretario, MATCH(RIGHT(AC47), premissas_nivel_cargo_letra, 0), MATCH(VALUE(LEFT(AC47)), premissas_nivel_cargo_numero, 0)), F47 = "Presidente", INDEX(Presidente, MATCH(RIGHT(AC47), premissas_nivel_cargo_letra, 0), MATCH(VALUE(LEFT(AC47)), premissas_nivel_cargo_numero, 0)), F47 = "Subsecretário(a)", INDEX(Subsecretario, MATCH(RIGHT(AC47), premissas_nivel_cargo_letra, 0), MATCH(VALUE(LEFT(AC47)), premissas_nivel_cargo_numero, 0)), F47 = "Superintendente", INDEX(Superintendente, MATCH(RIGHT(AC47), premissas_nivel_cargo_letra, 0), MATCH(VALUE(LEFT(AC47)), premissas_nivel_cargo_numero, 0)), F47 = "Coordenador(a)", INDEX(Coordenador, MATCH(RIGHT(AC47), premissas_nivel_cargo_letra, 0), MATCH(VALUE(LEFT(AC47)), premissas_nivel_cargo_numero, 0)), F47 = "Chefe", INDEX(Chefe, MATCH(RIGHT(AC47), premissas_nivel_cargo_letra, 0), MATCH(VALUE(LEFT(AC47)), premissas_nivel_cargo_numero, 0)), F47 = "Diretor(a)", INDEX(Diretor, MATCH(RIGHT(AC47), premissas_nivel_cargo_letra, 0), MATCH(VALUE(LEFT(AC47)), premissas_nivel_cargo_numero, 0)), F47 = "Gerente", INDEX(Gerente, MATCH(RIGHT(AC47), premissas_nivel_cargo_letra, 0), MATCH(VALUE(LEFT(AC47)), premissas_nivel_cargo_numero, 0)), F47 = "Assessor(a)", INDEX(Assessor, MATCH(RIGHT(AC47), premissas_nivel_cargo_letra, 0), MATCH(VALUE(LEFT(AC47)), premissas_nivel_cargo_numero, 0)), F47 = "Ouvidor(a)", INDEX(Ouvidor, MATCH(RIGHT(AC47), premissas_nivel_cargo_letra, 0), MATCH(VALUE(LEFT(AC47)), premissas_nivel_cargo_numero, 0)) ), "")} | AE47: =ifs(G47 = "", "", AD47 = "", "Ainda Não Classificado", NOT(AD47 = ""), "Classificado com Sucesso")
A48: =IFERROR(__xludf.dummyfunction("""COMPUTED_VALUE"""),47) | B48: =IFERROR(__xludf.dummyfunction("""COMPUTED_VALUE"""),"CASA CIVIL") | C48: =IFERROR(__xludf.dummyfunction("""COMPUTED_VALUE"""),"3º") | D48: =IFERROR(__xludf.dummyfunction("""COMPUTED_VALUE"""),"Coordenadoria Técnica de Inteligência e Dados") | E48: =IFERROR(__xludf.dummyfunction("""COMPUTED_VALUE"""),"Coordenador Técnico") | F48: =IFERROR(__xludf.dummyfunction("""COMPUTED_VALUE"""),"Coordenador(a)") | G48: =IFERROR(__xludf.dummyfunction("""COMPUTED_VALUE"""),"Tecnologias da Informação") | H48: =IFERROR(__xludf.dummyfunction("""COMPUTED_VALUE"""),"Gestão") | I48: #NAME? | J48: #NAME? | K48: #NAME? | L48: #NAME? | M48: #NAME? | N48: #NAME? | S48: #NAME? | T48: #NAME? | U48: #NAME? | V48: #NAME? | W48: #NAME? | X48: #NAME? | Y48: 0 | Z48: Não | AA48: 0 | AB48: Baixa | AD48: {=IFERROR(ifs( F48 = "Secretário(a)", INDEX(Secretario, MATCH(RIGHT(AC48), premissas_nivel_cargo_letra, 0), MATCH(VALUE(LEFT(AC48)), premissas_nivel_cargo_numero, 0)), F48 = "Presidente", INDEX(Presidente, MATCH(RIGHT(AC48), premissas_nivel_cargo_letra, 0), MATCH(VALUE(LEFT(AC48)), premissas_nivel_cargo_numero, 0)), F48 = "Subsecretário(a)", INDEX(Subsecretario, MATCH(RIGHT(AC48), premissas_nivel_cargo_letra, 0), MATCH(VALUE(LEFT(AC48)), premissas_nivel_cargo_numero, 0)), F48 = "Superintendente", INDEX(Superintendente, MATCH(RIGHT(AC48), premissas_nivel_cargo_letra, 0), MATCH(VALUE(LEFT(AC48)), premissas_nivel_cargo_numero, 0)), F48 = "Coordenador(a)", INDEX(Coordenador, MATCH(RIGHT(AC48), premissas_nivel_cargo_letra, 0), MATCH(VALUE(LEFT(AC48)), premissas_nivel_cargo_numero, 0)), F48 = "Chefe", INDEX(Chefe, MATCH(RIGHT(AC48), premissas_nivel_cargo_letra, 0), MATCH(VALUE(LEFT(AC48)), premissas_nivel_cargo_numero, 0)), F48 = "Diretor(a)", INDEX(Diretor, MATCH(RIGHT(AC48), premissas_nivel_cargo_letra, 0), MATCH(VALUE(LEFT(AC48)), premissas_nivel_cargo_numero, 0)), F48 = "Gerente", INDEX(Gerente, MATCH(RIGHT(AC48), premissas_nivel_cargo_letra, 0), MATCH(VALUE(LEFT(AC48)), premissas_nivel_cargo_numero, 0)), F48 = "Assessor(a)", INDEX(Assessor, MATCH(RIGHT(AC48), premissas_nivel_cargo_letra, 0), MATCH(VALUE(LEFT(AC48)), premissas_nivel_cargo_numero, 0)), F48 = "Ouvidor(a)", INDEX(Ouvidor, MATCH(RIGHT(AC48), premissas_nivel_cargo_letra, 0), MATCH(VALUE(LEFT(AC48)), premissas_nivel_cargo_numero, 0)) ), "")} | AE48: =ifs(G48 = "", "", AD48 = "", "Ainda Não Classificado", NOT(AD48 = ""), "Classificado com Sucesso")
A49: =IFERROR(__xludf.dummyfunction("""COMPUTED_VALUE"""),48) | B49: =IFERROR(__xludf.dummyfunction("""COMPUTED_VALUE"""),"CASA CIVIL") | C49: =IFERROR(__xludf.dummyfunction("""COMPUTED_VALUE"""),"3º") | D49: =IFERROR(__xludf.dummyfunction("""COMPUTED_VALUE"""),"Coordenadoria Técnica de Monitoramento e Operações") | E49: =IFERROR(__xludf.dummyfunction("""COMPUTED_VALUE"""),"Coordenador Técnico") | F49: =IFERROR(__xludf.dummyfunction("""COMPUTED_VALUE"""),"Coordenador(a)") | G49: =IFERROR(__xludf.dummyfunction("""COMPUTED_VALUE"""),"Técnico-Operacional") | H49: =IFERROR(__xludf.dummyfunction("""COMPUTED_VALUE"""),"Gestão") | I49: #NAME? | J49: #NAME? | K49: #NAME? | L49: #NAME? | M49: #NAME? | N49: #NAME? | S49: #NAME? | T49: #NAME? | U49: #NAME? | V49: #NAME? | W49: #NAME? | X49: #NAME? | Y49: 0 | Z49: Não | AA49: 0 | AB49: Baixa | AD49: {=IFERROR(ifs( F49 = "Secretário(a)", INDEX(Secretario, MATCH(RIGHT(AC49), premissas_nivel_cargo_letra, 0), MATCH(VALUE(LEFT(AC49)), premissas_nivel_cargo_numero, 0)), F49 = "Presidente", INDEX(Presidente, MATCH(RIGHT(AC49), premissas_nivel_cargo_letra, 0), MATCH(VALUE(LEFT(AC49)), premissas_nivel_cargo_numero, 0)), F49 = "Subsecretário(a)", INDEX(Subsecretario, MATCH(RIGHT(AC49), premissas_nivel_cargo_letra, 0), MATCH(VALUE(LEFT(AC49)), premissas_nivel_cargo_numero, 0)), F49 = "Superintendente", INDEX(Superintendente, MATCH(RIGHT(AC49), premissas_nivel_cargo_letra, 0), MATCH(VALUE(LEFT(AC49)), premissas_nivel_cargo_numero, 0)), F49 = "Coordenador(a)", INDEX(Coordenador, MATCH(RIGHT(AC49), premissas_nivel_cargo_letra, 0), MATCH(VALUE(LEFT(AC49)), premissas_nivel_cargo_numero, 0)), F49 = "Chefe", INDEX(Chefe, MATCH(RIGHT(AC49), premissas_nivel_cargo_letra, 0), MATCH(VALUE(LEFT(AC49)), premissas_nivel_cargo_numero, 0)), F49 = "Diretor(a)", INDEX(Diretor, MATCH(RIGHT(AC49), premissas_nivel_cargo_letra, 0), MATCH(VALUE(LEFT(AC49)), premissas_nivel_cargo_numero, 0)), F49 = "Gerente", INDEX(Gerente, MATCH(RIGHT(AC49), premissas_nivel_cargo_letra, 0), MATCH(VALUE(LEFT(AC49)), premissas_nivel_cargo_numero, 0)), F49 = "Assessor(a)", INDEX(Assessor, MATCH(RIGHT(AC49), premissas_nivel_cargo_letra, 0), MATCH(VALUE(LEFT(AC49)), premissas_nivel_cargo_numero, 0)), F49 = "Ouvidor(a)", INDEX(Ouvidor, MATCH(RIGHT(AC49), premissas_nivel_cargo_letra, 0), MATCH(VALUE(LEFT(AC49)), premissas_nivel_cargo_numero, 0)) ), "")} | AE49: =ifs(G49 = "", "", AD49 = "", "Ainda Não Classificado", NOT(AD49 = ""), "Classificado com Sucesso")
A50: =IFERROR(__xludf.dummyfunction("""COMPUTED_VALUE"""),49) | B50: =IFERROR(__xludf.dummyfunction("""COMPUTED_VALUE"""),"CASA CIVIL") | C50: =IFERROR(__xludf.dummyfunction("""COMPUTED_VALUE"""),"2º") | D50: =IFERROR(__xludf.dummyfunction("""COMPUTED_VALUE"""),"Coordenadoria Geral de Comunicação Institucional") | E50: =IFERROR(__xludf.dummyfunction("""COMPUTED_VALUE"""),"Coordenador Geral") | F50: =IFERROR(__xludf.dummyfunction("""COMPUTED_VALUE"""),"Coordenador(a)") | G50: =IFERROR(__xludf.dummyfunction("""COMPUTED_VALUE"""),"Comunicação e Relacionamento com o Cidadão") | H50: =IFERROR(__xludf.dummyfunction("""COMPUTED_VALUE"""),"Gestão") | I50: #NAME? | J50: #NAME? | K50: #NAME? | L50: #NAME? | M50: #NAME? | N50: #NAME? | S50: #NAME? | T50: #NAME? | U50: #NAME? | V50: #NAME? | W50: #NAME? | X50: #NAME? | Y50: 0 | Z50: Não | AA50: 0 | AB50: Baixa | AD50: {=IFERROR(ifs( F50 = "Secretário(a)", INDEX(Secretario, MATCH(RIGHT(AC50), premissas_nivel_cargo_letra, 0), MATCH(VALUE(LEFT(AC50)), premissas_nivel_cargo_numero, 0)), F50 = "Presidente", INDEX(Presidente, MATCH(RIGHT(AC50), premissas_nivel_cargo_letra, 0), MATCH(VALUE(LEFT(AC50)), premissas_nivel_cargo_numero, 0)), F50 = "Subsecretário(a)", INDEX(Subsecretario, MATCH(RIGHT(AC50), premissas_nivel_cargo_letra, 0), MATCH(VALUE(LEFT(AC50)), premissas_nivel_cargo_numero, 0)), F50 = "Superintendente", INDEX(Superintendente, MATCH(RIGHT(AC50), premissas_nivel_cargo_letra, 0), MATCH(VALUE(LEFT(AC50)), premissas_nivel_cargo_numero, 0)), F50 = "Coordenador(a)", INDEX(Coordenador, MATCH(RIGHT(AC50), premissas_nivel_cargo_letra, 0), MATCH(VALUE(LEFT(AC50)), premissas_nivel_cargo_numero, 0)), F50 = "Chefe", INDEX(Chefe, MATCH(RIGHT(AC50), premissas_nivel_cargo_letra, 0), MATCH(VALUE(LEFT(AC50)), premissas_nivel_cargo_numero, 0)), F50 = "Diretor(a)", INDEX(Diretor, MATCH(RIGHT(AC50), premissas_nivel_cargo_letra, 0), MATCH(VALUE(LEFT(AC50)), premissas_nivel_cargo_numero, 0)), F50 = "Gerente", INDEX(Gerente, MATCH(RIGHT(AC50), premissas_nivel_cargo_letra, 0), MATCH(VALUE(LEFT(AC50)), premissas_nivel_cargo_numero, 0)), F50 = "Assessor(a)", INDEX(Assessor, MATCH(RIGHT(AC50), premissas_nivel_cargo_letra, 0), MATCH(VALUE(LEFT(AC50)), premissas_nivel_cargo_numero, 0)), F50 = "Ouvidor(a)", INDEX(Ouvidor, MATCH(RIGHT(AC50), premissas_nivel_cargo_letra, 0), MATCH(VALUE(LEFT(AC50)), premissas_nivel_cargo_numero, 0)) ), "")} | AE50: =ifs(G50 = "", "", AD50 = "", "Ainda Não Classificado", NOT(AD50 = ""), "Classificado com Sucesso")
A51: =IFERROR(__xludf.dummyfunction("""COMPUTED_VALUE"""),50) | B51: =IFERROR(__xludf.dummyfunction("""COMPUTED_VALUE"""),"CASA CIVIL") | C51: =IFERROR(__xludf.dummyfunction("""COMPUTED_VALUE"""),"3º") | D51: =IFERROR(__xludf.dummyfunction("""COMPUTED_VALUE"""),"Gerência de Imprensa") | E51: =IFERROR(__xludf.dummyfunction("""COMPUTED_VALUE"""),"Gerente III") | F51: =IFERROR(__xludf.dummyfunction("""COMPUTED_VALUE"""),"Gerente") | G51: =IFERROR(__xludf.dummyfunction("""COMPUTED_VALUE"""),"Comunicação e Relacionamento com o Cidadão") | H51: =IFERROR(__xludf.dummyfunction("""COMPUTED_VALUE"""),"Gestão") | I51: #NAME? | J51: #NAME? | K51: #NAME? | L51: #NAME? | M51: #NAME? | N51: #NAME? | S51: #NAME? | T51: #NAME? | U51: #NAME? | V51: #NAME? | W51: #NAME? | X51: #NAME? | Y51: 0 | Z51: Não | AA51: 0 | AB51: Baixa | AD51: {=IFERROR(ifs( F51 = "Secretário(a)", INDEX(Secretario, MATCH(RIGHT(AC51), premissas_nivel_cargo_letra, 0), MATCH(VALUE(LEFT(AC51)), premissas_nivel_cargo_numero, 0)), F51 = "Presidente", INDEX(Presidente, MATCH(RIGHT(AC51), premissas_nivel_cargo_letra, 0), MATCH(VALUE(LEFT(AC51)), premissas_nivel_cargo_numero, 0)), F51 = "Subsecretário(a)", INDEX(Subsecretario, MATCH(RIGHT(AC51), premissas_nivel_cargo_letra, 0), MATCH(VALUE(LEFT(AC51)), premissas_nivel_cargo_numero, 0)), F51 = "Superintendente", INDEX(Superintendente, MATCH(RIGHT(AC51), premissas_nivel_cargo_letra, 0), MATCH(VALUE(LEFT(AC51)), premissas_nivel_cargo_numero, 0)), F51 = "Coordenador(a)", INDEX(Coordenador, MATCH(RIGHT(AC51), premissas_nivel_cargo_letra, 0), MATCH(VALUE(LEFT(AC51)), premissas_nivel_cargo_numero, 0)), F51 = "Chefe", INDEX(Chefe, MATCH(RIGHT(AC51), premissas_nivel_cargo_letra, 0), MATCH(VALUE(LEFT(AC51)), premissas_nivel_cargo_numero, 0)), F51 = "Diretor(a)", INDEX(Diretor, MATCH(RIGHT(AC51), premissas_nivel_cargo_letra, 0), MATCH(VALUE(LEFT(AC51)), premissas_nivel_cargo_numero, 0)), F51 = "Gerente", INDEX(Gerente, MATCH(RIGHT(AC51), premissas_nivel_cargo_letra, 0), MATCH(VALUE(LEFT(AC51)), premissas_nivel_cargo_numero, 0)), F51 = "Assessor(a)", INDEX(Assessor, MATCH(RIGHT(AC51), premissas_nivel_cargo_letra, 0), MATCH(VALUE(LEFT(AC51)), premissas_nivel_cargo_numero, 0)), F51 = "Ouvidor(a)", INDEX(Ouvidor, MATCH(RIGHT(AC51), premissas_nivel_cargo_letra, 0), MATCH(VALUE(LEFT(AC51)), premissas_nivel_cargo_numero, 0)) ), "")} | AE51: =ifs(G51 = "", "", AD51 = "", "Ainda Não Classificado", NOT(AD51 = ""), "Classificado com Sucesso")
A52: =IFERROR(__xludf.dummyfunction("""COMPUTED_VALUE"""),51) | B52: =IFERROR(__xludf.dummyfunction("""COMPUTED_VALUE"""),"CASA CIVIL") | C52: =IFERROR(__xludf.dummyfunction("""COMPUTED_VALUE"""),"3º") | D52: =IFERROR(__xludf.dummyfunction("""COMPUTED_VALUE"""),"Gerência de Conteúdo Estratégico") | E52: =IFERROR(__xludf.dummyfunction("""COMPUTED_VALUE"""),"Gerente III") | F52: =IFERROR(__xludf.dummyfunction("""COMPUTED_VALUE"""),"Gerente") | G52: =IFERROR(__xludf.dummyfunction("""COMPUTED_VALUE"""),"Comunicação e Relacionamento com o Cidadão") | H52: =IFERROR(__xludf.dummyfunction("""COMPUTED_VALUE"""),"Gestão") | I52: #NAME? | J52: #NAME? | K52: #NAME? | L52: #NAME? | M52: #NAME? | N52: #NAME? | S52: #NAME? | T52: #NAME? | U52: #NAME? | V52: #NAME? | W52: #NAME? | X52: #NAME? | Y52: 0 | Z52: Não | AA52: 0 | AB52: Baixa | AD52: {=IFERROR(ifs( F52 = "Secretário(a)", INDEX(Secretario, MATCH(RIGHT(AC52), premissas_nivel_cargo_letra, 0), MATCH(VALUE(LEFT(AC52)), premissas_nivel_cargo_numero, 0)), F52 = "Presidente", INDEX(Presidente, MATCH(RIGHT(AC52), premissas_nivel_cargo_letra, 0), MATCH(VALUE(LEFT(AC52)), premissas_nivel_cargo_numero, 0)), F52 = "Subsecretário(a)", INDEX(Subsecretario, MATCH(RIGHT(AC52), premissas_nivel_cargo_letra, 0), MATCH(VALUE(LEFT(AC52)), premissas_nivel_cargo_numero, 0)), F52 = "Superintendente", INDEX(Superintendente, MATCH(RIGHT(AC52), premissas_nivel_cargo_letra, 0), MATCH(VALUE(LEFT(AC52)), premissas_nivel_cargo_numero, 0)), F52 = "Coordenador(a)", INDEX(Coordenador, MATCH(RIGHT(AC52), premissas_nivel_cargo_letra, 0), MATCH(VALUE(LEFT(AC52)), premissas_nivel_cargo_numero, 0)), F52 = "Chefe", INDEX(Chefe, MATCH(RIGHT(AC52), premissas_nivel_cargo_letra, 0), MATCH(VALUE(LEFT(AC52)), premissas_nivel_cargo_numero, 0)), F52 = "Diretor(a)", INDEX(Diretor, MATCH(RIGHT(AC52), premissas_nivel_cargo_letra, 0), MATCH(VALUE(LEFT(AC52)), premissas_nivel_cargo_numero, 0)), F52 = "Gerente", INDEX(Gerente, MATCH(RIGHT(AC52), premissas_nivel_cargo_letra, 0), MATCH(VALUE(LEFT(AC52)), premissas_nivel_cargo_numero, 0)), F52 = "Assessor(a)", INDEX(Assessor, MATCH(RIGHT(AC52), premissas_nivel_cargo_letra, 0), MATCH(VALUE(LEFT(AC52)), premissas_nivel_cargo_numero, 0)), F52 = "Ouvidor(a)", INDEX(Ouvidor, MATCH(RIGHT(AC52), premissas_nivel_cargo_letra, 0), MATCH(VALUE(LEFT(AC52)), premissas_nivel_cargo_numero, 0)) ), "")} | AE52: =ifs(G52 = "", "", AD52 = "", "Ainda Não Classificado", NOT(AD52 = ""), "Classificado com Sucesso")
A53: =IFERROR(__xludf.dummyfunction("""COMPUTED_VALUE"""),52) | B53: =IFERROR(__xludf.dummyfunction("""COMPUTED_VALUE"""),"CASA CIVIL") | C53: =IFERROR(__xludf.dummyfunction("""COMPUTED_VALUE"""),"3º") | D53: =IFERROR(__xludf.dummyfunction("""COMPUTED_VALUE"""),"Coordenação de Publicidade") | E53: =IFERROR(__xludf.dummyfunction("""COMPUTED_VALUE"""),"Coordenador II") | F53: =IFERROR(__xludf.dummyfunction("""COMPUTED_VALUE"""),"Coordenador(a)") | G53: =IFERROR(__xludf.dummyfunction("""COMPUTED_VALUE"""),"Comunicação e Relacionamento com o Cidadão") | H53: =IFERROR(__xludf.dummyfunction("""COMPUTED_VALUE"""),"Gestão") | I53: #NAME? | J53: #NAME? | K53: #NAME? | L53: #NAME? | M53: #NAME? | N53: #NAME? | S53: #NAME? | T53: #NAME? | U53: #NAME? | V53: #NAME? | W53: #NAME? | X53: #NAME? | Y53: 0 | Z53: Não | AA53: 0 | AB53: Baixa | AD53: {=IFERROR(ifs( F53 = "Secretário(a)", INDEX(Secretario, MATCH(RIGHT(AC53), premissas_nivel_cargo_letra, 0), MATCH(VALUE(LEFT(AC53)), premissas_nivel_cargo_numero, 0)), F53 = "Presidente", INDEX(Presidente, MATCH(RIGHT(AC53), premissas_nivel_cargo_letra, 0), MATCH(VALUE(LEFT(AC53)), premissas_nivel_cargo_numero, 0)), F53 = "Subsecretário(a)", INDEX(Subsecretario, MATCH(RIGHT(AC53), premissas_nivel_cargo_letra, 0), MATCH(VALUE(LEFT(AC53)), premissas_nivel_cargo_numero, 0)), F53 = "Superintendente", INDEX(Superintendente, MATCH(RIGHT(AC53), premissas_nivel_cargo_letra, 0), MATCH(VALUE(LEFT(AC53)), premissas_nivel_cargo_numero, 0)), F53 = "Coordenador(a)", INDEX(Coordenador, MATCH(RIGHT(AC53), premissas_nivel_cargo_letra, 0), MATCH(VALUE(LEFT(AC53)), premissas_nivel_cargo_numero, 0)), F53 = "Chefe", INDEX(Chefe, MATCH(RIGHT(AC53), premissas_nivel_cargo_letra, 0), MATCH(VALUE(LEFT(AC53)), premissas_nivel_cargo_numero, 0)), F53 = "Diretor(a)", INDEX(Diretor, MATCH(RIGHT(AC53), premissas_nivel_cargo_letra, 0), MATCH(VALUE(LEFT(AC53)), premissas_nivel_cargo_numero, 0)), F53 = "Gerente", INDEX(Gerente, MATCH(RIGHT(AC53), premissas_nivel_cargo_letra, 0), MATCH(VALUE(LEFT(AC53)), premissas_nivel_cargo_numero, 0)), F53 = "Assessor(a)", INDEX(Assessor, MATCH(RIGHT(AC53), premissas_nivel_cargo_letra, 0), MATCH(VALUE(LEFT(AC53)), premissas_nivel_cargo_numero, 0)), F53 = "Ouvidor(a)", INDEX(Ouvidor, MATCH(RIGHT(AC53), premissas_nivel_cargo_letra, 0), MATCH(VALUE(LEFT(AC53)), premissas_nivel_cargo_numero, 0)) ), "")} | AE53: =ifs(G53 = "", "", AD53 = "", "Ainda Não Classificado", NOT(AD53 = ""), "Classificado com Sucesso")
A54: =IFERROR(__xludf.dummyfunction("""COMPUTED_VALUE"""),53) | B54: =IFERROR(__xludf.dummyfunction("""COMPUTED_VALUE"""),"CASA CIVIL") | C54: =IFERROR(__xludf.dummyfunction("""COMPUTED_VALUE"""),"3º") | D54: =IFERROR(__xludf.dummyfunction("""COMPUTED_VALUE"""),"Gerência de Produção e Imagem") | E54: =IFERROR(__xludf.dummyfunction("""COMPUTED_VALUE"""),"Gerente III") | F54: =IFERROR(__xludf.dummyfunction("""COMPUTED_VALUE"""),"Gerente") | G54: =IFERROR(__xludf.dummyfunction("""COMPUTED_VALUE"""),"Comunicação e Relacionamento com o Cidadão") | H54: =IFERROR(__xludf.dummyfunction("""COMPUTED_VALUE"""),"Gestão") | I54: #NAME? | J54: #NAME? | K54: #NAME? | L54: #NAME? | M54: #NAME? | N54: #NAME? | S54: #NAME? | T54: #NAME? | U54: #NAME? | V54: #NAME? | W54: #NAME? | X54: #NAME? | Y54: 0 | Z54: Não | AA54: 0 | AB54: Baixa | AD54: {=IFERROR(ifs( F54 = "Secretário(a)", INDEX(Secretario, MATCH(RIGHT(AC54), premissas_nivel_cargo_letra, 0), MATCH(VALUE(LEFT(AC54)), premissas_nivel_cargo_numero, 0)), F54 = "Presidente", INDEX(Presidente, MATCH(RIGHT(AC54), premissas_nivel_cargo_letra, 0), MATCH(VALUE(LEFT(AC54)), premissas_nivel_cargo_numero, 0)), F54 = "Subsecretário(a)", INDEX(Subsecretario, MATCH(RIGHT(AC54), premissas_nivel_cargo_letra, 0), MATCH(VALUE(LEFT(AC54)), premissas_nivel_cargo_numero, 0)), F54 = "Superintendente", INDEX(Superintendente, MATCH(RIGHT(AC54), premissas_nivel_cargo_letra, 0), MATCH(VALUE(LEFT(AC54)), premissas_nivel_cargo_numero, 0)), F54 = "Coordenador(a)", INDEX(Coordenador, MATCH(RIGHT(AC54), premissas_nivel_cargo_letra, 0), MATCH(VALUE(LEFT(AC54)), premissas_nivel_cargo_numero, 0)), F54 = "Chefe", INDEX(Chefe, MATCH(RIGHT(AC54), premissas_nivel_cargo_letra, 0), MATCH(VALUE(LEFT(AC54)), premissas_nivel_cargo_numero, 0)), F54 = "Diretor(a)", INDEX(Diretor, MATCH(RIGHT(AC54), premissas_nivel_cargo_letra, 0), MATCH(VALUE(LEFT(AC54)), premissas_nivel_cargo_numero, 0)), F54 = "Gerente", INDEX(Gerente, MATCH(RIGHT(AC54), premissas_nivel_cargo_letra, 0), MATCH(VALUE(LEFT(AC54)), premissas_nivel_cargo_numero, 0)), F54 = "Assessor(a)", INDEX(Assessor, MATCH(RIGHT(AC54), premissas_nivel_cargo_letra, 0), MATCH(VALUE(LEFT(AC54)), premissas_nivel_cargo_numero, 0)), F54 = "Ouvidor(a)", INDEX(Ouvidor, MATCH(RIGHT(AC54), premissas_nivel_cargo_letra, 0), MATCH(VALUE(LEFT(AC54)), premissas_nivel_cargo_numero, 0)) ), "")} | AE54: =ifs(G54 = "", "", AD54 = "", "Ainda Não Classificado", NOT(AD54 = ""), "Classificado com Sucesso")
A55: =IFERROR(__xludf.dummyfunction("""COMPUTED_VALUE"""),54) | B55: =IFERROR(__xludf.dummyfunction("""COMPUTED_VALUE"""),"CASA CIVIL") | C55: =IFERROR(__xludf.dummyfunction("""COMPUTED_VALUE"""),"3º") | D55: =IFERROR(__xludf.dummyfunction("""COMPUTED_VALUE"""),"Gerência de Mídias Digitais") | E55: =IFERROR(__xludf.dummyfunction("""COMPUTED_VALUE"""),"Gerente III") | F55: =IFERROR(__xludf.dummyfunction("""COMPUTED_VALUE"""),"Gerente") | G55: =IFERROR(__xludf.dummyfunction("""COMPUTED_VALUE"""),"Comunicação e Relacionamento com o Cidadão") | H55: =IFERROR(__xludf.dummyfunction("""COMPUTED_VALUE"""),"Gestão") | I55: #NAME? | J55: #NAME? | K55: #NAME? | L55: #NAME? | M55: #NAME? | N55: #NAME? | S55: #NAME? | T55: #NAME? | U55: #NAME? | V55: #NAME? | W55: #NAME? | X55: #NAME? | Y55: 0 | Z55: Não | AA55: 0 | AB55: Baixa | AD55: {=IFERROR(ifs( F55 = "Secretário(a)", INDEX(Secretario, MATCH(RIGHT(AC55), premissas_nivel_cargo_letra, 0), MATCH(VALUE(LEFT(AC55)), premissas_nivel_cargo_numero, 0)), F55 = "Presidente", INDEX(Presidente, MATCH(RIGHT(AC55), premissas_nivel_cargo_letra, 0), MATCH(VALUE(LEFT(AC55)), premissas_nivel_cargo_numero, 0)), F55 = "Subsecretário(a)", INDEX(Subsecretario, MATCH(RIGHT(AC55), premissas_nivel_cargo_letra, 0), MATCH(VALUE(LEFT(AC55)), premissas_nivel_cargo_numero, 0)), F55 = "Superintendente", INDEX(Superintendente, MATCH(RIGHT(AC55), premissas_nivel_cargo_letra, 0), MATCH(VALUE(LEFT(AC55)), premissas_nivel_cargo_numero, 0)), F55 = "Coordenador(a)", INDEX(Coordenador, MATCH(RIGHT(AC55), premissas_nivel_cargo_letra, 0), MATCH(VALUE(LEFT(AC55)), premissas_nivel_cargo_numero, 0)), F55 = "Chefe", INDEX(Chefe, MATCH(RIGHT(AC55), premissas_nivel_cargo_letra, 0), MATCH(VALUE(LEFT(AC55)), premissas_nivel_cargo_numero, 0)), F55 = "Diretor(a)", INDEX(Diretor, MATCH(RIGHT(AC55), premissas_nivel_cargo_letra, 0), MATCH(VALUE(LEFT(AC55)), premissas_nivel_cargo_numero, 0)), F55 = "Gerente", INDEX(Gerente, MATCH(RIGHT(AC55), premissas_nivel_cargo_letra, 0), MATCH(VALUE(LEFT(AC55)), premissas_nivel_cargo_numero, 0)), F55 = "Assessor(a)", INDEX(Assessor, MATCH(RIGHT(AC55), premissas_nivel_cargo_letra, 0), MATCH(VALUE(LEFT(AC55)), premissas_nivel_cargo_numero, 0)), F55 = "Ouvidor(a)", INDEX(Ouvidor, MATCH(RIGHT(AC55), premissas_nivel_cargo_letra, 0), MATCH(VALUE(LEFT(AC55)), premissas_nivel_cargo_numero, 0)) ), "")} | AE55: =ifs(G55 = "", "", AD55 = "", "Ainda Não Classificado", NOT(AD55 = ""), "Classificado com Sucesso")
A56: =IFERROR(__xludf.dummyfunction("""COMPUTED_VALUE"""),55) | B56: =IFERROR(__xludf.dummyfunction("""COMPUTED_VALUE"""),"CASA CIVIL") | C56: =IFERROR(__xludf.dummyfunction("""COMPUTED_VALUE"""),"2º") | D56: =IFERROR(__xludf.dummyfunction("""COMPUTED_VALUE"""),"Coordenadoria Geral de Integração Territorial") | E56: =IFERROR(__xludf.dummyfunction("""COMPUTED_VALUE"""),"Coordenador Geral") | F56: =IFERROR(__xludf.dummyfunction("""COMPUTED_VALUE"""),"Coordenador(a)") | G56: =IFERROR(__xludf.dummyfunction("""COMPUTED_VALUE"""),"Técnico-Operacional") | H56: =IFERROR(__xludf.dummyfunction("""COMPUTED_VALUE"""),"Gestão") | I56: #NAME? | J56: #NAME? | K56: #NAME? | L56: #NAME? | M56: #NAME? | N56: #NAME? | S56: #NAME? | T56: #NAME? | U56: #NAME? | V56: #NAME? | W56: #NAME? | X56: #NAME? | Y56: 0 | Z56: Não | AA56: 0 | AB56: Baixa | AD56: {=IFERROR(ifs( F56 = "Secretário(a)", INDEX(Secretario, MATCH(RIGHT(AC56), premissas_nivel_cargo_letra, 0), MATCH(VALUE(LEFT(AC56)), premissas_nivel_cargo_numero, 0)), F56 = "Presidente", INDEX(Presidente, MATCH(RIGHT(AC56), premissas_nivel_cargo_letra, 0), MATCH(VALUE(LEFT(AC56)), premissas_nivel_cargo_numero, 0)), F56 = "Subsecretário(a)", INDEX(Subsecretario, MATCH(RIGHT(AC56), premissas_nivel_cargo_letra, 0), MATCH(VALUE(LEFT(AC56)), premissas_nivel_cargo_numero, 0)), F56 = "Superintendente", INDEX(Superintendente, MATCH(RIGHT(AC56), premissas_nivel_cargo_letra, 0), MATCH(VALUE(LEFT(AC56)), premissas_nivel_cargo_numero, 0)), F56 = "Coordenador(a)", INDEX(Coordenador, MATCH(RIGHT(AC56), premissas_nivel_cargo_letra, 0), MATCH(VALUE(LEFT(AC56)), premissas_nivel_cargo_numero, 0)), F56 = "Chefe", INDEX(Chefe, MATCH(RIGHT(AC56), premissas_nivel_cargo_letra, 0), MATCH(VALUE(LEFT(AC56)), premissas_nivel_cargo_numero, 0)), F56 = "Diretor(a)", INDEX(Diretor, MATCH(RIGHT(AC56), premissas_nivel_cargo_letra, 0), MATCH(VALUE(LEFT(AC56)), premissas_nivel_cargo_numero, 0)), F56 = "Gerente", INDEX(Gerente, MATCH(RIGHT(AC56), premissas_nivel_cargo_letra, 0), MATCH(VALUE(LEFT(AC56)), premissas_nivel_cargo_numero, 0)), F56 = "Assessor(a)", INDEX(Assessor, MATCH(RIGHT(AC56), premissas_nivel_cargo_letra, 0), MATCH(VALUE(LEFT(AC56)), premissas_nivel_cargo_numero, 0)), F56 = "Ouvidor(a)", INDEX(Ouvidor, MATCH(RIGHT(AC56), premissas_nivel_cargo_letra, 0), MATCH(VALUE(LEFT(AC56)), premissas_nivel_cargo_numero, 0)) ), "")} | AE56: =ifs(G56 = "", "", AD56 = "", "Ainda Não Classificado", NOT(AD56 = ""), "Classificado com Sucesso")
A57: =IFERROR(__xludf.dummyfunction("""COMPUTED_VALUE"""),56) | B57: =IFERROR(__xludf.dummyfunction("""COMPUTED_VALUE"""),"CASA CIVIL") | C57: =IFERROR(__xludf.dummyfunction("""COMPUTED_VALUE"""),"3º") | D57: =IFERROR(__xludf.dummyfunction("""COMPUTED_VALUE"""),"Coordenadoria Executiva") | E57: =IFERROR(__xludf.dummyfunction("""COMPUTED_VALUE"""),"Coordenador I") | F57: =IFERROR(__xludf.dummyfunction("""COMPUTED_VALUE"""),"Coordenador(a)") | G57: =IFERROR(__xludf.dummyfunction("""COMPUTED_VALUE"""),"Administrativo") | H57: =IFERROR(__xludf.dummyfunction("""COMPUTED_VALUE"""),"Gestão") | I57: #NAME? | J57: #NAME? | K57: #NAME? | L57: #NAME? | M57: #NAME? | N57: #NAME? | S57: #NAME? | T57: #NAME? | U57: #NAME? | V57: #NAME? | W57: #NAME? | X57: #NAME? | Y57: 0 | Z57: Não | AA57: 0 | AB57: Baixa | AD57: {=IFERROR(ifs( F57 = "Secretário(a)", INDEX(Secretario, MATCH(RIGHT(AC57), premissas_nivel_cargo_letra, 0), MATCH(VALUE(LEFT(AC57)), premissas_nivel_cargo_numero, 0)), F57 = "Presidente", INDEX(Presidente, MATCH(RIGHT(AC57), premissas_nivel_cargo_letra, 0), MATCH(VALUE(LEFT(AC57)), premissas_nivel_cargo_numero, 0)), F57 = "Subsecretário(a)", INDEX(Subsecretario, MATCH(RIGHT(AC57), premissas_nivel_cargo_letra, 0), MATCH(VALUE(LEFT(AC57)), premissas_nivel_cargo_numero, 0)), F57 = "Superintendente", INDEX(Superintendente, MATCH(RIGHT(AC57), premissas_nivel_cargo_letra, 0), MATCH(VALUE(LEFT(AC57)), premissas_nivel_cargo_numero, 0)), F57 = "Coordenador(a)", INDEX(Coordenador, MATCH(RIGHT(AC57), premissas_nivel_cargo_letra, 0), MATCH(VALUE(LEFT(AC57)), premissas_nivel_cargo_numero, 0)), F57 = "Chefe", INDEX(Chefe, MATCH(RIGHT(AC57), premissas_nivel_cargo_letra, 0), MATCH(VALUE(LEFT(AC57)), premissas_nivel_cargo_numero, 0)), F57 = "Diretor(a)", INDEX(Diretor, MATCH(RIGHT(AC57), premissas_nivel_cargo_letra, 0), MATCH(VALUE(LEFT(AC57)), premissas_nivel_cargo_numero, 0)), F57 = "Gerente", INDEX(Gerente, MATCH(RIGHT(AC57), premissas_nivel_cargo_letra, 0), MATCH(VALUE(LEFT(AC57)), premissas_nivel_cargo_numero, 0)), F57 = "Assessor(a)", INDEX(Assessor, MATCH(RIGHT(AC57), premissas_nivel_cargo_letra, 0), MATCH(VALUE(LEFT(AC57)), premissas_nivel_cargo_numero, 0)), F57 = "Ouvidor(a)", INDEX(Ouvidor, MATCH(RIGHT(AC57), premissas_nivel_cargo_letra, 0), MATCH(VALUE(LEFT(AC57)), premissas_nivel_cargo_numero, 0)) ), "")} | AE57: =ifs(G57 = "", "", AD57 = "", "Ainda Não Classificado", NOT(AD57 = ""), "Classificado com Sucesso")
A58: =IFERROR(__xludf.dummyfunction("""COMPUTED_VALUE"""),57) | B58: =IFERROR(__xludf.dummyfunction("""COMPUTED_VALUE"""),"CASA CIVIL") | C58: =IFERROR(__xludf.dummyfunction("""COMPUTED_VALUE"""),"2º") | D58: =IFERROR(__xludf.dummyfunction("""COMPUTED_VALUE"""),"Coordenadoria Geral de Gestão Institucional") | E58: =IFERROR(__xludf.dummyfunction("""COMPUTED_VALUE"""),"Coordenador Geral") | F58: =IFERROR(__xludf.dummyfunction("""COMPUTED_VALUE"""),"Coordenador(a)") | G58: =IFERROR(__xludf.dummyfunction("""COMPUTED_VALUE"""),"Administrativo") | H58: =IFERROR(__xludf.dummyfunction("""COMPUTED_VALUE"""),"Gestão") | I58: #NAME? | J58: #NAME? | K58: #NAME? | L58: #NAME? | M58: #NAME? | N58: #NAME? | S58: #NAME? | T58: #NAME? | U58: #NAME? | V58: #NAME? | W58: #NAME? | X58: #NAME? | Y58: 0 | Z58: Não | AA58: 0 | AB58: Baixa | AD58: {=IFERROR(ifs( F58 = "Secretário(a)", INDEX(Secretario, MATCH(RIGHT(AC58), premissas_nivel_cargo_letra, 0), MATCH(VALUE(LEFT(AC58)), premissas_nivel_cargo_numero, 0)), F58 = "Presidente", INDEX(Presidente, MATCH(RIGHT(AC58), premissas_nivel_cargo_letra, 0), MATCH(VALUE(LEFT(AC58)), premissas_nivel_cargo_numero, 0)), F58 = "Subsecretário(a)", INDEX(Subsecretario, MATCH(RIGHT(AC58), premissas_nivel_cargo_letra, 0), MATCH(VALUE(LEFT(AC58)), premissas_nivel_cargo_numero, 0)), F58 = "Superintendente", INDEX(Superintendente, MATCH(RIGHT(AC58), premissas_nivel_cargo_letra, 0), MATCH(VALUE(LEFT(AC58)), premissas_nivel_cargo_numero, 0)), F58 = "Coordenador(a)", INDEX(Coordenador, MATCH(RIGHT(AC58), premissas_nivel_cargo_letra, 0), MATCH(VALUE(LEFT(AC58)), premissas_nivel_cargo_numero, 0)), F58 = "Chefe", INDEX(Chefe, MATCH(RIGHT(AC58), premissas_nivel_cargo_letra, 0), MATCH(VALUE(LEFT(AC58)), premissas_nivel_cargo_numero, 0)), F58 = "Diretor(a)", INDEX(Diretor, MATCH(RIGHT(AC58), premissas_nivel_cargo_letra, 0), MATCH(VALUE(LEFT(AC58)), premissas_nivel_cargo_numero, 0)), F58 = "Gerente", INDEX(Gerente, MATCH(RIGHT(AC58), premissas_nivel_cargo_letra, 0), MATCH(VALUE(LEFT(AC58)), premissas_nivel_cargo_numero, 0)), F58 = "Assessor(a)", INDEX(Assessor, MATCH(RIGHT(AC58), premissas_nivel_cargo_letra, 0), MATCH(VALUE(LEFT(AC58)), premissas_nivel_cargo_numero, 0)), F58 = "Ouvidor(a)", INDEX(Ouvidor, MATCH(RIGHT(AC58), premissas_nivel_cargo_letra, 0), MATCH(VALUE(LEFT(AC58)), premissas_nivel_cargo_numero, 0)) ), "")} | AE58: =ifs(G58 = "", "", AD58 = "", "Ainda Não Classificado", NOT(AD58 = ""), "Classificado com Sucesso")
A59: =IFERROR(__xludf.dummyfunction("""COMPUTED_VALUE"""),58) | B59: =IFERROR(__xludf.dummyfunction("""COMPUTED_VALUE"""),"CASA CIVIL") | C59: =IFERROR(__xludf.dummyfunction("""COMPUTED_VALUE"""),"3º") | D59: =IFERROR(__xludf.dummyfunction("""COMPUTED_VALUE"""),"Assessoria de Gestão Institucional") | E59: =IFERROR(__xludf.dummyfunction("""COMPUTED_VALUE"""),"Assessor Chefe") | F59: =IFERROR(__xludf.dummyfunction("""COMPUTED_VALUE"""),"Assessor(a)") | G59: =IFERROR(__xludf.dummyfunction("""COMPUTED_VALUE"""),"Administrativo") | H59: =IFERROR(__xludf.dummyfunction("""COMPUTED_VALUE"""),"Gestão") | I59: #NAME? | J59: #NAME? | K59: #NAME? | L59: #NAME? | M59: #NAME? | N59: #NAME? | S59: #NAME? | T59: #NAME? | U59: #NAME? | V59: #NAME? | W59: #NAME? | X59: #NAME? | Y59: 0 | Z59: Não | AA59: 0 | AB59: Baixa | AD59: {=IFERROR(ifs( F59 = "Secretário(a)", INDEX(Secretario, MATCH(RIGHT(AC59), premissas_nivel_cargo_letra, 0), MATCH(VALUE(LEFT(AC59)), premissas_nivel_cargo_numero, 0)), F59 = "Presidente", INDEX(Presidente, MATCH(RIGHT(AC59), premissas_nivel_cargo_letra, 0), MATCH(VALUE(LEFT(AC59)), premissas_nivel_cargo_numero, 0)), F59 = "Subsecretário(a)", INDEX(Subsecretario, MATCH(RIGHT(AC59), premissas_nivel_cargo_letra, 0), MATCH(VALUE(LEFT(AC59)), premissas_nivel_cargo_numero, 0)), F59 = "Superintendente", INDEX(Superintendente, MATCH(RIGHT(AC59), premissas_nivel_cargo_letra, 0), MATCH(VALUE(LEFT(AC59)), premissas_nivel_cargo_numero, 0)), F59 = "Coordenador(a)", INDEX(Coordenador, MATCH(RIGHT(AC59), premissas_nivel_cargo_letra, 0), MATCH(VALUE(LEFT(AC59)), premissas_nivel_cargo_numero, 0)), F59 = "Chefe", INDEX(Chefe, MATCH(RIGHT(AC59), premissas_nivel_cargo_letra, 0), MATCH(VALUE(LEFT(AC59)), premissas_nivel_cargo_numero, 0)), F59 = "Diretor(a)", INDEX(Diretor, MATCH(RIGHT(AC59), premissas_nivel_cargo_letra, 0), MATCH(VALUE(LEFT(AC59)), premissas_nivel_cargo_numero, 0)), F59 = "Gerente", INDEX(Gerente, MATCH(RIGHT(AC59), premissas_nivel_cargo_letra, 0), MATCH(VALUE(LEFT(AC59)), premissas_nivel_cargo_numero, 0)), F59 = "Assessor(a)", INDEX(Assessor, MATCH(RIGHT(AC59), premissas_nivel_cargo_letra, 0), MATCH(VALUE(LEFT(AC59)), premissas_nivel_cargo_numero, 0)), F59 = "Ouvidor(a)", INDEX(Ouvidor, MATCH(RIGHT(AC59), premissas_nivel_cargo_letra, 0), MATCH(VALUE(LEFT(AC59)), premissas_nivel_cargo_numero, 0)) ), "")} | AE59: =ifs(G59 = "", "", AD59 = "", "Ainda Não Classificado", NOT(AD59 = ""), "Classificado com Sucesso")
A60: =IFERROR(__xludf.dummyfunction("""COMPUTED_VALUE"""),59) | B60: =IFERROR(__xludf.dummyfunction("""COMPUTED_VALUE"""),"CASA CIVIL") | C60: =IFERROR(__xludf.dummyfunction("""COMPUTED_VALUE"""),"3º") | D60: =IFERROR(__xludf.dummyfunction("""COMPUTED_VALUE"""),"Coordenadoria de Modelagem Organizacional") | E60: =IFERROR(__xludf.dummyfunction("""COMPUTED_VALUE"""),"Coordenador I") | F60: =IFERROR(__xludf.dummyfunction("""COMPUTED_VALUE"""),"Coordenador(a)") | G60: =IFERROR(__xludf.dummyfunction("""COMPUTED_VALUE"""),"Administrativo") | H60: =IFERROR(__xludf.dummyfunction("""COMPUTED_VALUE"""),"Gestão") | I60: #NAME? | J60: #NAME? | K60: #NAME? | L60: #NAME? | M60: #NAME? | N60: #NAME? | S60: #NAME? | T60: #NAME? | U60: #NAME? | V60: #NAME? | W60: #NAME? | X60: #NAME? | Y60: 0 | Z60: Não | AA60: 0 | AB60: Baixa | AD60: {=IFERROR(ifs( F60 = "Secretário(a)", INDEX(Secretario, MATCH(RIGHT(AC60), premissas_nivel_cargo_letra, 0), MATCH(VALUE(LEFT(AC60)), premissas_nivel_cargo_numero, 0)), F60 = "Presidente", INDEX(Presidente, MATCH(RIGHT(AC60), premissas_nivel_cargo_letra, 0), MATCH(VALUE(LEFT(AC60)), premissas_nivel_cargo_numero, 0)), F60 = "Subsecretário(a)", INDEX(Subsecretario, MATCH(RIGHT(AC60), premissas_nivel_cargo_letra, 0), MATCH(VALUE(LEFT(AC60)), premissas_nivel_cargo_numero, 0)), F60 = "Superintendente", INDEX(Superintendente, MATCH(RIGHT(AC60), premissas_nivel_cargo_letra, 0), MATCH(VALUE(LEFT(AC60)), premissas_nivel_cargo_numero, 0)), F60 = "Coordenador(a)", INDEX(Coordenador, MATCH(RIGHT(AC60), premissas_nivel_cargo_letra, 0), MATCH(VALUE(LEFT(AC60)), premissas_nivel_cargo_numero, 0)), F60 = "Chefe", INDEX(Chefe, MATCH(RIGHT(AC60), premissas_nivel_cargo_letra, 0), MATCH(VALUE(LEFT(AC60)), premissas_nivel_cargo_numero, 0)), F60 = "Diretor(a)", INDEX(Diretor, MATCH(RIGHT(AC60), premissas_nivel_cargo_letra, 0), MATCH(VALUE(LEFT(AC60)), premissas_nivel_cargo_numero, 0)), F60 = "Gerente", INDEX(Gerente, MATCH(RIGHT(AC60), premissas_nivel_cargo_letra, 0), MATCH(VALUE(LEFT(AC60)), premissas_nivel_cargo_numero, 0)), F60 = "Assessor(a)", INDEX(Assessor, MATCH(RIGHT(AC60), premissas_nivel_cargo_letra, 0), MATCH(VALUE(LEFT(AC60)), premissas_nivel_cargo_numero, 0)), F60 = "Ouvidor(a)", INDEX(Ouvidor, MATCH(RIGHT(AC60), premissas_nivel_cargo_letra, 0), MATCH(VALUE(LEFT(AC60)), premissas_nivel_cargo_numero, 0)) ), "")} | AE60: =ifs(G60 = "", "", AD60 = "", "Ainda Não Classificado", NOT(AD60 = ""), "Classificado com Sucesso")
A61: =IFERROR(__xludf.dummyfunction("""COMPUTED_VALUE"""),60) | B61: =IFERROR(__xludf.dummyfunction("""COMPUTED_VALUE"""),"CASA CIVIL") | C61: =IFERROR(__xludf.dummyfunction("""COMPUTED_VALUE"""),"3º") | D61: =IFERROR(__xludf.dummyfunction("""COMPUTED_VALUE"""),"Coordenadoria de Controle Organizacional") | E61: =IFERROR(__xludf.dummyfunction("""COMPUTED_VALUE"""),"Coordenador I") | F61: =IFERROR(__xludf.dummyfunction("""COMPUTED_VALUE"""),"Coordenador(a)") | G61: =IFERROR(__xludf.dummyfunction("""COMPUTED_VALUE"""),"Administrativo") | H61: =IFERROR(__xludf.dummyfunction("""COMPUTED_VALUE"""),"Gestão") | I61: #NAME? | J61: #NAME? | K61: #NAME? | L61: #NAME? | M61: #NAME? | N61: #NAME? | S61: #NAME? | T61: #NAME? | U61: #NAME? | V61: #NAME? | W61: #NAME? | X61: #NAME? | Y61: 0 | Z61: Não | AA61: 0 | AB61: Baixa | AD61: {=IFERROR(ifs( F61 = "Secretário(a)", INDEX(Secretario, MATCH(RIGHT(AC61), premissas_nivel_cargo_letra, 0), MATCH(VALUE(LEFT(AC61)), premissas_nivel_cargo_numero, 0)), F61 = "Presidente", INDEX(Presidente, MATCH(RIGHT(AC61), premissas_nivel_cargo_letra, 0), MATCH(VALUE(LEFT(AC61)), premissas_nivel_cargo_numero, 0)), F61 = "Subsecretário(a)", INDEX(Subsecretario, MATCH(RIGHT(AC61), premissas_nivel_cargo_letra, 0), MATCH(VALUE(LEFT(AC61)), premissas_nivel_cargo_numero, 0)), F61 = "Superintendente", INDEX(Superintendente, MATCH(RIGHT(AC61), premissas_nivel_cargo_letra, 0), MATCH(VALUE(LEFT(AC61)), premissas_nivel_cargo_numero, 0)), F61 = "Coordenador(a)", INDEX(Coordenador, MATCH(RIGHT(AC61), premissas_nivel_cargo_letra, 0), MATCH(VALUE(LEFT(AC61)), premissas_nivel_cargo_numero, 0)), F61 = "Chefe", INDEX(Chefe, MATCH(RIGHT(AC61), premissas_nivel_cargo_letra, 0), MATCH(VALUE(LEFT(AC61)), premissas_nivel_cargo_numero, 0)), F61 = "Diretor(a)", INDEX(Diretor, MATCH(RIGHT(AC61), premissas_nivel_cargo_letra, 0), MATCH(VALUE(LEFT(AC61)), premissas_nivel_cargo_numero, 0)), F61 = "Gerente", INDEX(Gerente, MATCH(RIGHT(AC61), premissas_nivel_cargo_letra, 0), MATCH(VALUE(LEFT(AC61)), premissas_nivel_cargo_numero, 0)), F61 = "Assessor(a)", INDEX(Assessor, MATCH(RIGHT(AC61), premissas_nivel_cargo_letra, 0), MATCH(VALUE(LEFT(AC61)), premissas_nivel_cargo_numero, 0)), F61 = "Ouvidor(a)", INDEX(Ouvidor, MATCH(RIGHT(AC61), premissas_nivel_cargo_letra, 0), MATCH(VALUE(LEFT(AC61)), premissas_nivel_cargo_numero, 0)) ), "")} | AE61: =ifs(G61 = "", "", AD61 = "", "Ainda Não Classificado", NOT(AD61 = ""), "Classificado com Sucesso")
A62: =IFERROR(__xludf.dummyfunction("""COMPUTED_VALUE"""),61) | B62: =IFERROR(__xludf.dummyfunction("""COMPUTED_VALUE"""),"CASA CIVIL") | C62: =IFERROR(__xludf.dummyfunction("""COMPUTED_VALUE"""),"3º") | D62: =IFERROR(__xludf.dummyfunction("""COMPUTED_VALUE"""),"Coordenadoria de Gestão do Sistema Integrado de Codificação Institucional") | E62: =IFERROR(__xludf.dummyfunction("""COMPUTED_VALUE"""),"Coordenador I") | F62: =IFERROR(__xludf.dummyfunction("""COMPUTED_VALUE"""),"Coordenador(a)") | G62: =IFERROR(__xludf.dummyfunction("""COMPUTED_VALUE"""),"Administrativo") | H62: =IFERROR(__xludf.dummyfunction("""COMPUTED_VALUE"""),"Gestão") | I62: #NAME? | J62: #NAME? | K62: #NAME? | L62: #NAME? | M62: #NAME? | N62: #NAME? | S62: #NAME? | T62: #NAME? | U62: #NAME? | V62: #NAME? | W62: #NAME? | X62: #NAME? | Y62: 0 | Z62: Não | AA62: 0 | AB62: Baixa | AD62: {=IFERROR(ifs( F62 = "Secretário(a)", INDEX(Secretario, MATCH(RIGHT(AC62), premissas_nivel_cargo_letra, 0), MATCH(VALUE(LEFT(AC62)), premissas_nivel_cargo_numero, 0)), F62 = "Presidente", INDEX(Presidente, MATCH(RIGHT(AC62), premissas_nivel_cargo_letra, 0), MATCH(VALUE(LEFT(AC62)), premissas_nivel_cargo_numero, 0)), F62 = "Subsecretário(a)", INDEX(Subsecretario, MATCH(RIGHT(AC62), premissas_nivel_cargo_letra, 0), MATCH(VALUE(LEFT(AC62)), premissas_nivel_cargo_numero, 0)), F62 = "Superintendente", INDEX(Superintendente, MATCH(RIGHT(AC62), premissas_nivel_cargo_letra, 0), MATCH(VALUE(LEFT(AC62)), premissas_nivel_cargo_numero, 0)), F62 = "Coordenador(a)", INDEX(Coordenador, MATCH(RIGHT(AC62), premissas_nivel_cargo_letra, 0), MATCH(VALUE(LEFT(AC62)), premissas_nivel_cargo_numero, 0)), F62 = "Chefe", INDEX(Chefe, MATCH(RIGHT(AC62), premissas_nivel_cargo_letra, 0), MATCH(VALUE(LEFT(AC62)), premissas_nivel_cargo_numero, 0)), F62 = "Diretor(a)", INDEX(Diretor, MATCH(RIGHT(AC62), premissas_nivel_cargo_letra, 0), MATCH(VALUE(LEFT(AC62)), premissas_nivel_cargo_numero, 0)), F62 = "Gerente", INDEX(Gerente, MATCH(RIGHT(AC62), premissas_nivel_cargo_letra, 0), MATCH(VALUE(LEFT(AC62)), premissas_nivel_cargo_numero, 0)), F62 = "Assessor(a)", INDEX(Assessor, MATCH(RIGHT(AC62), premissas_nivel_cargo_letra, 0), MATCH(VALUE(LEFT(AC62)), premissas_nivel_cargo_numero, 0)), F62 = "Ouvidor(a)", INDEX(Ouvidor, MATCH(RIGHT(AC62), premissas_nivel_cargo_letra, 0), MATCH(VALUE(LEFT(AC62)), premissas_nivel_cargo_numero, 0)) ), "")} | AE62: =ifs(G62 = "", "", AD62 = "", "Ainda Não Classificado", NOT(AD62 = ""), "Classificado com Sucesso")
